Workbook

Sheet Tabla de contenido
A2: ESTANDARES Y CRITERIOS - AUTOEVALUCION 3100-2019
A3: RAZON SOCIAL: CLÍNICA LAS PEÑITAS S.A.S. MUNICIPIO: Sincelejo, Sucre (Cra. 25 No. 23-26, Av. Las Peñitas) SERVICIOS A PRESTAR: Servicio farmacéutico (mediana/alta complejidad, modalidad intramural). Estándares 11.1.1 a 11.1.7 evaluados desde el servicio farmacéutico. Elaborado Por: __________________________________ (BORRADOR - pendiente de verificación con evidencias)
A6: ESTANDARES Y CRITERIOS - AUTOEVALUCION 3100-2019 | B6: Servicio | C6: Páginas
A7: 11.1. ESTÁNDARES Y CRITERIOS APLICABLES A TODOS LOS SERVICIOS | B7: 11.1.1 TALENTO HUMANO | C7: 59 -61
B8: 11.1.2. INFRAESTRUCTURA | C8: 61 - 68
B9: 11.1.3. DOTACIÓN | C9: 68 - 71
B10: 11.1.4. MEDICAMENTOS, DISPOSITIVOS MÉDICOS E INSUMOS | C10: 71 - 73
B11: 11.1.5. PROCESOS PRIORITARIOS | C11: 73 - 77
B12: 11.1.6. HISTORIA CLÍNICA Y REGISTROS | C12: 77 - 79
B13: 11.1.7. INTERDEPENDENCIA | C13: 79
A14: 11.2. GRUPO CONSULTA EXTERNA | B14: 11.2.1. SERVICIO DE CONSULTA EXTERNA GENERAL | C14: 80-84
B15: 11.2.2. SERVICIO DE CONSULTA EXTERNA ESPECIALIZADA | C15: 85-88
B16: 11.2.3. SERVICIO DE VACUNACIÓN | C16: 88-91
B17: 11.2.4. SERVICIO DE SEGURIDAD Y SALUD EN EL TRABAJO | C17: 91-93
A18: 11.3. GRUPO APOYO DIAGNÓSTICO Y COMPLEMENTACIÓN TERAPÉUTICA | B18: 11.3.1. SERVICIO DE TERAPIAS | C18: 94-97
B19: 11.3.2. SERVICIO FARMACÉUTICO | C19: 97-101
B20: 11.3.3 SERVICIO DE RADIOLOGiA ODONTOLÓGICA | C20: 101-103
B21: 11.3.4 SERVICIO DE IMÁGENES DIAGNÓSTICAS | C21: 103-104
B22: 11.3.5 SERVICIO DE MEDICINA NUCLEAR | C22: 112-115
B23: 11.3.6 SERVICIO DE RADIOTERAPIA | C23: 116-119
B24: 11.3.7 SERVICIO DE QUIMIOTERAPIA | C24: 119-123
B25: 11.3.8 SERVICIO DE DIAGNÓSTICO VASCULAR | C25: 123-125
B26: 11.3.9 SERVICIO DE HEMODINAMIA E INTERVENCIONISMO | C26: 125-128
B27: 11.3.10 SERVICIO DE GESTIÓN PRE TRANSFUSIONAL | C27: 129-130
B28: 11.3.11. SERVICIO DE TOMA DE MUESTRAS DE LABORATORIO CLÍNICO
B29: 11.3.12 SERVICIO DE LABORATORIO CLÍNICO | C29: 132-135
B30: 11.3.13 SERVICIO DE TOMA DE MUESTRAS DE CUELLO UTERINO Y GINECOLÓGICAS | C30: 135-137
B31: 11.3.14 SERVICIO DE LABORATORIO DE CITOLOGiAS CERVICO-UTERINAS | C31: 137-138
B32: 11.3.15 SERVICIO DE LABORATORIO DE HISTOTECNOLOGIA | C32: 138-139
B33: 11.3.16 SERVICIO DE PATOLOGÍA | C33: 140-142
B34: 11.3.17 SERVICIO DE DIÁLISIS | C34: 142-146
A35: 11.4 GRUPO INTERNACIÓN | B35: 11.4.1 SERVICIO DE HOSPITALIZACIÓN | C35: 146-154
B36: 11.4.2 SERVICIO DE HOSPITALIZACIÓN PACIENTE CRÓNICO | C36: 154-162
B37: 11.4.3 SERVICIO DE CUIDADO BÁSICO NEONATAL | C37: 162-165
B38: 11.4.4 SERVICIO DE CUIDADO INTERMEDIO NEONATAL | C38: 165-168
B39: 11.4.5 SERVICIO DE CUIDADO INTENSIVO NEONATAL | C39: 168-172
B40: 11.4.6 SERVICIO DE CUIDADO INTERMEDIO PEDIÁTRICO | C40: 172-175
B41: 11.4.7 SERVICIO DE CUIDADO INTENSIVO PEDIÁTRICO | C41: 175-179
B42: 11.4.8 SERVICIO DE CUIDADO INTERMEDIO ADULTO | C42: 179-182
B43: 11.4.9 SERVICIO DE CUIDADO INTENSIVO ADULTOS | C43: 182-186
B44: 11.4.10 SERVICIO DE HOSPITALIZACIÓN EN SALUD MENTAL O CONSUMO DE SUSTANCIAS PSICOACTIVAS | C44: 186-190
B45: 11.4.11 SERVICIO DE HOSPITALIZACIÓN PARCIAL | C45: 190-195
B46: 11.4.12 SERVICIO PARA EL CUIDADO BÁSICO DEL CONSUMO DE SUSTANCIAS PSICOACTIVAS | C46: 195-199
A47: 11.5 GRUPO QUIRÚRGICO | B47: 11.5.1 SERVICIO DE CIRUGÍA | C47: 199-206
A48: 11.6 GRUPO ATENCIÓN INMEDIATA | B48: 11.6.1 SERVICIO DE URGENCIAS | C48: 206-213
B49: 11.6.2 SERVICIO DE TRANSPORTE ASISTENCIAL | C49: 213-222
B50: 11.6.3 SERVICIO ATENCIÓN PREHOSPITALARIA | C50: 222-225
B51: 11.6.4 SERVICIO PARA LA ATENCIÓN DEL PARTO | C51: 225-230

Sheet Revisión final SF
A1: PREAUDITORÍA DE HABILITACIÓN – SERVICIO FARMACÉUTICO – CLÍNICA LAS PEÑITAS S.A.S. (Sincelejo)
A2: Alcance | B2: Estándares 11.1.1 a 11.1.7 evaluados exclusivamente desde el Servicio Farmacéutico, y estándar específico 11.3.2 SF. Revisión documental de las respuestas registradas en el archivo; no incluye visita de campo.
A3: Base de la revisión | B3: Las respuestas evaluadas son el borrador de autoevaluación elaborado sin acceso a documentos ni registros de la clínica. Describen la evidencia que debería existir, no evidencia aportada. Por eso ningún criterio puede calificarse como "Cumple" en esta etapa.
A4: Correspondencia con la columna Estado | B4: Cumple → C | Cumple parcialmente, No cumple y No evidenciado → NC | No aplica → NA. El concepto completo está en la columna E "Concepto preauditoría (QF)" de cada hoja.
A5: Advertencia | B5: Este archivo es un instrumento de preauditoría interna. No debe radicarse como autoevaluación oficial: la columna Estado refleja la falta de evidencia, no necesariamente el incumplimiento real.
A7: RESULTADO POR ESTÁNDAR
A8: Talento humano | B8: No evidenciado: 6 | No aplica: 15 | Cumple: 0 | Cumple parcialmente: 0 | No cumple: 0
A9: Infraestructura | B9: No evidenciado: 40 | No aplica: 129 | Cumple: 0 | Cumple parcialmente: 0 | No cumple: 0
A10: Dotación | B10: No evidenciado: 11 | No aplica: 40 | Cumple: 0 | Cumple parcialmente: 0 | No cumple: 0
A11: Medicamentos, DM e insumos | B11: No evidenciado: 46 | No aplica: 5 | Cumple: 0 | Cumple parcialmente: 0 | No cumple: 0
A12: Procesos prioritarios | B12: No evidenciado: 22 | No aplica: 69 | Cumple: 0 | Cumple parcialmente: 0 | No cumple: 0
A13: Historia clínica y registros | B13: No evidenciado: 6 | No aplica: 45 | Cumple: 0 | Cumple parcialmente: 0 | No cumple: 0
A14: Interdependencia | B14: No evidenciado: 0 | No aplica: 5 | Cumple: 0 | Cumple parcialmente: 0 | No cumple: 0
A15: 11.3.2 Servicio farmacéutico | B15: No evidenciado: 24 | No aplica: 14 | Cumple: 0 | Cumple parcialmente: 0 | No cumple: 0
A17: 1. RESPUESTAS QUE DEBEN CORREGIRSE
A18: MD – Criterio 13 (convenio banco de sangre) | B18: Estaba en C. No corresponde al SF: la sangre y sus componentes no se gestionan en farmacia. Corregido a NA.
A19: MD – Criterio 15 (kit agentes químicos) | B19: Estaba en C. Se exige a transporte asistencial, APH y urgencias, no al SF. Corregido a NA.
A20: DOT – Criterio 15 (empaque cerrado sucio/limpio) | B20: Estaba en C. Se refiere a elementos sucios y limpios de los servicios quirúrgicos, de internación y de urgencias; el transporte de medicamentos se evalúa en MD 4.3. Corregido a NA.
A21: DOT – Criterios 1.1 a 1.6 (equipos biomédicos) | B21: La respuesta trata neveras, termohigrómetros y aire acondicionado como equipos biomédicos. Debe precisarse qué equipos del SF son biomédicos; el control de los demás equipos se soporta en el criterio 9 del SF.
A22: SF – Criterio 5.4 (almacenamiento) | B22: Fija rangos genéricos de temperatura y humedad; el criterio exige las condiciones del fabricante de cada producto. Reformular indicando los rangos definidos por producto y el control aplicado.
A23: INF – Criterios 8, 10, 11 / PP – 12.7 | B23: Respuestas condicionales ("si… marcar NA"). Una autoevaluación debe afirmar la condición real: indicar el piso donde funciona el SF, si hay ascensor o rampa, y quién gestiona los gases medicinales.
A24: Calificaciones NA basadas en supuestos | B24: TH 4.1-4.3 (práctica formativa), INF 3, 5-5.4, 6, 7, 9.1-9.4 y 38-40 (edificación y atención al público), MD 14 (fabricación de gases) y PP 16.1-16.3 (reúso de DM). Deben confirmarse con información real antes de sostener el NA.
A25: Complejidad del SF | B25: Toda la evaluación supone mediana/alta complejidad. Debe confirmarse en REPS; define el perfil del talento humano, las áreas y la exigencia de dosis unitaria (SF criterios 1, 7, 13 y 17).
A27: 2. RESPUESTAS QUE REQUIEREN EVIDENCIA DOCUMENTAL (prioridad alta)
A28: Talento humano SF | B28: Hojas de vida del QF director técnico, regentes y auxiliares: títulos, tarjeta profesional, ReTHUS, certificados de aptitud ocupacional, inducción, reinducción y capacitación. Estudio de cargas y cuadros de turno 24 h.
A29: Medicamentos de control especial | B29: Resolución vigente del Fondo Rotatorio de Estupefacientes de Sucre, libro oficial actualizado, informes mensuales y procedimiento.
A30: Cadena de frío y condiciones ambientales | B30: Registros de temperatura y humedad (farmacia, bodega, stocks, neveras), certificados de calibración de termohigrómetros, plan de contingencia y evidencia de acciones ante desviaciones.
A31: Procesos generales del SF | B31: Manual de procesos y procedimientos bajo control documental firmado por el QF: selección, adquisición, recepción, almacenamiento, distribución, dispensación, devolución, disposición final.
A32: Comité de Farmacia y Terapéutica | B32: Acto de conformación, actas y listado básico de medicamentos aprobado.
A33: Farmacovigilancia y tecnovigilancia | B33: Programas, inscripción en las redes del INVIMA, referente designado y reportes realizados.
A34: Seguridad en el uso de medicamentos | B34: Listados de alto riesgo y LASA, doble verificación, conciliación, reporte y análisis de errores de medicación con planes de mejora.
A35: Registros sanitarios | B35: Consulta en INVIMA, con fecha, sobre una muestra de medicamentos y dispositivos médicos.
A36: Recepción técnica y disposición final | B36: Actas de recepción diligenciadas, contrato con gestor de residuos peligrosos y actas de destrucción.
A37: Carros de paro | B37: Listado aprobado según morbilidad y listas de chequeo diligenciadas.
A39: 3. CRITERIOS QUE REQUIEREN VERIFICACIÓN EN CAMPO
A40: Áreas del SF (SF 5.1-5.8) | B40: Delimitación y señalización de administración, recepción, dispensación, almacenamiento, control especial, rechazados/devueltos, vencidos y cuarentena.
A41: Condiciones locativas | B41: Pisos, paredes y techos lavables, sin humedad; ventilación y aire acondicionado; circulación libre; uso de estibas.
A42: Almacenamiento | B42: Separación de piso y paredes, segregación de alto riesgo y LASA con señalización, rotación FEFO, ausencia de vencidos en estanterías y stocks.
A43: Control especial | B43: Mueble o área con seguridad y acceso restringido; cuadre del inventario físico contra el libro oficial.
A44: Cadena de frío | B44: Neveras exclusivas, termómetro o data logger, temperatura actual dentro de 2-8 °C, respaldo con planta eléctrica.
A45: Instrumentos de medición | B45: Un termohigrómetro por área, con etiqueta de calibración vigente.
A46: Dispensación | B46: Aviso de prohibición de asesoría farmacológica visible; verificación de dos identificadores en una muestra de dispensaciones.
A47: Kit de derrames y carros de paro | B47: Existencia, ubicación y contenido del kit; revisión al azar de carros de paro.
A48: Registros | B48: Diligenciamiento oportuno, legible, con fecha, hora y firma; sin llenado retroactivo.
A50: 4. PRINCIPALES HALLAZGOS
A51: H1. Ausencia de evidencia | B51: Ninguna respuesta aporta evidencia verificable (documento, registro, foto o dato). Todas describen lo que debería existir. Estado actual: 155 criterios "No evidenciado" y 0 "Cumple".
A52: H2. Complejidad no confirmada | B52: La calificación de los criterios de mediana/alta complejidad del SF se basa en un supuesto.
A53: H3. Alcance del SF no definido | B53: No se define si el SF atiende pacientes ambulatorios, qué procesos especiales realiza (dosis unitaria, reempaque) ni si gestiona gases medicinales y reactivos; esto afecta la aplicabilidad de varios criterios.
A54: H4. Criterios de otros servicios mal calificados | B54: Tres criterios de otros servicios estaban calificados como C para el SF (MD 13, MD 15, DOT 15); fueron corregidos a NA.
A55: H5. Criterios de alto riesgo sin soporte | B55: Control especial, cadena de frío, alto riesgo/LASA y registros sanitarios no tienen evidencia; son los que con mayor frecuencia generan observaciones en la visita.
A56: H6. Interdependencia | B56: Correctamente en NA: la Res. 3100/2019 no asigna servicios interdependientes al SF (criterios 21 y 22), y la clínica no hace mezclas.
A58: 5. RECOMENDACIONES DE AJUSTE
A59: Cómo redactar cada respuesta | B59: Reemplazar "Verificar evidencia: …" por una afirmación con su soporte: qué existe, nombre y código del documento, fecha o vigencia, dónde se encuentra y registro de implementación. Ej.: "Procedimiento de recepción técnica PR-SF-003 v2 (mar-2026); actas de recepción diligenciadas en formato FR-SF-010, archivadas en farmacia."
A60: Diferenciar documento de implementación | B60: Para cada proceso, citar el procedimiento Y al menos un registro reciente de ejecución (acta, formato, reporte).
A61: Confirmar aplicabilidad | B61: Confirmar en REPS la complejidad y las modalidades del SF, y definir el alcance (ambulatorio, dosis unitaria, gases, reactivos) antes de sostener cualquier NA.
A62: Priorizar | B62: 1) Control especial y cadena de frío; 2) talento humano del SF; 3) alto riesgo/LASA y errores de medicación; 4) áreas del SF; 5) resto de procesos y registros.
A63: Carpeta de evidencias | B63: Organizar una carpeta por estándar con los soportes referenciados en cada respuesta, para presentarla en la visita de verificación.
A64: Revalidar | B64: Una vez completadas las respuestas con evidencia real, repetir esta preauditoría para asignar Cumple / Cumple parcialmente / No cumple.

Sheet Consolidado
B3: Estándares y criterios aplicables a todos los servicios | C3: Total criterios | D3: C | E3: NC | F3: NA | G3: Cumplimiento
B4: TS - Talento Humano | C4: 21 | D4: ='11.1.1TH'!C30 | E4: ='11.1.1TH'!C31 | F4: ='11.1.1TH'!C32 | G4: =D4/(C4-F4)
B5: TS - Infraestructura | C5: 167 | D5: ='11.1.2.INF'!C202 | E5: ='11.1.2.INF'!C203 | F5: ='11.1.2.INF'!C204 | G5: =D5/(C5-F5)
B6: TS - Dotación | C6: 52 | D6: ='11.1.3.DOT'!C68 | E6: ='11.1.3.DOT'!C69 | F6: ='11.1.3.DOT'!C70 | G6: =D6/(C6-F6)
B7: TS - Medicamentos, dispositivos médicos e insumos | C7: 51 | D7: ='11.1.4MD'!C65 | E7: ='11.1.4MD'!C66 | F7: ='11.1.4MD'!C67 | G7: =D7/(C7-F7)
B8: TS - Procesos prioritarios | C8: 91 | D8: ='11.1.5.PP'!C115 | E8: ='11.1.5.PP'!C116 | F8: ='11.1.5.PP'!C117 | G8: =D8/(C8-F8)
B9: TS - Historia clinica y registros | C9: 50 | D9: ='11.1.6.HCR'!C64 | E9: ='11.1.6.HCR'!C65 | F9: ='11.1.6.HCR'!C66 | G9: =D9/(C9-F9)
B10: TS - Interdependencia | C10: 5 | D10: ='11.1.7INT'!C12 | E10: ='11.1.7INT'!C13 | F10: ='11.1.7INT'!C14 | G10: =D10/(C10-F10)
B23: Grupo consulta externa | C23: Total criterios | D23: C | E23: NC | F23: NA | G23: Cumplimiento
B24: Servicio de consulta externa general | C24: 95 | D24: ='11.2.1.S_CE_G'!C161 | E24: ='11.2.1.S_CE_G'!C162 | F24: ='11.2.1.S_CE_G'!C163 | G24: =D24/(C24-F24)
B25: Servicio de consulta externa especializada | C25: 39 | D25: ='11.2.2.S_CE_E'!C94 | E25: ='11.2.2.S_CE_E'!C95 | F25: ='11.2.2.S_CE_E'!C96 | G25: =D25/(C25-F25)
B26: Servicio de vacunación | C26: 57 | D26: ='11.2.3.S_CE_V'!C84 | E26: ='11.2.3.S_CE_V'!C85 | F26: ='11.2.3.S_CE_V'!C86 | G26: =D26/(C26-F26)
B27: Servicio de seguridad y salud en el trabajo | C27: 29 | D27: ='11.2.4.S_CE_SST'!C56 | E27: ='11.2.4.S_CE_SST'!C57 | F27: ='11.2.4.S_CE_SST'!C58 | G27: =D27/(C27-F27)
B40: Grupo apoyo diagnóstico y complementación terapéutica | C40: Total criterios | D40: C | E40: NC | F40: NA | G40: Cumplimiento
B41: Servicio de terapias | C41: 44 | D41: ='11.3.1.S_TR'!C80 | E41: ='11.3.1.S_TR'!C81 | F41: ='11.3.1.S_TR'!C82 | G41: =D41/(C41-F41)
B42: Servicio farmacéutico | C42: 38 | D42: =' 11.3.2.SF'!C74 | E42: =' 11.3.2.SF'!C75 | F42: =' 11.3.2.SF'!C76 | G42: =D42/(C42-F42)
B43: Servicio de radiología odontológica | C43: 44 | D43: ='11.3.3.S_Rx_OD'!C72 | E43: ='11.3.3.S_Rx_OD'!C73 | F43: ='11.3.3.S_Rx_OD'!C74 | G43: =D43/(C43-F43)
B44: Servicio de imágenes diagnósticas | C44: =88+31 | D44: ='11.3.4.S_IDx'!C218 | E44: ='11.3.4.S_IDx'!C219 | F44: ='11.3.4.S_IDx'!C220 | G44: =D44/(C44-F44)
B45: Servicio de medicina nuclear | C45: 63 | D45: =' 11.3.5.S_MNuc'!C102 | E45: =' 11.3.5.S_MNuc'!C103 | F45: =' 11.3.5.S_MNuc'!C104 | G45: =D45/(C45-F45)
B46: Servicio de radioterapia | C46: 82 | D46: ='11.3.6.S_Radio'!C118 | E46: ='11.3.6.S_Radio'!C119 | F46: ='11.3.6.S_Radio'!C120 | G46: =D46/(C46-F46)
B47: Servicio de quimioterapia | C47: 80 | D47: ='11.3.7.S_Quimio'!C110 | E47: ='11.3.7.S_Quimio'!C111 | F47: ='11.3.7.S_Quimio'!C112 | G47: =D47/(C47-F47)
B48: Servicio de diagnóstico vascular 1 | C48: 33 | D48: ='11.3.8 S_Dx VASC'!C56 | E48: ='11.3.8 S_Dx VASC'!C57 | F48: ='11.3.8 S_Dx VASC'!C58 | G48: =D48/(C48-F48)
B49: Servicio de diagnóstico vascular 2 | C49: 33 | D49: ='11.3.8 S_Dx VASC'!#REF! | E49: ='11.3.8 S_Dx VASC'!#REF! | F49: ='11.3.8 S_Dx VASC'!#REF! | G49: =D49/(C49-F49)
B50: Servicio de diagnóstico vascular 3 | C50: 33 | D50: ='11.3.8 S_Dx VASC'!#REF! | E50: ='11.3.8 S_Dx VASC'!#REF! | F50: ='11.3.8 S_Dx VASC'!#REF! | G50: =D50/(C50-F50)
B51: Servicio de diagnóstico vascular 4 | C51: 33 | D51: ='11.3.8 S_Dx VASC'!#REF! | E51: ='11.3.8 S_Dx VASC'!#REF! | F51: ='11.3.8 S_Dx VASC'!#REF! | G51: =D51/(C51-F51)
B52: Servicio de diagnóstico vascular 5 | C52: 33 | D52: ='11.3.8 S_Dx VASC'!#REF! | E52: ='11.3.8 S_Dx VASC'!#REF! | F52: ='11.3.8 S_Dx VASC'!#REF! | G52: =D52/(C52-F52)
B53: Servicio de diagnóstico vascular 6 | C53: 33 | D53: ='11.3.8 S_Dx VASC'!#REF! | E53: ='11.3.8 S_Dx VASC'!#REF! | F53: ='11.3.8 S_Dx VASC'!#REF! | G53: =D53/(C53-F53)
B54: Servicio de diagnóstico vascular 7 | C54: 33 | D54: ='11.3.8 S_Dx VASC'!#REF! | E54: ='11.3.8 S_Dx VASC'!#REF! | F54: ='11.3.8 S_Dx VASC'!#REF! | G54: =D54/(C54-F54)
B55: Servicio de hemodinamia e intervencionismo | C55: 91 | D55: ='11.3.9S_HI'!C119 | E55: ='11.3.9S_HI'!C120 | F55: ='11.3.9S_HI'!C121 | G55: =D55/(C55-F55)
B56: Servicio de gestión pre transfusional | C56: 40 | D56: ='11.3.10 S_GPT'!C50 | E56: ='11.3.10 S_GPT'!C51 | F56: ='11.3.10 S_GPT'!C52 | G56: =D56/(C56-F56)
B57: Servicio de toma de muestras de laboratorio clínico | C57: 29 | D57: ='11.3.11.S_TMLC'!C48 | E57: ='11.3.11.S_TMLC'!C49 | F57: ='11.3.11.S_TMLC'!C50 | G57: =D57/(C57-F57)
B58: Servicio de laboratorio clínico | C58: 59 | D58: ='11.3.12.S_LC'!C81 | E58: ='11.3.12.S_LC'!C82 | F58: ='11.3.12.S_LC'!C83 | G58: =D58/(C58-F58)
B59: Servicio de toma de muestras de cuello uterino y ginecológicas | C59: 42 | D59: =' 11.3.13 S_TM_CU'!C60 | E59: =' 11.3.13 S_TM_CU'!C61 | F59: =' 11.3.13 S_TM_CU'!C62 | G59: =D59/(C59-F59)
B60: Servicio de laboratorio de citologías cérvico-uterinas | C60: 32 | D60: ='11.3.14.S_LCU'!C55 | E60: ='11.3.14.S_LCU'!C56 | F60: ='11.3.14.S_LCU'!C57 | G60: =D60/(C60-F60)
B61: Servicio de laboratorio de histotecnología | C61: 33 | D61: ='11.3.15.S_LHT'!C46 | E61: ='11.3.15.S_LHT'!C47 | F61: ='11.3.15.S_LHT'!C48 | G61: =D61/(C61-F61)
B62: Servicio de patología | C62: 51 | D62: ='11.3.16.S_LPT'!C75 | E62: ='11.3.16.S_LPT'!C76 | F62: ='11.3.16.S_LPT'!C77 | G62: =D62/(C62-F62)
B63: Servicio de diálisis | C63: 100 | D63: ='11.3.17.S_Dial'!C127 | E63: ='11.3.17.S_Dial'!C128 | F63: ='11.3.17.S_Dial'!C129 | G63: =D63/(C63-F63)
B66: Grupo de internación | C66: Total criterios | D66: C | E66: NC | F66: NA | G66: Cumplimiento
B67: Servicio de hospitalización | C67: 183 | D67: ='11.4.1.S_HP'!C266 | E67: ='11.4.1.S_HP'!C267 | F67: ='11.4.1.S_HP'!C268 | G67: =D67/(C67-F67)
B68: Servicio de hospitalización paciente crónico | C68: 167 | D68: ='11.4.2.S_HP_PC'!C247 | E68: ='11.4.2.S_HP_PC'!C248 | F68: ='11.4.2.S_HP_PC'!C249 | G68: =D68/(C68-F68)
B69: Servicio de cuidado básico neonatal | C69: 67 | D69: ='11.4.3.S_CBN'!C91 | E69: ='11.4.3.S_CBN'!C92 | F69: ='11.4.3.S_CBN'!C93 | G69: =D69/(C69-F69)
B70: Servicio de cuidado intermedio neonatal | C70: 88 | D70: ='11.4.4.S_CIN '!C113 | E70: ='11.4.4.S_CIN '!C114 | F70: ='11.4.4.S_CIN '!C115 | G70: =D70/(C70-F70)
B71: Servicio de cuidado intensivo neonatal | C71: 119 | D71: ='11.4.5.S_CINN'!C144 | E71: ='11.4.5.S_CINN'!C145 | F71: ='11.4.5.S_CINN'!C146 | G71: =D71/(C71-F71)
B72: Servicio de cuidado intermedio pediátrico | C72: 85 | D72: ='11.4.6. S_CINP'!C114 | E72: ='11.4.6. S_CINP'!C115 | F72: ='11.4.6. S_CINP'!C116 | G72: =D72/(C72-F72)
B73: Servicio de cuidado intensivo pediátrico | C73: 112 | D73: ='11.4.7.S_CIP'!C140 | E73: ='11.4.7.S_CIP'!C141 | F73: ='11.4.7.S_CIP'!C142 | G73: =D73/(C73-F73)
B74: Servicio de cuidado intermedio adulto | C74: 82 | D74: ='11.4.8.S_CIMA'!C111 | E74: ='11.4.8.S_CIMA'!C112 | F74: ='11.4.8.S_CIMA'!C113 | G74: =D74/(C74-F74)
B75: Servicio de cuidado intensivo adultos | C75: 97 | D75: ='11.4.9.S_CIA'!C126 | E75: ='11.4.9.S_CIA'!C127 | F75: ='11.4.9.S_CIA'!C128 | G75: =D75/(C75-F75)
B76: Servicio de hospitalización en salud mental o consumo de sustancias psicoactivas | C76: 104 | D76: ='11.4.10.S_HSM CSP'!C138 | E76: ='11.4.10.S_HSM CSP'!C139 | F76: ='11.4.10.S_HSM CSP'!C140 | G76: =D76/(C76-F76)
B77: Servicio de hospitalización parcial | C77: 127 | D77: ='11.4.11.S_HSP'!C176 | E77: ='11.4.11.S_HSP'!C177 | F77: ='11.4.11.S_HSP'!C178 | G77: =D77/(C77-F77)
B78: Servicio para el cuidado básico del consumo de sustancias psicoactivas | C78: 86 | D78: ='11.4.12.S_CB_CSP'!C116 | E78: ='11.4.12.S_CB_CSP'!C117 | F78: ='11.4.12.S_CB_CSP'!C118 | G78: =D78/(C78-F78)
B90: Grupo quirúrgico | C90: Total criterios | D90: C | E90: NC | F90: NA | G90: Cumplimiento
B91: Servicio de cirugía | C91: 189 | D91: ='11.5.1.S_CX'!C239 | E91: ='11.5.1.S_CX'!C240 | F91: ='11.5.1.S_CX'!C241 | G91: =D91/(C91-F91)
B106: Grupo atención inmediata | C106: Total criterios | D106: C | E106: NC | F106: NA | G106: Cumplimiento
B107: Servicio de urgencias | C107: 197 | D107: ='11.6.1.S_UR'!C249 | E107: ='11.6.1.S_UR'!C250 | F107: ='11.6.1.S_UR'!C251 | G107: =D107/(C107-F107)
B108: Servicio de transporte asistencial | C108: 208 | D108: ='11.6.2.S_TR_AS'!C288 | E108: ='11.6.2.S_TR_AS'!C289 | F108: ='11.6.2.S_TR_AS'!C290 | G108: =D108/(C108-F108)
B109: Servicio atención prehospitalaria | C109: 74 | D109: ='11.6.3.S_AT_PH'!C100 | E109: ='11.6.3.S_AT_PH'!C101 | F109: ='11.6.3.S_AT_PH'!C102 | G109: =D109/(C109-F109)
B110: Servicio para la atención del parto | C110: 169 | D110: ='11.6.4.S_A.parto'!C219 | E110: ='11.6.4.S_A.parto'!C220 | F110: ='11.6.4.S_A.parto'!C221 | G110: =D110/(C110-F110)

Sheet 11.1.1TH
B1: VOLVER A TABLA DE CONTENIDO
B2: Estandar de Talento Humano
A3: Estandar | B3: Criterios | C3: Estado | D3: Comentarios | E3: Concepto preauditoría (QF)
A4: TSTH | B4: 1. El talento humano en salud y otros profesionales que se relacionan con la atención o resultados en salud de los usuarios, cuentan con los titulos, según aplique, de educación superior o certificados de aptitud ocupacional, expedidos por la entidad educativa competente. En el caso de títulos o certificados obtenidos en el extranjero, copia de la resolución de convalidación expedida por el Ministerio de Educación Nacional | C4: NC | D4: La respuesta enumera los cargos (QF director técnico, regentes, auxiliares) pero no aporta hojas de vida, diplomas ni certificados de aptitud ocupacional. No permite verificar que el perfil de cada cargo cumpla lo exigido para el SF; se requieren los soportes académicos de todo el personal del servicio. | E4: No evidenciado
A5: TSTH | B5: 2. El talento humano en salud cuenta con copia de la resolución de autorización del ejercicio expedido por la autoridad competente o inscripción e en el ReTHUS | C5: NC | D5: Se menciona la consulta en ReTHUS sin relacionar nombres ni resultados. Se requiere el listado del personal del SF con su número de inscripción en ReTHUS o resolución de autorización del ejercicio, y la copia en cada hoja de vida. | E5: No evidenciado
A6: TSTH | B6: 3. El prestador de servicios de salud determina la cantidad necesaria de talento humano requerido para cada uno de los servicios ofertados y prestados, de acuerdo con la capacidad instalada, la relación entre la oferta y demanda, la oportunidad en la prestación, tiempo de la atención y el riesgo en la atención. Este criterio no aplica para profesionales independientes de salud | C6: NC | D6: La respuesta describe qué debería contener el estudio de cargas, pero no evidencia que exista ni su resultado. No permite verificar la cobertura 24 h del SF para hospitalización y urgencias ni la disponibilidad del QF. Se requieren el documento de suficiencia de talento humano del SF y los cuadros de turno. | E6: No evidenciado
A7: TSTH | B7: 4. El prestador de servicios de salud que actúe como escenario de práctica formativa en el área de la salud, cuenta con:
A8: TSTH | B8: 4.1. Convenio vigente con la institución educativa autorizada por la entidad competente | C8: NC | D8: La calificación NA se basa en un supuesto (que el SF no es escenario de práctica), no en información confirmada. Debe verificarse si hay estudiantes (QF, regencia de farmacia, SENA) en el SF; si los hay, se requieren convenio docencia-servicio vigente, mecanismo de supervisión y estudio de capacidad. | E8: No evidenciado
A9: TSTH | B9: 4.2. Información documentada de los mecanismos de supervisión permanente del personal en entrnamiento | C9: NC | D9: La calificación NA se basa en un supuesto (que el SF no es escenario de práctica), no en información confirmada. Debe verificarse si hay estudiantes (QF, regencia de farmacia, SENA) en el SF; si los hay, se requieren convenio docencia-servicio vigente, mecanismo de supervisión y estudio de capacidad. | E9: No evidenciado
A10: TSTH | B10: 4.3. Estudio de la capacidad instalada en el cual se dtermine el número máximo de estudiantes que simultaneamente puedan acceder por programa de formación y por jornada, para cada uno de los servicios que se utilicen como escenarios de práctica formativa en el área de la salud, estudio que debe ser elaborado teniendo en cuenta los "lineamientos de referencia para la asignación de cupos de estudiantes en escenarios clinicos" publicados por el Ministerio de Salud y Protección Social | C10: NC | D10: La calificación NA se basa en un supuesto (que el SF no es escenario de práctica), no en información confirmada. Debe verificarse si hay estudiantes (QF, regencia de farmacia, SENA) en el SF; si los hay, se requieren convenio docencia-servicio vigente, mecanismo de supervisión y estudio de capacidad. | E10: No evidenciado
A11: TSTH | B11: 5. En los servicios de salud diferentes a los servicios de consulta externa especializada de dolor y cuidado paliativo, donde se atienden pacientes con enfermedades terminales, crónicas, degenerativas e irreversibles, a los cuales se les decida como conducta médica: como parte del plan integral de cuidado que gestiona el equipo de salud, o por solicitud del paciente; el manejo de dolor y cuidado paliativo, el profesional en medicina tratante cuenta con constancia de asistencia en las acciones de formación continua en el manejo de dolor y cuidado paliativo, cuando no sea especialista en dolor y cuidado paliativo | C11: NA | D11: No aplica al servicio farmacéutico: dirigido a profesionales de medicina tratantes en manejo de dolor y cuidado paliativo. | E11: No aplica
A12: TSTH | B12: 6. El talento humano en salud de los servicios de atención del parto, cuidado intensivo y cuidado intermedio neonatal, pediátrico y adultos, cuentan con constancia de asistencia en las acciones de formación continua para la gestión del duelo | C12: NA | D12: No aplica al servicio farmacéutico: dirigido al talento humano de atención del parto y cuidado intensivo/intermedio (gestión del duelo). | E12: No aplica
A13: TSTH | B13: 7. En los servicios de salud donde se realicen imagenes diagnósticas por ultrasonido, cuenta con médico especialista en radiologia e imagenes diagnósticas también podrán realizar imagenes diagnósticas aquellos médicos especialistas, quienes en su pensum o formación académica hayan adquirido los conocimientos del manejo e interpretación del espectro electromagnetico, del ultrasonido especialmente, así como de la radiaciones ionizantes para establecer el diagnóstico o el tratamiento de las enfermedades inherentes a su especialidad, para lo cual deberá acreditar el respectivo certificado. | C13: NA | D13: No aplica al servicio farmacéutico: aplica a servicios de imágenes diagnósticas por ultrasonido. | E13: No aplica
A14: TSTH | B14: 8. Los profesionales de la medicina de los servicios de hospitalización de baja, mediana y alta complejidad, hospitalización paciente crónico con y sin ventilador, cuidados intensivos neonatales, pediátricos y adultos; urgencias, y servicios del grupo quirurgico en modalidad intramural,cuentan con certificación vigente de aprobación de la evaluación de competencias esenciales para el cuidado de la donante expedida por el Instituto Nacional de Salud. | C14: NA | D14: No aplica al servicio farmacéutico: dirigido a profesionales de medicina de hospitalización, UCI, urgencias y cirugía (competencias en cuidado del donante - INS). | E14: No aplica
A15: TSTH | B15: 9. Las instituciones prestadoras de servicios de salud con servicios de cuidado intensivo pediatrico y adulto que adicionalmente habiliten servicio quirurgico de neurocirugía, tienen disponibilidad de coordinador operativo de trasplantes. | C15: NA | D15: No aplica al servicio farmacéutico: aplica a IPS con UCI y neurocirugía (coordinador operativo de trasplantes). | E15: No aplica
A16: TSTH | B16: 10. El talento humano en salud de los servicios de salud de los grupos de consulta externa, internación y el servicio de urgencias, cuentan con constancia de asistencia en las acciones de formación continua en la atención integral en salud de las personas victimas de violencia sexual. | C16: NA | D16: No aplica al servicio farmacéutico: dirigido a consulta externa, internación y urgencias (atención a víctimas de violencia sexual). El SF sí debe garantizar la disponibilidad del kit de profilaxis post-exposición. | E16: No aplica
A17: TSTH | B17: 11. El talento humano en salud de los servicios de transporte asistencial, atención prehospitalaria y urgencias, cuentasn con constancia de asistencia en las acciones de formación continua en la atención a personas víctimas de ataques con agentes químicos. | C17: NA | D17: No aplica al servicio farmacéutico: dirigido a transporte asistencial, APH y urgencias (víctimas de agentes químicos). | E17: No aplica
A18: TSTH | B18: 12. Cuando en un servicio de salud se realicen "pruebas en punto de atención del paciente - (point of care testing - POCT)", el talento humano en salud qeu las realice, a excepción del profesional en bacteriologia cuenta con constancia de asistencia en las acciones de formación continua en la atención a personas víctimas de ataques con agentes químicos. | C18: NA | D18: No aplica al servicio farmacéutico: en la farmacia no se realizan pruebas en punto de atención (POCT). | E18: No aplica
A19: TSTH | B19: 13. Procedimientos bajo sedación:
A20: TSTH | B20: 13.1 Cuando fuera de salas de cirugía, se realicen procedimientos bajo sedación Grado I y II, adicional al profesional de salud que realiza el procedimiento, cuenta con:
A21: TSTH | B21: 13.1.1. Profesional en la medicina especialista en anestesiologia, o profesional de la medicina o profesional en odontologia, según aplique, el cual será el encargado de administrar el medicamento y realizar el monitoreo continuo del paciente (registro de signos vitales y la respuesta a la sedación) | C21: NA | D21: No aplica al servicio farmacéutico: en la farmacia no se realizan procedimientos bajo sedación. | E21: No aplica
A22: TSTH | B22: 13.1.2. Todos los profesionales, a excepción del profesional de la medicina especialista en anestesiologia, deben demostrar constancia de asistencia a curso de formación continua en soporte vital básico y sedación | C22: NA | D22: No aplica al servicio farmacéutico: en la farmacia no se realizan procedimientos bajo sedación. | E22: No aplica
A23: TSTH | B23: 13.1.3 Para sedacción con óxido nitroso en odontologia, el profesional de la odontología cuenta con constancia de asistencia en las acciones de formación continua para uso clínico y práctico de este gas. | C23: NA | D23: No aplica al servicio farmacéutico: en la farmacia no se realizan procedimientos bajo sedación. | E23: No aplica
A24: TSTH | B24: 13.2. Cuando fuera de las salas de cirugia, se realicen procedimientos bajo sedación grado III, adicional al profesional de salud que realiza el procedimiento, cuenta con profesional de la medicina con especialidad médico - quirúrgica, quién será el responsable de administrar la sedación | C24: NA | D24: No aplica al servicio farmacéutico: en la farmacia no se realizan procedimientos bajo sedación. | E24: No aplica
A25: TSTH | B25: 13.3. Cuando fuera de las salas de cirugía, se realicen procedimientos bajo sedación grado IV, adicional al profesional de salud que realiza el procedimiento, cuenta con profesional de la medicina especialisa en anestesiologia, quién será el responsable de administrar la sedación | C25: NA | D25: No aplica al servicio farmacéutico: en la farmacia no se realizan procedimientos bajo sedación. | E25: No aplica
A26: TSTH | B26: 13.4 Cuenta con profesional de la medicina especialista en anestesiologia cuando la atención de trate de pacientes con caracteristicas particulares: poco colaboradores; edades extremas; con enfermedades severas:cardíacas, pulmonares, hepáticas, renales o del sistema nervioso central;cualquier alteración del grado de consciencia, con obesidad mórbida, con apnea del sueño, embarazadas, o quienes abusan del alcohol o de las drogas; antecedentes de sedación fallida o que presentaron efectos adversos a algún medicamento utilizado en la sedación, por tener un elevado riesgo de desarrollar complicaciones relacionadas con la sedación analgesia | C26: NA | D26: No aplica al servicio farmacéutico: en la farmacia no se realizan procedimientos bajo sedación. | E26: No aplica
A27: TSTH | B27: Modalidad de telemedicina prestador remisor - prestador de referencia
A28: TSTH | B28: 14. Adicional a los criterios del estándar de talento humano enunciados que le aplique, el talento humano en salud que preste directamente un servicio de salud bajo la modalidad telemedicina cuentan con constancia de asistencia en las acciones de formación continua en el manejo de tecnología utilizada por el prestador, los procesos y herramientas inherentes a la prestación de servicios bajo esta modalidad | C28: NA | D28: No aplica: el servicio farmacéutico no está habilitado en modalidad telemedicina (verificar en el REPS). | E28: No aplica
B30: CUMPLE | C30: =COUNTIF($C$4:$C$28,"C")
B31: NO CUMPLE | C31: =COUNTIF($C$4:$C$28,"NC")
B32: NO APLICA | C32: =COUNTIF($C$4:$C$28,"NA")

Sheet 11.1.2.INF
B1: VOLVER A TABLA DE CONTENIDO
B2: Estandar de Infraestructura
A3: Estandar | B3: Criterios | C3: Estado | D3: Comentarios | E3: Concepto preauditoría (QF)
A4: TSINF | B4: Edificaciones de uso exclusivo en salud
A5: TSINF | B5: 1. Los servicios de salud de urgencias, de atención del parto, hospitalarios y de cirugía que realicen procedimientos quirúrgicos no ambulatorios, solo se pueden prestar en edificaciones de uso exclusivo de salud. | C5: NC | D5: La respuesta afirma uso exclusivo en salud sin aportar certificado de uso del suelo ni licencia de construcción. Es un criterio de la edificación que condiciona al SF; debe verificarse con el documento correspondiente. | E5: No evidenciado
A6: TSINF | B6: 2. Los servicios de salud de: urgencias, cirugía y del grupo de internación, así como en los servicios de salud donde se realice el proceso de esterilización, deben contar con ambiente de aseo de uso exclusivo | C6: NA | D6: No aplica al servicio farmacéutico: el ambiente de aseo exclusivo se exige a urgencias, cirugía, internación y esterilización. Verificar que la farmacia tenga acceso a cuarto de aseo con insumos propios. | E6: No aplica
A7: TSINF | B7: 3. Cuando en una edificación de uso exclusivo de salud funcione más de un prestador de servicios de salud con servicios de los grupos de consulta externa y apoyo diagnóstico y complementación terapeutica, cada prestador cuenta con infraestructura separada delimitada fisicamente. Se pueden compartir los siguientes ambientes y áreas: aseo, salas de espera y unidades sanitarias. | C7: NC | D7: El NA supone un único prestador en la edificación, sin evidencia que lo confirme. Verificar en REPS y en campo que no funcionen otros prestadores (p. ej. farmacias o laboratorios de terceros) en la misma edificación. | E7: No evidenciado
A8: TSINF | B8: 4. Las edificaciones donde se presten servicios de salud de urgencias y del grupo de internación, cuentan con tanque de almacenamientode agua para el consumo humano que garantice como mínimo una reserva de 24 horas de servicio continuo, calculando con base en el consumo de 600 lt por cama/camilla al día. | C8: NC | D8: No se aportan el cálculo de reserva de 24 h ni los certificados de lavado y desinfección del tanque. La información no permite verificar el criterio; requiere soporte documental y verificación física. | E8: No evidenciado
A9: TSINF | B9: 5. Cuando el prestador de servicios de salud cuente con mas de una infraestructura y estas se puedan vincular funcionalmente entre si, lo harán mediante tunel o puente cubierto, o muro(s) colindante(s) que cuenten con acceso (s) que intercomuniquen las infraestructuras, de uso exclusivo del prestador y adicionalmente cumplen con las siguientes caracteristicas: | C9: NC | D9: El NA se basa en el supuesto de una sola infraestructura, sin confirmar. Debe verificarse en REPS si la clínica tiene sedes o edificaciones vinculadas funcionalmente; si existen y el SF abastece entre ellas, el criterio aplica. | E9: No evidenciado
A10: TSINF | B10: 5.1. Ancho que permita la movilización de camas, camillas, sillas de ruedas, equipos biomédicos y personal para el traslado de los pacientes en condiciones seguras. | C10: NC | D10: El NA se basa en el supuesto de una sola infraestructura, sin confirmar. Debe verificarse en REPS si la clínica tiene sedes o edificaciones vinculadas funcionalmente; si existen y el SF abastece entre ellas, el criterio aplica. | E10: No evidenciado
A11: TSINF | B11: 5.2. El piso del túnel o puente debe ser uniforme y de material antideslizante o con elementos que garanticen esta propiedad en todo su recorrido, con pasamanos d a ambos lados y con protecciones laterales hacia espacios libres. | C11: NC | D11: El NA se basa en el supuesto de una sola infraestructura, sin confirmar. Debe verificarse en REPS si la clínica tiene sedes o edificaciones vinculadas funcionalmente; si existen y el SF abastece entre ellas, el criterio aplica. | E11: No evidenciado
A12: TSINF | B12: 5.3. Lo anterior siempre y cuando la norma urbanística de la jurisdicción donde se localizan las sedes hayan aprobado esta forma de vinculación funcional entre las mismas. | C12: NC | D12: El NA se basa en el supuesto de una sola infraestructura, sin confirmar. Debe verificarse en REPS si la clínica tiene sedes o edificaciones vinculadas funcionalmente; si existen y el SF abastece entre ellas, el criterio aplica. | E12: No evidenciado
A13: TSINF | B13: 5.4. Esta edificación se podrá habilitar como una o varias sedes, de acuerdo con lo que determine el prestador de servicios de salud | C13: NC | D13: El NA se basa en el supuesto de una sola infraestructura, sin confirmar. Debe verificarse en REPS si la clínica tiene sedes o edificaciones vinculadas funcionalmente; si existen y el SF abastece entre ellas, el criterio aplica. | E13: No evidenciado
A14: TSINF | B14: Edificaciones de uso mixto
A15: TSINF | B15: 6. Cuando en una edificación de uso mixto funcione más de un prestador de servicios de salud, cada uno cuenta con infraestructura separada y delimitada físicamente. Se pueden compartir las salas de espera y las unidades sanitarias. | C15: NC | D15: El NA depende de confirmar el uso exclusivo en salud (criterio 1), que no está evidenciado. Verificar junto con ese criterio. | E15: No evidenciado
A16: TSINF | B16: 7. En edificaciones de uso mixto pueden funsionar los prestadores de servicios de salud que oferten y presten servicios de los grupos de consulta externa. de apoyo diagnóstico y complementación terapeutica y los servicios del grupo quirurgico que realicen exclusivamente procedimientos de cirugia ambulatoria. | C16: NC | D16: El NA depende de confirmar el uso exclusivo en salud (criterio 1), que no está evidenciado. Verificar junto con ese criterio. | E16: No evidenciado
A17: TSINF | B17: Edificaciones de uso exclusivo en salud y edificaciones de uso mixto
A18: TSINF | B18: 8. Los prestadores de servicios de salud ubicados en edificaciones de hasta tres (3) pisos o niveles contados a partir del nivel más bajo construido, y que funcione en segundo o tercer nivel o piso, cuentan con ascensor o rampa o sistema alternativo de elevación. El sistema alternativo de elevación no puede ser utilizado cuando se presten servicios hospitalarios, cirugía, urgencias o de atención del parto. | C18: NC | D18: La respuesta es condicional ('si... marcar NA') y no indica en qué piso funciona el SF ni si hay ascensor o rampa. Debe precisarse la ubicación del SF y verificarse en campo el medio de acceso para el traslado de medicamentos e insumos. | E18: No evidenciado
A19: TSINF | B19: 9. Los sistemas alternativos de elevación deben cumplir con las siguientes condiciones:
A20: TSINF | B20: 9.1. Su ubicación no interfiera con el acceso y evacuación de los usuarios por las escaleras | C20: NC | D20: El NA supone que no se usan sistemas alternativos de elevación, sin confirmarlo. Verificar en campo; si el acceso al SF o el traslado de medicamentos a otros pisos depende de uno, el criterio aplica. | E20: No evidenciado
A21: TSINF | B21: 9.2. Estén disponibles tanto para el acceso como para la evacuación de los usuarios | C21: NC | D21: El NA supone que no se usan sistemas alternativos de elevación, sin confirmarlo. Verificar en campo; si el acceso al SF o el traslado de medicamentos a otros pisos depende de uno, el criterio aplica. | E21: No evidenciado
A22: TSINF | B22: 9.3. Su manejo sea autonomo | C22: NC | D22: El NA supone que no se usan sistemas alternativos de elevación, sin confirmarlo. Verificar en campo; si el acceso al SF o el traslado de medicamentos a otros pisos depende de uno, el criterio aplica. | E22: No evidenciado
A23: TSINF | B23: 9.4. Garanticen seguridad durante su uso | C23: NC | D23: El NA supone que no se usan sistemas alternativos de elevación, sin confirmarlo. Verificar en campo; si el acceso al SF o el traslado de medicamentos a otros pisos depende de uno, el criterio aplica. | E23: No evidenciado
A24: TSINF | B24: 10. Las edificaciones con más de tres (3) pisos o niveles, contados a partir del nivel más bajo construido, cuentan con ascensor. | C24: NC | D24: Respuesta condicional; no informa el número de pisos de la edificación. Debe precisarse y verificarse en campo la existencia del ascensor si la edificación supera tres pisos. | E24: No evidenciado
A25: TSINF | B25: 11. En edificaciones donde se presten servicios de los grupos de internación, atención del parto, quirurgicos o urgencias para la movilización de pacientes en camilla, la cabina de los ascensores debe tener las dimensiones interiores mínimas de 2.20 de profundidad y de 1.20 ancho, que garanticen el traslado seguro de los pacientes. Las dimensiones de la cabina podrán ser variables en el o los ascensores que el prestador determine para la movilización de usuarios a pie o en silla de ruedas. | C25: NC | D25: Respuesta condicional; no informa si hay ascensor ni las dimensiones de la cabina. Es un criterio de la edificación, no específico del SF; debe verificarse en campo con medición. | E25: No evidenciado
A26: TSINF | B26: 12. Si se tienen escaleras o rampas, el piso debe ser uniforme y de material antideslizante o con elementos que garanticen esta propiedad en todo su recorrido, con pasamanos de preferencia a ambos lados y con protecciones laterales hacia espacios libres. | C26: NC | D26: Afirmación sin evidencia. Requiere verificación física de pisos antideslizantes, pasamanos y protecciones laterales en escaleras y rampas de acceso al SF. | E26: No evidenciado
A27: TSINF | B27: 13. Las edificaciones donde se presten servicios de salud cuentan con suministro de agua, energia eléctrica, conexión a la red de alcantarillado y sistemas de comunicaciones. | C27: NC | D27: No se aportan soportes de servicios públicos. Se verifica con recibos vigentes y observación en campo; debe confirmarse también la conectividad que requiere el software de inventario y dispensación del SF. | E27: No evidenciado
A28: TSINF | B28: 14. En edificaciones donde se presten servicios de cirugía, atención del parto, laboratorio clínico, urgencias, gestión pre transfusional, dialisis, hospitalarios, imagénes diagnósticas, vacunación, servicio farmaceutico y los que requieran cadena de frio, cuentan con planta electrica. | C28: NC | D28: Criterio crítico para el SF porque protege la cadena de frío. La respuesta no evidencia que exista la planta ni que cubra neveras y aire acondicionado de farmacia. Se requieren ficha técnica, identificación de los circuitos respaldados, registros de pruebas periódicas y mantenimiento. | E28: No evidenciado
A29: TSINF | B29: 15. El prestador de servicios de salud que utilice equipos generadores de radiaciones ionizantes cuenta con licencia de práctica médica vigente expedida por la entidad competente. | C29: NA | D29: No aplica al servicio farmacéutico: la licencia de práctica médica para radiaciones ionizantes aplica a imágenes diagnósticas; se evalúa en ese servicio. | E29: No aplica
A30: TSINF | B30: 16. El prestador de servicios de salud que utilice fuentes radiactivas cuenta con autorización vigente de empleo de material radiactivo, expedida por la entidad reguladora competente | C30: NA | D30: No aplica al servicio farmacéutico: la farmacia no utiliza fuentes radiactivas. | E30: No aplica
A31: TSINF | B31: 17. Cada prestador de servicios de salud debe contar con el respectivo concepto sanitario que dé cumplimiento a lo establecido en la normatividad sanitaria vigente en aspectos tales como agua para consumo humano, gestión de residuos, control de vectores, orden y aseo, condiciones locativas, entre otros. Este concepto será emitido por las autoridades sanitarias correspondientes, en el marco de sus competencias, y debe considerar los servicios de apoyo como lavanderia y servicio de alimentación. Cuando estos servicios de apoyo son contratados con terceros dichos proveedores deben contar con el concepto sanitario correspondiente a la actividad de bienes y servicios que presta. | C31: NC | D31: No se aporta el concepto sanitario ni su fecha. Debe verificarse que esté vigente, sea favorable y no tenga requerimientos pendientes relacionados con el SF o con la gestión de residuos de medicamentos. | E31: No evidenciado
A32: TSINF | B32: Generalidades de los ambientes y las áreas de los servicios y sus características
A33: TSINF | B33: 18. Las áreas y ambientes de todos los servicios de salud cuentan con ventilación natural o artificial. | C33: NC | D33: No se evidencia el tipo de ventilación del SF ni registros que demuestren control de temperatura. Verificar en campo el aire acondicionado y cruzarlo con los registros de temperatura del área. | E33: No evidenciado
A34: TSINF | B34: 19. Las áreas de circulación están libres de obstáculos de manera que permitan la movilización de pacientes, talento humano, usuarios y equipos biomédicos | C34: NC | D34: Solo puede confirmarse en campo. Hallazgo frecuente en farmacias: cajas en el piso o en pasillos que obstruyen la circulación; verificar el uso de estibas y que los pasillos estén libres. | E34: No evidenciado
A35: TSINF | B35: 20. Los ambientes y áreas que hagan parte de cualquier servicio de salud, deben permitir la instalación y movilización de equipos biomedicos y personal necesarios para la atención del paciente en condiciones de rutina o de emergencia. | C35: NC | D35: No se describen las dimensiones ni la distribución del SF. Debe verificarse en campo que los carros de distribución circulen sin obstáculos entre recepción, almacenamiento y dispensación. | E35: No evidenciado
A36: TSINF | B36: 21.En los servicios del grupo quirurgico, los ambientes y áreas clasificados como no restringidos, semirestringidos, deben señalizarse mediante la demarcación permanente en piso con material lavable y resistente al tráfico pesado, utilizando los siguientes colores | C36: NA | D36: No aplica al servicio farmacéutico: la demarcación por colores (verde, amarillo, rojo) aplica a los servicios del grupo quirúrgico. | E36: No aplica
A37: TSINF | B37: 21.1. Verde: Ambientes o áreas no restringidas | C37: NA | D37: No aplica al servicio farmacéutico: la demarcación por colores (verde, amarillo, rojo) aplica a los servicios del grupo quirúrgico. | E37: No aplica
A38: TSINF | B38: 21.2. Amarillo: Ambientes o áreas semi-restringidas | C38: NA | D38: No aplica al servicio farmacéutico: la demarcación por colores (verde, amarillo, rojo) aplica a los servicios del grupo quirúrgico. | E38: No aplica
A39: TSINF | B39: 21.3. Roja: Ambientes o áreas restringidas | C39: NA | D39: No aplica al servicio farmacéutico: la demarcación por colores (verde, amarillo, rojo) aplica a los servicios del grupo quirúrgico. | E39: No aplica
A40: TSINF | B40: 22. Cada uno de los pisos o niveles de la edificación cuenta con señalización y planos indicativos de las rutas de evacuación, salidas de emergencia y puntos de encuentro, visible al público en general. | C40: NC | D40: No se evidencian planos de evacuación ni señalización en el área del SF. Requiere verificación en campo. | E40: No evidenciado
A41: TSINF | B41: 23. Si el prestador de servicios de salud no tiene habilitado el servicio de gestión pre-transfusional, pero realiza procedimientos de transfusión sanguínea en alguno de sus servicios habilitados, tiene disponibilidad de un área con iluminación y ventilación natural o artificial, para la ubicación de la dotación requerida de acuerdo con los componentes sanguíneos a transfundir. | C41: NA | D41: No aplica al servicio farmacéutico: el área para transfusión aplica a los servicios donde se realizan transfusiones. | E41: No aplica
A42: TSINF | B42: 24. Cuando un prestador de servicios de salud realice procedimientos bajo sedación fuera de salas de cirugía, tiene disponibilidad de área o ambiente para la recuperación de pacientes que puede ser la misma área o ambiente donde se realiza el procedimiento, garantizando la privacidad del usuario. | C42: NA | D42: No aplica al servicio farmacéutico: en la farmacia no se realizan procedimientos bajo sedación. | E42: No aplica
A43: TSINF | B43: 25. El prestador de servicios de salud que realice el proceso de esterilización, cuenta con:
A44: TSINF | B44: 25.1. Ambiente o área de recibo de material contaminado. | C44: NA | D44: No aplica al servicio farmacéutico: en la farmacia no se realiza el proceso de esterilización. | E44: No aplica
A45: TSINF | B45: 25.2. Ambiente o área de lavado | C45: NA | D45: No aplica al servicio farmacéutico: en la farmacia no se realiza el proceso de esterilización. | E45: No aplica
A46: TSINF | B46: 25.3. Ambiente o área de secado | C46: NA | D46: No aplica al servicio farmacéutico: en la farmacia no se realiza el proceso de esterilización. | E46: No aplica
A47: TSINF | B47: 25.4. Ambiente o área de empaque. | C47: NA | D47: No aplica al servicio farmacéutico: en la farmacia no se realiza el proceso de esterilización. | E47: No aplica
A48: TSINF | B48: 25.5. Ambiente o área de esterilización | C48: NA | D48: No aplica al servicio farmacéutico: en la farmacia no se realiza el proceso de esterilización. | E48: No aplica
A49: TSINF | B49: 25.6. Ambiente o área para almacenamiento de material esteril | C49: NA | D49: No aplica al servicio farmacéutico: en la farmacia no se realiza el proceso de esterilización. | E49: No aplica
A50: TSINF | B50: 25.7. Mesón de trabajo con poceta | C50: NA | D50: No aplica al servicio farmacéutico: en la farmacia no se realiza el proceso de esterilización. | E50: No aplica
A51: TSINF | B51: 25.8. Lavamanos, cuando el proceso se realice fuera del servicio de salud | C51: NA | D51: No aplica al servicio farmacéutico: en la farmacia no se realiza el proceso de esterilización. | E51: No aplica
A52: TSINF | B52: 26. El prestador de servicios de salud que contrate el proceso de esterilización, dentro de su infraestructura cuenta con:
A53: TSINF | B53: 26.1. Ambiente o área para lavado, limpieza y desinfección y entrega de material limpio al proveedor | C53: NA | D53: No aplica al servicio farmacéutico: en la farmacia no se contrata el proceso de esterilización. | E53: No aplica
A54: TSINF | B54: 26.2. Ambiente o área para la recepción y almacenamiento del material esteril | C54: NA | D54: No aplica al servicio farmacéutico: en la farmacia no se contrata el proceso de esterilización. | E54: No aplica
A55: TSINF | B55: 27. El prestador de servicios de salud que realice el proceso de esterilización en una cetral de esterilización cuenta con los siguientes ambientes y áreas señalizadas unidireccionales y de circulación restringida.
A56: TSINF | B56: 27.1. Ambiente de recibo y lavado de material contaminado | C56: NA | D56: No aplica al servicio farmacéutico: la central de esterilización no hace parte del servicio farmacéutico. | E56: No aplica
A57: TSINF | B57: 27.2. Ambiente limpio con las siguientes áreas: | C57: NA | D57: No aplica al servicio farmacéutico: la central de esterilización no hace parte del servicio farmacéutico. | E57: No aplica
A58: TSINF | B58: 27.2.1. Área de secado | C58: NA | D58: No aplica al servicio farmacéutico: la central de esterilización no hace parte del servicio farmacéutico. | E58: No aplica
A59: TSINF | B59: 27.2.2. Área de empaque | C59: NA | D59: No aplica al servicio farmacéutico: la central de esterilización no hace parte del servicio farmacéutico. | E59: No aplica
A60: TSINF | B60: 27.2.3. Área de esterilización | C60: NA | D60: No aplica al servicio farmacéutico: la central de esterilización no hace parte del servicio farmacéutico. | E60: No aplica
A61: TSINF | B61: 27.3. Ambiente para almacenamiento de material esteril | C61: NA | D61: No aplica al servicio farmacéutico: la central de esterilización no hace parte del servicio farmacéutico. | E61: No aplica
A62: TSINF | B62: Caracteristicas de los ambientes y áreas que pueden ser requeridos en varios servicios de salud
A63: TSINF | B63: 28. Consultorio: para efectos del presente manual se definen los siguientes tipos de consultorios de acuerdo con la oferta de servicios:
A64: TSINF | B64: 28.1. Consultorio donde se realiza examen fisico: ambiente con mínimo 10 mt2 (sin incluir la unidad sanitaria) que cuenta con_ | C64: NA | D64: No aplica al servicio farmacéutico: la farmacia no cuenta con consultorios. | E64: No aplica
A65: TSINF | B65: 28.1.1. área para entrevista | C65: NA | D65: No aplica al servicio farmacéutico: la farmacia no cuenta con consultorios. | E65: No aplica
A66: TSINF | B66: 28.1.2. área de examen | C66: NA | D66: No aplica al servicio farmacéutico: la farmacia no cuenta con consultorios. | E66: No aplica
A67: TSINF | B67: 28.1.3. Lavamanos. No se exige adicional si el consultorio cuenta con unidad sanitaria | C67: NA | D67: No aplica al servicio farmacéutico: la farmacia no cuenta con consultorios. | E67: No aplica
A68: TSINF | B68: 28.1.4. Las áreas están separadas entre si por barrera física fija o móvil, con excepción de los consultorios del servicio de urgencias, optometría y oftalmologia, donde no se requiere. | C68: NA | D68: No aplica al servicio farmacéutico: la farmacia no cuenta con consultorios. | E68: No aplica
A69: TSINF | B69: 28.2. Consultorio donde se realizan procedimientos: ambiente mínimo de 10 m2 (sin incluir la unidad sanitaria) que cuenta con: | C69: NA | D69: No aplica al servicio farmacéutico: la farmacia no cuenta con consultorios. | E69: No aplica
A70: TSINF | B70: 28.2.1. Área para entrevista. | C70: NA | D70: No aplica al servicio farmacéutico: la farmacia no cuenta con consultorios. | E70: No aplica
A71: TSINF | B71: 28.2.2. Área de procedimientos. | C71: NA | D71: No aplica al servicio farmacéutico: la farmacia no cuenta con consultorios. | E71: No aplica
A72: TSINF | B72: 28.2.3. Las áreas están separadas entre sí por barrera física fija. | C72: NA | D72: No aplica al servicio farmacéutico: la farmacia no cuenta con consultorios. | E72: No aplica
A73: TSINF | B73: 28.2.4. Mesón de trabajo. | C73: NA | D73: No aplica al servicio farmacéutico: la farmacia no cuenta con consultorios. | E73: No aplica
A74: TSINF | B74: 28.2.5. Poceta, cuando la requiera, según los procedimientos que el prestrador documente en el estándar de procesos prioritarios. | C74: NA | D74: No aplica al servicio farmacéutico: la farmacia no cuenta con consultorios. | E74: No aplica
A75: TSINF | B75: 28.2.6. Lavamanos. No se exige adiocnal si el consultorio cuenta con una unidad sanitaria. | C75: NA | D75: No aplica al servicio farmacéutico: la farmacia no cuenta con consultorios. | E75: No aplica
... A88: TSINF | B88: 29.2. Lavamanos. No se exige adicional si el consultorio cuenta con unidad sanitaria. | C88: NA | D88: No aplica al servicio farmacéutico: la farmacia no cuenta con consultorios. | E88: No aplica
A89: TSINF | B89: 30. Sala de procedimientos: Es el ambiente donde se realizan procedimientos derivados de los servicios de salud. Para efectos del presente manual, se definen los siguientes tipos de sala:
A90: TSINF | B90: 30.1. Sala de procedimientos o curaciones. Ambiente con mínimo 8 m2, que cuenta con: | C90: NA | D90: No aplica al servicio farmacéutico: la farmacia no cuenta con salas de procedimientos. | E90: No aplica
A91: TSINF | B91: 30.1.1. Mesón de trabajo | C91: NA | D91: No aplica al servicio farmacéutico: la farmacia no cuenta con salas de procedimientos. | E91: No aplica
A92: TSINF | B92: 30.1.2. Poceta, cuando la requiera, según los procedimientos que el prestador documente en el estándar de procedimientos prioritarios. | C92: NA | D92: No aplica al servicio farmacéutico: la farmacia no cuenta con salas de procedimientos. | E92: No aplica
A93: TSINF | B93: 30.1.3. Lavamanos | C93: NA | D93: No aplica al servicio farmacéutico: la farmacia no cuenta con salas de procedimientos. | E93: No aplica
A94: TSINF | B94: 30.2. Sala de procedimientos de Litotricia: Ambiente con dimensión variable acirde con la tecnólogía utilizada, que cuenta con mesón de trabajo con poceta y disponibilidad de: | C94: NA | D94: No aplica al servicio farmacéutico: la farmacia no cuenta con salas de procedimientos. | E94: No aplica
A95: TSINF | B95: 30.2.1. Vestidor para pacientes con área para casilleros. | C95: NA | D95: No aplica al servicio farmacéutico: la farmacia no cuenta con salas de procedimientos. | E95: No aplica
A96: TSINF | B96: 30.2.2. Área de recuperación. | C96: NA | D96: No aplica al servicio farmacéutico: la farmacia no cuenta con salas de procedimientos. | E96: No aplica
A97: TSINF | B97: 30.2.3. Unidad sanitaria. | C97: NA | D97: No aplica al servicio farmacéutico: la farmacia no cuenta con salas de procedimientos. | E97: No aplica
A98: TSINF | B98: 30.3. Sala de procedimientos endoscópicos: Ambiente con dimensión variable acorde con el tipo de tecnología utilizada y los procedimientos que se realicen, cuenta con:
A99: TSINF | B99: 30.3.1. Área de procedimientos endoscópicos. | C99: NA | D99: No aplica al servicio farmacéutico: la farmacia no realiza procedimientos endoscópicos, electroencefalográficos ni con láser. | E99: No aplica
A100: TSINF | B100: 30.3.2. Área de recuperación, que puede ser la misma área donde se realice el procedimiento endoscópico. | C100: NA | D100: No aplica al servicio farmacéutico: la farmacia no realiza procedimientos endoscópicos, electroencefalográficos ni con láser. | E100: No aplica
A101: TSINF | B101: 30.3.3 Lavamanos. Disponibilidad de: | C101: NA | D101: No aplica al servicio farmacéutico: la farmacia no realiza procedimientos endoscópicos, electroencefalográficos ni con láser. | E101: No aplica
A102: TSINF | B102: 30.3.4. Unidad sanitaria | C102: NA | D102: No aplica al servicio farmacéutico: la farmacia no realiza procedimientos endoscópicos, electroencefalográficos ni con láser. | E102: No aplica
A103: TSINF | B103: 30.3.5. Vestidr para pacientes con área para casilleros que puede ser la misma unidad sanitaria con casilleros. | C103: NA | D103: No aplica al servicio farmacéutico: la farmacia no realiza procedimientos endoscópicos, electroencefalográficos ni con láser. | E103: No aplica
A104: TSINF | B104: 30.3.6. Ambiente o área para almacenar materiales e insumos. | C104: NA | D104: No aplica al servicio farmacéutico: la farmacia no realiza procedimientos endoscópicos, electroencefalográficos ni con láser. | E104: No aplica
A105: TSINF | B105: 30.3.7. Área de limpieza y desinfección de endoscopis con mesón de trabajo con poceta. | C105: NA | D105: No aplica al servicio farmacéutico: la farmacia no realiza procedimientos endoscópicos, electroencefalográficos ni con láser. | E105: No aplica
A106: TSINF | B106: 30.3.8. Ambiente o área para almacenamiento de equipos biomédicos. | C106: NA | D106: No aplica al servicio farmacéutico: la farmacia no realiza procedimientos endoscópicos, electroencefalográficos ni con láser. | E106: No aplica
A107: TSINF | B107: 30.4. Si se realiza procedimiento de monitorización electroencefalográfica con vídeo y radio, cuenta con:
A108: TSINF | B108: 30.4.1. Ambiente con dimensión variable acorde con el tipo de tecnología utilizada. Disponibilidad de: | C108: NA | D108: No aplica al servicio farmacéutico: la farmacia no realiza procedimientos endoscópicos, electroencefalográficos ni con láser. | E108: No aplica
A109: TSINF | B109: 30.4.2. Unidad sanitaria | C109: NA | D109: No aplica al servicio farmacéutico: la farmacia no realiza procedimientos endoscópicos, electroencefalográficos ni con láser. | E109: No aplica
A110: TSINF | B110: 30.5. Si se realiza procedimientos terapéuticos con láser de argón o yag láser, cuenta con ambiente con dimensión variable acorde con el tipo de tecnología utilizada: | C110: NA | D110: No aplica al servicio farmacéutico: la farmacia no realiza procedimientos endoscópicos, electroencefalográficos ni con láser. | E110: No aplica
A111: TSINF | B111: 31. Sistema de alarma cuando se cuente con red de distribución de gases medicinales. | C111: NA | D111: No aplica al servicio farmacéutico: el sistema de alarma de la red de gases medicinales se evalúa a nivel institucional (servicios de internación, urgencias y cirugía). | E111: No aplica
A112: TSINF | B112: 32. Puesto de enfermería Área con dimensión variable que, de acuerdo con las necesidades de cada servicio, cumplen con las siguientes características:
...

Sheet 11.1.3.DOT
B1: VOLVER A TABLA DE CONTENIDO
B2: Estandar de Dotación
A3: Estandar | B3: Criterios | C3: Estado | D3: Comentarios | E3: Concepto preauditoría (QF)
A4: TSDOT | B4: 1. El prestador de servicios de salud cuenta con el registro de la relación de los equipos biomédicos requeridos para la prestación de servicios de salud, este registro cuenta como mínimo con la siguiente información:
A5: TSDOT | B5: 1.1. Nombre del equipo biomédico. | C5: NC | D5: La respuesta trata neveras, termohigrómetros y aire acondicionado como 'equipos biomédicos'; en sentido estricto son equipos de apoyo e instrumentos de medición. Debe definirse qué equipos biomédicos tiene el SF y aportar el inventario; si no tiene ninguno, sus equipos se controlan en el criterio 9 del SF (hoja 11.3.2). | E5: No evidenciado
A6: TSDOT | B6: 1.2. Marca. | C6: NC | D6: No se aporta el inventario, por lo que no es posible verificar el registro de la marca de los equipos del SF. | E6: No evidenciado
A7: TSDOT | B7: 1.3. Modelo. | C7: NC | D7: No se aporta el inventario, por lo que no es posible verificar el registro del modelo de los equipos del SF. | E7: No evidenciado
A8: TSDOT | B8: 1.4. Serie. | C8: NC | D8: No se aporta el inventario, por lo que no es posible verificar el registro de la serie de los equipos del SF. | E8: No evidenciado
A9: TSDOT | B9: 1.5. Registro sanitario para dispositivos médicos o permiso de comercialización para equipos biomédicos de tecnología controlada, cuando lo requiera. | C9: NC | D9: No se identifica qué equipos del SF requieren registro sanitario o permiso de comercialización. Termohigrómetros y aires acondicionados no lo requieren; debe precisarse equipo por equipo y aportar el soporte de los que sí. | E9: No evidenciado
A10: TSDOT | B10: 1.6. Clasificación por riesgo, cuando el equipo lo requiera. | C10: NC | D10: No se evidencia la clasificación por riesgo, que solo aplica a los equipos que sean dispositivos médicos. Debe precisarse en el inventario. | E10: No evidenciado
A11: TSDOT | B11: 2. El prestador de servicios de salud garantiza las condiciones técnicas de calidad de los equipos biomédicos, para lo cual cuenta con:
A12: TSDOT | B12: 2.1. Programa de mantenimiento preventivo de los equipos biomédicos, que incluya el cumplimiento de las recomendaciones establecidas por el fabricante o de acuerdo con el protocolo de mantenimiento que tenga definido el prestador, éste último cuando no esté definido por el fabricante. | C12: NC | D12: Solo se menciona el cronograma. Debe demostrarse la ejecución: registros de mantenimiento de neveras y aire acondicionado, y certificados de calibración vigentes de los termohigrómetros emitidos por un laboratorio acreditado. Sin calibración, los registros de temperatura y humedad no son confiables. | E12: No evidenciado
A13: TSDOT | B13: 2.2. Hoja(s) de vida del(los) equipo(s) biomédico(s), con los registros de los mantenimientos preventivos y correctivos, según corresponda. | C13: NC | D13: No se aportan hojas de vida. Debe verificarse que cada equipo del SF tenga hoja de vida con los mantenimientos y las calibraciones registrados. | E13: No evidenciado
A14: TSDOT | B14: 3. El prestador de servicios de salud cuenta con un programa de capacitación en el uso de dispositivos médicos cuando éstos lo requieran, el cual puede ser desarrollado por el fabricante, importador o por el mismo prestador. | C14: NA | D14: No aplica al servicio farmacéutico: el personal de farmacia no usa dispositivos médicos en pacientes. Sí debe estar capacitado en el uso de neveras y data loggers (dejar registro). | E14: No aplica
A15: TSDOT | B15: 4. La dotación de los servicios de salud está en concordancia con lo definido por el prestador en el estándar de procesos prioritarios. | C15: NC | D15: La respuesta enumera la dotación esperada sin demostrar que exista. Debe verificarse en campo, contra el manual de procesos del SF, que la dotación corresponda a los procesos que realmente se ejecutan. | E15: No evidenciado
A16: TSDOT | B16: 5. La suficiencia de equipos biomédicos está relacionada con la frecuencia de uso de los mismo, incluyendo los tiempos del proceso de esterilización, cuando aplique. | C16: NC | D16: No se informa el número de neveras y termohigrómetros ni de las áreas o stocks a controlar. Debe verificarse que cada área de almacenamiento de medicamentos (farmacia, bodega, stocks de servicios) tenga su instrumento de medición. | E16: No evidenciado
A17: TSDOT | B17: 6. El mantenimiento de los equipos biomédicps es ejecutado por el talento humano profesional, tecnólogo o técnico en áreas relacionadas. Este mantenimiento puede ser realizado directamente por el prestador de servicios de salud o mediante contrato o convenio con un tercero. | C17: NC | D17: No se aporta contrato ni soporte de idoneidad del personal de mantenimiento. Se requieren el contrato con la empresa o la hoja de vida del técnico, y la verificación de las firmas en los reportes de mantenimiento. | E17: No evidenciado
A18: TSDOT | B18: 7. Los prestadores que oferten servicios de salud en modalidad extramural no pueden elaborar ni adaptar dispositivos médicos sobre medida. | C18: NA | D18: No aplica: el servicio farmacéutico no presta modalidad extramural (unidad móvil, jornada de salud ni domiciliaria). | E18: No aplica
A19: TSDOT | B19: 8. Los servicios de salud que requieren carro de paro, cuenta con la siguiente dotación:
A20: TSDOT | B20: 8.1. Desfibrilador bifásico con sistema de visualización integrado, capacidad de cardioversión, marcapasos transcutáneo y paletas para adultos y pediátricas según aplique. | C20: NA | D20: No aplica al servicio farmacéutico: la farmacia no requiere carro de paro. El SF sí define, repone y controla los medicamentos y dispositivos de los carros de paro de los demás servicios (ver hoja 11.1.4, criterios 11 y 12). | E20: No aplica
A21: TSDOT | B21: 8.2. Resucitador pulmonar manual. | C21: NA | D21: No aplica al servicio farmacéutico: la farmacia no requiere carro de paro. El SF sí define, repone y controla los medicamentos y dispositivos de los carros de paro de los demás servicios (ver hoja 11.1.4, criterios 11 y 12). | E21: No aplica
A22: TSDOT | B22: 8.3. Aspirador o sistema de vacío. | C22: NA | D22: No aplica al servicio farmacéutico: la farmacia no requiere carro de paro. El SF sí define, repone y controla los medicamentos y dispositivos de los carros de paro de los demás servicios (ver hoja 11.1.4, criterios 11 y 12). | E22: No aplica
A23: TSDOT | B23: 8.4. Monitor de signos vitales con accesorios que cuenta como mínimo con:
A24: TSDOT | B24: 8.4.1. Trazado electrocardiográfico si no está incorporado en el desfibrilador | C24: NA | D24: No aplica al servicio farmacéutico: la farmacia no requiere carro de paro. El SF sí define, repone y controla los medicamentos y dispositivos de los carros de paro de los demás servicios (ver hoja 11.1.4, criterios 11 y 12). | E24: No aplica
A25: TSDOT | B25: 8.4.2.Presión no invasiva | C25: NA | D25: No aplica al servicio farmacéutico: la farmacia no requiere carro de paro. El SF sí define, repone y controla los medicamentos y dispositivos de los carros de paro de los demás servicios (ver hoja 11.1.4, criterios 11 y 12). | E25: No aplica
A26: TSDOT | B26: 8.4.3. Saturación de oxígeno que puede estar integrado en el monitor o externo | C26: NA | D26: No aplica al servicio farmacéutico: la farmacia no requiere carro de paro. El SF sí define, repone y controla los medicamentos y dispositivos de los carros de paro de los demás servicios (ver hoja 11.1.4, criterios 11 y 12). | E26: No aplica
A27: TSDOT | B27: 8.4.4. Batería | C27: NA | D27: No aplica al servicio farmacéutico: la farmacia no requiere carro de paro. El SF sí define, repone y controla los medicamentos y dispositivos de los carros de paro de los demás servicios (ver hoja 11.1.4, criterios 11 y 12). | E27: No aplica
A28: TSDOT | B28: 8.5. Laringoscopio con hojas rectas y curvas para adultos y pediátricas, según aplique | C28: NA | D28: No aplica al servicio farmacéutico: la farmacia no requiere carro de paro. El SF sí define, repone y controla los medicamentos y dispositivos de los carros de paro de los demás servicios (ver hoja 11.1.4, criterios 11 y 12). | E28: No aplica
A29: TSDOT | B29: 8.6. Medicamentos, dispositivos médicos e insumos, definidos por el prestador. | C29: NA | D29: No aplica al servicio farmacéutico: la farmacia no requiere carro de paro. El SF sí define, repone y controla los medicamentos y dispositivos de los carros de paro de los demás servicios (ver hoja 11.1.4, criterios 11 y 12). | E29: No aplica
A30: TSDOT | B30: 9. Las instituciones prestadoras de servicios de salud con servicios de hospitalización, hospitalización paciente crónico con y sin ventilador, cuidado intensivo neonatal, pediátrico y adulto, urgencias y del grupo quirúrgico, en la modalidad intramural, cuentan con equipos de telecomunicaciones de doble via y conectividad para notificar a la Red de Donación y Trasplantes sobre la existencia de un posible donante. | C30: NA | D30: No aplica al servicio farmacéutico: los equipos para notificar a la Red de Donación y Trasplantes se evalúan a nivel institucional (hospitalización, urgencias, UCI y cirugía). | E30: No aplica
A31: TSDOT | B31: 10. Las instituciones prestadoras de servicios de salud con servicios de cuidado intensivo pediátrico y adulto que adicionalmente habiliten el servicio quirúrgico de neurocirugía, cuentan con equipo biomédico para realizar pruebas auxiliares en el diagnóstico de muerte encefálica, según lo documentado en el estándar de procesos prioritarios. | C31: NA | D31: No aplica al servicio farmacéutico: aplica a IPS con UCI y neurocirugía. | E31: No aplica
A32: TSDOT | B32: 11. En los sistemas centralizados de gases medicinales, se realiza el mantenimiento a los componentes del sistema por el personal capacitado por el fabricante. | C32: NA | D32: No aplica al servicio farmacéutico: el mantenimiento del sistema centralizado de gases medicinales se evalúa a nivel institucional. | E32: No aplica
A33: TSDOT | B33: 12. El prestador de servicios de salud que realice el proceso de esterilización en un área o ambiente dentro o fuera del servicio de salud cuenta con los equipos biomédicos y la dotación de acuerdo con el método utilizado. | C33: NA | D33: No aplica al servicio farmacéutico: en la farmacia no se realiza el proceso de esterilización. | E33: No aplica
A34: TSDOT | B34: 13. Si el prestador de servicios de salud no tiene habilitado el servicio de gestión pre transfusional, pero realiza procedimientos de transfusión sanguínea en alguno de sus servicios habilitados cuenta con:
A35: TSDOT | B35: 13.1. Nevera o depósito fria para el almacenamiento de sangre o de sus componentes con sistema de control de temperatura entre 1ºC y 6ºC y alarma audible o sistema de monitoreo que alerte cambios próximos al límite en que la sangre o sus componentes puedan deteriorarse. | C35: NA | D35: No aplica al servicio farmacéutico: la dotación para transfusiones aplica a los servicios donde se transfunde. | E35: No aplica
A36: TSDOT | B36: 13.2. Equipo para descongelar plasma, cuando se requiera, con sistema de control de temperatura. | C36: NA | D36: No aplica al servicio farmacéutico: la dotación para transfusiones aplica a los servicios donde se transfunde. | E36: No aplica
A37: TSDOT | B37: 13.3 Congelador para la conservación de plasma o crioprecipitados con registro y control de temperatura por debajo de -18ºC y sistema de alarma audible que alerte cambios próximos al límite en que el componente almacenado pueda deteriorarse, cuando se requiera. | C37: NA | D37: No aplica al servicio farmacéutico: la dotación para transfusiones aplica a los servicios donde se transfunde. | E37: No aplica
A38: TSDOT | B38: 13.4. Agitador o rotador de plaquetas con sistema de control de temperatura entre 20ºC y 24ºC cuando se requiera. | C38: NA | D38: No aplica al servicio farmacéutico: la dotación para transfusiones aplica a los servicios donde se transfunde. | E38: No aplica
A39: TSDOT | B39: 13.5. Nevera para transporte de componentes sanguíneos, donde se garantice la cadena de frío. | C39: NA | D39: No aplica al servicio farmacéutico: la dotación para transfusiones aplica a los servicios donde se transfunde. | E39: No aplica
A40: TSDOT | B40: 14. Los servicios de salud donde se realicen procedimientos bajo sedación fuera de salas de cirugía y monitorización electroencefalográfica con video y radio cuentan con carro de paro. | C40: NA | D40: No aplica al servicio farmacéutico: en la farmacia no se realizan procedimientos bajo sedación. | E40: No aplica
A41: TSDOT | B41: 15. En los servicios de los grupos quirúrgico, internación y el servicio de urgencias, el prestador de servicios de salud cuenta con accesorios para garantizar empaque cerrado y transporte de los elementos sucios y limplos, como compreseros, vehículos para ta recolección interna de residuos, carros de comida, instrumental, entre otros. | C41: NA | D41: No aplica al SF: el criterio se refiere al transporte cerrado de elementos sucios y limpios (compreseros, residuos, comidas, instrumental) en los servicios quirúrgicos, de internación y de urgencias. El transporte de medicamentos se evalúa en la hoja 11.1.4 (criterio 4.3). Se corrige la calificación C del borrador. | E41: No aplica
A42: TSDOT | B42: Modalidad extramural
A43: TSDOT | B43: 16. Adicional a los criterios enunciados del presente estándar, que le apliquen, el prestador de servicios de salud cuenta con: | C43: NA | D43: No aplica: el servicio farmacéutico no presta modalidad extramural (unidad móvil, jornada de salud ni domiciliaria). | E43: No aplica
A44: TSDOT | B44: 16.1. Sistemas de telecomunicaciones de doble vía. | C44: NA | D44: No aplica: el servicio farmacéutico no presta modalidad extramural (unidad móvil, jornada de salud ni domiciliaria). | E44: No aplica
A45: TSDOT | B45: 16.2. Cuando se realicen pruebas para la detección de eventos de interés en salud pública, cuenta con:
A46: TSDOT | B46: 16.2.1. Microscopio | C46: NA | D46: No aplica: el servicio farmacéutico no presta modalidad extramural (unidad móvil, jornada de salud ni domiciliaria). | E46: No aplica
A47: TSDOT | B47: 16.2.2. Cinta métrica | C47: NA | D47: No aplica: el servicio farmacéutico no presta modalidad extramural (unidad móvil, jornada de salud ni domiciliaria). | E47: No aplica
A48: TSDOT | B48: 16.2.3. Báscula | C48: NA | D48: No aplica: el servicio farmacéutico no presta modalidad extramural (unidad móvil, jornada de salud ni domiciliaria). | E48: No aplica
A49: TSDOT | B49: Modalidad telemedicina
A50: TSDOT | B50: 17. El prestador de servicios de salud realiza el mantenimiento de la tecnología de información y de comunicaciones para avalar la calidad de la información, y adicionalmente cuenta con: | C50: NA | D50: No aplica: el servicio farmacéutico no está habilitado en modalidad telemedicina (verificar en el REPS). | E50: No aplica
A51: TSDOT | B51: 17.1. Prestador remisor
A52: TSDOT | B52: 17.1.1. Documento firmado por un ingeniero biomédico con tarjeta profesional vigente, que certifique que:
A53: TSDOT | B53: 17.1.1.1. Los dispositivos periféricos necesarios, de acuerdo con el tipo de servicios ofertados, garantizan la obtención de la información requerida por el prestador de referencia. | C53: NA | D53: No aplica: el servicio farmacéutico no está habilitado en modalidad telemedicina (verificar en el REPS). | E53: No aplica
A54: TSDOT | B54: 17.1.1.2. Los equipos de captura utilizados por el prestador de servicios de salud garantizan que la información obtenida es equivalente a la original, de manera que al ser reproducida se garantice su calidad y confiabilidad. | C54: NA | D54: No aplica: el servicio farmacéutico no está habilitado en modalidad telemedicina (verificar en el REPS). | E54: No aplica
A55: TSDOT | B55: 17.1.1.3. Los parámetros de digitalización y compresión seleccionados en los equipos durante la captura de datos o imágenes garantizan la resolución necesaria para permitir el diagnóstico. | C55: NA | D55: No aplica: el servicio farmacéutico no está habilitado en modalidad telemedicina (verificar en el REPS). | E55: No aplica
A56: TSDOT | B56: 17.1.1.4. Si el prestador de servicios de salud realiza consulta dermatológica en la modalidad de telemedicina cuenta con cámara digital de alta resolución que permita un fácil enfoque de las lesiones de piel y revisión de las imágenes capturadas previo a la transmisión al dermatólogo. | C56: NA | D56: No aplica: el servicio farmacéutico no está habilitado en modalidad telemedicina (verificar en el REPS). | E56: No aplica
A57: TSDOT | B57: 17.1.2. Documento firmado por un ingeniero de sistemas con tarjeta profesional vigente, que certifique que:
A58: TSDOT | B58: 17.1.2.1. Los dispositivos utilizados para transferencia de información sincrónica por videoconferencia garantizan óptima fidelidad y calidad del video y sonido para el prestador remisor y para e! prestador de referencia. | C58: NA | D58: No aplica: el servicio farmacéutico no está habilitado en modalidad telemedicina (verificar en el REPS). | E58: No aplica
A59: TSDOT | B59: 17.1.2.2. El software utilizado se adapta al cambio en la disponibilidad del ancho de banda sin perder conexión. En el caso que la videoconferencia sea grabada se deberán contemplar todos criterios de seguridad informática, que permita resguardar adecuadamente la confidencialidad y privacidad del paciente. | C59: NA | D59: No aplica: el servicio farmacéutico no está habilitado en modalidad telemedicina (verificar en el REPS). | E59: No aplica
A60: TSDOT | B60: 17.1.2.3. Las pantallas o monitores grado médico utilizados para el despliegue de imágenes cuentan con una distancia máxima de 0.25 milímetros entre píxeles (dot pitch), para garantizar la interpretación adecuada de la información recibida. | C60: NA | D60: No aplica: el servicio farmacéutico no está habilitado en modalidad telemedicina (verificar en el REPS). | E60: No aplica
A61: TSDOT | B61: 17.2. Prestador de referencia.
A62: TSDOT | B62: 17.2.1. Documento firmado por un ingeniero de sistemas con tarjeta profesional vigente, que certifique que: | C62: NA | D62: No aplica: el servicio farmacéutico no está habilitado en modalidad telemedicina (verificar en el REPS). | E62: No aplica
A63: TSDOT | B63: 17.2.1.1. Los dispositivos utilizados para transferencia de información sincrónica por videoconferencia garantizan una óptima fidelidad y calidad del video y sonido tanto para el prestador remisor como para el prestador de referencia. | C63: NA | D63: No aplica: el servicio farmacéutico no está habilitado en modalidad telemedicina (verificar en el REPS). | E63: No aplica
A64: TSDOT | B64: 17.2.1.2. El software utilizado se adapta al cambio de la disponibilidad del ancho de banda sin perder la conexión. | C64: NA | D64: No aplica: el servicio farmacéutico no está habilitado en modalidad telemedicina (verificar en el REPS). | E64: No aplica
A65: TSDOT | B65: 17.2.1.3. En el caso que la videoconferencia sea grabada se deberán contemplar todos los criterios de seguridad informática, que permita resguardar adecuadamente la confidencialidad y privacidad del paciente. | C65: NA | D65: No aplica: el servicio farmacéutico no está habilitado en modalidad telemedicina (verificar en el REPS). | E65: No aplica
A66: TSDOT | B66: 17.2.2. Las pantallas o monitores grado médico utilizados para el despliegue de imágenes cuentan con una distancia máxima de 0.19 milímetros entre pixeles (dot pitch), resolución mínima de 1024 x 768 pixeles, como mínimo un ratio de contraste de 500:1 y mínimo de luminancia (brillo) de 250 cd/m2 que permita garantizar la interpretación adecuada de la información recibida. | C66: NA | D66: No aplica: el servicio farmacéutico no está habilitado en modalidad telemedicina (verificar en el REPS). | E66: No aplica
B68: CUMPLE | C68: =COUNTIF($C$5:$C$66,"C")
B69: NO CUMPLE | C69: =COUNTIF($C$5:$C$66,"NC")
B70: NO APLICA | C70: =COUNTIF($C$5:$C$66,"NA")

Sheet 11.1.4MD
B1: VOLVER A TABLA DE CONTENIDO
B2: Estandar de Medicamentos, dispositivos médicos e insumos
A3: Estandar | B3: Criterios | C3: Estado | D3: Comentarios | E3: Concepto preauditoría (QF)
A4: TSMD | B4: 1. El prestador de servicios de salud lleva registros con la información de todos los medicamentos para uso humano requeridos en la prestación de los servicios que oferte; dichos registros cuentan con la siguiente información:
A5: TSMD | B5: 1.1. Principio activo. | C5: NC | D5: El registro de principio activo se menciona como parte del inventario, sin aportar el listado básico ni una salida del sistema. Se requiere revisar una muestra del inventario del SF y confirmar que el campo esté completo y concuerde con el producto físico. | E5: No evidenciado
A6: TSMD | B6: 1.2. Forma farmacéutica. | C6: NC | D6: El registro de forma farmacéutica se menciona como parte del inventario, sin aportar el listado básico ni una salida del sistema. Se requiere revisar una muestra del inventario del SF y confirmar que el campo esté completo y concuerde con el producto físico. | E6: No evidenciado
A7: TSMD | B7: 1.3. Concentración | C7: NC | D7: El registro de concentración se menciona como parte del inventario, sin aportar el listado básico ni una salida del sistema. Se requiere revisar una muestra del inventario del SF y confirmar que el campo esté completo y concuerde con el producto físico. | E7: No evidenciado
A8: TSMD | B8: 1.4. Lote. | C8: NC | D8: El registro de lote se menciona como parte del inventario, sin aportar el listado básico ni una salida del sistema. Se requiere revisar una muestra del inventario del SF y confirmar que el campo esté completo y concuerde con el producto físico. | E8: No evidenciado
A9: TSMD | B9: 1.5. Fecha de vencimiento. | C9: NC | D9: El registro de fecha de vencimiento se menciona como parte del inventario, sin aportar el listado básico ni una salida del sistema. Se requiere revisar una muestra del inventario del SF y confirmar que el campo esté completo y concuerde con el producto físico. | E9: No evidenciado
A10: TSMD | B10: 1.6. Presentación comercial. | C10: NC | D10: El registro de presentación comercial se menciona como parte del inventario, sin aportar el listado básico ni una salida del sistema. Se requiere revisar una muestra del inventario del SF y confirmar que el campo esté completo y concuerde con el producto físico. | E10: No evidenciado
A11: TSMD | B11: 1.7. Unidad de medida. | C11: NC | D11: El registro de unidad de medida se menciona como parte del inventario, sin aportar el listado básico ni una salida del sistema. Se requiere revisar una muestra del inventario del SF y confirmar que el campo esté completo y concuerde con el producto físico. | E11: No evidenciado
A12: TSMD | B12: 1.8. Registro sanitario vigente o permiso cuando se autorice, expedido por el Invima. | C12: NC | D12: No se aporta evidencia de la verificación de registros sanitarios. Se requiere la consulta en INVIMA, con fecha, para una muestra de productos, y el control de registros vencidos o en trámite de renovación. Es un punto de alto riesgo en la visita. | E12: No evidenciado
A13: TSMD | B13: 2. Los dispositivos médicos de uso humano requeridos para la prestación de los servicios de salud cuentan con información documentada que dé cuenta de la verificación y seguimiento de la siguiente información:
A14: TSMD | B14: 2.1. Descripción. | C14: NC | D14: No se aporta el listado de dispositivos médicos, por lo que no es posible verificar el registro de la descripción. Se requiere revisar una muestra y cruzarla con el producto físico. | E14: No evidenciado
A15: TSMD | B15: 2.2. Marca del dispositivo. | C15: NC | D15: No se aporta el listado de dispositivos médicos, por lo que no es posible verificar el registro de la marca. Se requiere revisar una muestra y cruzarla con el producto físico. | E15: No evidenciado
A16: TSMD | B16: 2.3. Serie (cuando le aplique). | C16: NC | D16: No se aporta el listado de dispositivos médicos, por lo que no es posible verificar el registro de la serie. Aplica sobre todo a dispositivos seriados. Se requiere revisar una muestra y cruzarla con el producto físico. | E16: No evidenciado
A17: TSMD | B17: 2.4. Presentación comercial. | C17: NC | D17: No se aporta el listado de dispositivos médicos, por lo que no es posible verificar el registro de la presentación comercial. Se requiere revisar una muestra y cruzarla con el producto físico. | E17: No evidenciado
A18: TSMD | B18: 2.5. Registro sanitario vigente o permiso de comercialización expedido por el Invima. | C18: NC | D18: No se aporta el listado de dispositivos médicos, por lo que no es posible verificar el registro de el registro sanitario o permiso de comercialización INVIMA vigente. La vigencia debe verificarse con consulta en INVIMA. Se requiere revisar una muestra y cruzarla con el producto físico. | E18: No evidenciado
A19: TSMD | B19: 2.6. Clasificación por riesgo (información consignada en el registro sanitario o permiso de comercialización). | C19: NC | D19: No se aporta el listado de dispositivos médicos, por lo que no es posible verificar el registro de la clasificación por riesgo. Debe coincidir con la consignada en el registro sanitario. Se requiere revisar una muestra y cruzarla con el producto físico. | E19: No evidenciado
A20: TSMD | B20: 2.7. Vida útil, cuando le aplique. | C20: NC | D20: No se aporta el listado de dispositivos médicos, por lo que no es posible verificar el registro de la vida útil. Aplica solo a los dispositivos que la tengan definida. Se requiere revisar una muestra y cruzarla con el producto físico. | E20: No evidenciado
A21: TSMD | B21: 2.8. Lote | C21: NC | D21: No se aporta el listado de dispositivos médicos, por lo que no es posible verificar el registro de el lote. Se requiere revisar una muestra y cruzarla con el producto físico. | E21: No evidenciado
A22: TSMD | B22: 2.9. Fecha de vencimiento | C22: NC | D22: No se aporta el listado de dispositivos médicos, por lo que no es posible verificar el registro de la fecha de vencimiento. Se requiere revisar una muestra y cruzarla con el producto físico. | E22: No evidenciado
A23: TSMD | B23: 3. Los reactivos de diagnóstico in vitro requeridos para la prestación de los servicios de salud cuentan con la información documentada que dé cuenta de la verificación y seguimiento de la siguiente información:
A24: TSMD | B24: 3.1. Nombre | C24: NC | D24: No se establece si el SF adquiere, almacena o distribuye los reactivos de diagnóstico in vitro o si los gestiona directamente el laboratorio. Debe definirse el responsable: si es el SF, se requiere el listado con nombre; si no, el criterio se evalúa en el laboratorio clínico y no en el SF. | E24: No evidenciado
A25: TSMD | B25: 3.2. Marca | C25: NC | D25: No se establece si el SF adquiere, almacena o distribuye los reactivos de diagnóstico in vitro o si los gestiona directamente el laboratorio. Debe definirse el responsable: si es el SF, se requiere el listado con marca; si no, el criterio se evalúa en el laboratorio clínico y no en el SF. | E25: No evidenciado
A26: TSMD | B26: 3.3. Presentación comercial | C26: NC | D26: No se establece si el SF adquiere, almacena o distribuye los reactivos de diagnóstico in vitro o si los gestiona directamente el laboratorio. Debe definirse el responsable: si es el SF, se requiere el listado con presentación comercial; si no, el criterio se evalúa en el laboratorio clínico y no en el SF. | E26: No evidenciado
A27: TSMD | B27: 3.4. Registro sanitario vigente o permiso de comecialización expedido por el Invima. | C27: NC | D27: No se establece si el SF adquiere, almacena o distribuye los reactivos de diagnóstico in vitro o si los gestiona directamente el laboratorio. Debe definirse el responsable: si es el SF, se requiere el listado con registro sanitario INVIMA vigente; si no, el criterio se evalúa en el laboratorio clínico y no en el SF. | E27: No evidenciado
A28: TSMD | B28: 3.5. Clasificación del riesgo santario | C28: NC | D28: No se establece si el SF adquiere, almacena o distribuye los reactivos de diagnóstico in vitro o si los gestiona directamente el laboratorio. Debe definirse el responsable: si es el SF, se requiere el listado con clasificación de riesgo sanitario; si no, el criterio se evalúa en el laboratorio clínico y no en el SF. | E28: No evidenciado
A29: TSMD | B29: 3.6. Vida útil, cuando aplique | C29: NC | D29: No se establece si el SF adquiere, almacena o distribuye los reactivos de diagnóstico in vitro o si los gestiona directamente el laboratorio. Debe definirse el responsable: si es el SF, se requiere el listado con vida útil; si no, el criterio se evalúa en el laboratorio clínico y no en el SF. | E29: No evidenciado
A30: TSMD | B30: 3.7. Fecha de vencimiento y lote. | C30: NC | D30: No se establece si el SF adquiere, almacena o distribuye los reactivos de diagnóstico in vitro o si los gestiona directamente el laboratorio. Debe definirse el responsable: si es el SF, se requiere el listado con fecha de vencimiento y lote; si no, el criterio se evalúa en el laboratorio clínico y no en el SF. | E30: No evidenciado
A31: TSMD | B31: 4. El prestador de servicios de salud cuenta con información documentada de los procesos generales según aplique, para:
A32: TSMD | B32: 4.1. Selección | C32: NC | D32: Se mencionan el procedimiento de selección y el Comité de Farmacia y Terapéutica sin aportarlos. Se requieren el procedimiento, el acto de conformación del comité, actas recientes y el listado básico de medicamentos aprobado y actualizado. | E32: No evidenciado
A33: TSMD | B33: 4.2. Adquisición | C33: NC | D33: No se aporta el procedimiento de adquisición ni la evaluación de proveedores. Se requieren ambos, más soportes de compra que demuestren que se adquiere a proveedores autorizados. | E33: No evidenciado
A34: TSMD | B34: 4.3. Transporte | C34: NC | D34: No se evidencia el procedimiento de transporte ni el control de temperatura durante el traslado (del proveedor a la clínica y de la farmacia a los servicios), en especial para refrigerados. | E34: No evidenciado
A35: TSMD | B35: 4.4. Recepción | C35: NC | D35: No se aportan el procedimiento ni actas de recepción técnica diligenciadas (lote, vencimiento, registro sanitario, estado del producto). Se requiere revisar una muestra de actas recientes. | E35: No evidenciado
A36: TSMD | B36: 4.5. Almacenamiento | C36: NC | D36: La respuesta no demuestra los criterios de almacenamiento: orden definido, separación de piso y paredes, segregación de alto riesgo y LASA. Requiere procedimiento y verificación en campo. | E36: No evidenciado
A37: TSMD | B37: 4.6. Conservación | C37: NC | D37: Se menciona el procedimiento de conservación sin aportar registros de temperatura y humedad. Se requieren ambos y la evidencia de acciones ante desviaciones. | E37: No evidenciado
A38: TSMD | B38: 4.7. Control de fechas de vencimiento | C38: NC | D38: Se requieren el procedimiento de semaforización y evidencia de su aplicación: listado de próximos a vencer, rotación FEFO y ausencia de vencidos en estanterías, stocks y carros de paro (verificación en campo). | E38: No evidenciado
A39: TSMD | B39: 4.8. Control de cadena de frío, manejo de contingencias con la cadena de frío | C39: NC | D39: Criterio de alto riesgo. No se aportan registros de temperatura de neveras (al menos dos veces al día o data logger, rango 2-8 °C) ni el plan de contingencia documentado y su aplicación ante excursiones de temperatura. | E39: No evidenciado
A40: TSMD | B40: 4.9. Distribución | C40: NC | D40: No se aportan el procedimiento de distribución ni evidencia del sistema implementado. En mediana/alta complejidad debe verificarse la distribución en dosis unitaria a hospitalización. | E40: No evidenciado
A41: TSMD | B41: 4.10. Dispensación | C41: NC | D41: Se requieren el procedimiento de dispensación y evidencia de su implementación: validación de la prescripción, verificación de identificadores y registros de dispensación. | E41: No evidenciado
A42: TSMD | B42: 4.11. Devolución | C42: NC | D42: No se evidencian el procedimiento ni registros de devoluciones (de servicios a farmacia y de farmacia a proveedores) con su trazabilidad. | E42: No evidenciado
A43: TSMD | B43: 4.12. Disposición final | C43: NC | D43: Se requieren el procedimiento, el contrato vigente con un gestor de residuos peligrosos autorizado y actas de destrucción. Para medicamentos de control especial, la destrucción debe tramitarse ante el Fondo Rotatorio de Estupefacientes. | E43: No evidenciado
... A55: TSMD | B55: 15. En los servicios de transporte asistencial, atención prehospitalaria y urgencias cuenta con kit de emergencias para la atención a víctimas de ataques con agentes químicos. | C55: NA | D55: No aplica al SF: el kit para víctimas de ataques con agentes químicos se exige en transporte asistencial, atención prehospitalaria y urgencias. Se corrige la calificación C del borrador. | E55: No aplica
A56: TSMD | B56: Modalidad extramural unidad móvil, jornada de salud y domiciliaria.
A57: TSMD | B57: 16. Adicional a los criterios enunciados de presente estándar, que le aplique a estas modalidades, el prestador de servicios en salud cuenta con:
A58: TSMD | B58: 16.1. Dispositivos médicos e insumos asistenciales según la patalogía del paciente o eventos de interés en salud pública cuando se requiera. | C58: NA | D58: Se asume que no presta modalidad extramural. Si realiza jornadas de salud o atención domiciliaria (p. ej. sede de promoción y prevención), aplica. | E58: No aplica
A59: TSMD | B59: 16.2. Medicamentos de acuerdo con inventario establecido por el prestador acorde a lo documentado en sus procesos prioritarios, cuando se requiera. | C59: NA | D59: Se asume que no presta modalidad extramural. Si la presta, verificar inventario de medicamentos definido. | E59: No aplica
A60: TSMD | B60: Modalidad telemedicina
A61: TSMD | B61: Prestador remisor y prestador de referencia.
A62: TSMD | B62: 17. El prestador de servicio de salud cumple con los criterios que le apliquen del presente estándar. | C62: NA | D62: Se asume que no tiene habilitada modalidad telemedicina. Verificar en el REPS. | E62: No aplica
B65: CUMPLE | C65: =COUNTIF($C$5:$C$62,"C")
B66: NO CUMPLE | C66: =COUNTIF($C$5:$C$62,"NC")
B67: NO APLICA | C67: =COUNTIF($C$5:$C$62,"NA")

Sheet 11.1.5.PP
B1: VOLVER A TABLA DE CONTENIDO
B2: Estandar de Procesos Prioritarios
A3: Estandar | B3: Criterios | C3: Estado | D3: Comentarios | E3: Concepto preauditoría (QF)
A4: TSPP | B4: 1. El prestador de servicios de salud cuenta con una política de seguridad del paciente acorde con los lineamientos expedidos por el Ministerio de Salud y Protección Social. | C4: NC | D4: Se refiere la política sin aportarla. Se requieren el documento aprobado y evidencia de su socialización al personal del SF (listas de asistencia, evaluación de conocimiento). | E4: No evidenciado
A5: TSPP | B5: 2. El prestador de servicios de salud realiza actividades encaminadas a gestionar la seguridad del paciente. | C5: NC | D5: La respuesta enuncia actividades (rondas, listas de chequeo, análisis de errores) sin evidencia de ejecución. Se requieren registros de rondas, listas diligenciadas y actas de análisis de casos del SF. | E5: No evidenciado
A6: TSPP | B6: 3. El prestador de servicios de salud cuenta con un comité o instancia que orienta y promueve la política de seguridad del paciente, el control de infecciones y ta optimización del uso de antibióticos, cuando tos prescriba o administre. En el caso de profesionales independientes de salud podrá ser el mismo prestador. | C6: NC | D6: No se aportan el acto de conformación ni las actas del comité. Debe verificarse la participación documentada del QF en el comité y en el programa de optimización de antimicrobianos (PROA). | E6: No evidenciado
A7: TSPP | B7: 4. El prestador de servicios de salud adopta y realiza las siguientes prácticas seguras, según aplique a su servicio de salud y cuenta con información documentada para:
A8: TSPP | B8: 4.1. Asegurar la correcta identificación del paciente en los procesos asistenciales. (que incluya como mínimo dos identificadores: nombre completo y número de identificación) | C8: NC | D8: Se requiere evidencia de que la dispensación verifica dos identificadores: procedimiento y rótulos de dosis unitaria con nombre y documento. Verificar en campo con una muestra de dispensaciones. | E8: No evidenciado
A9: TSPP | B9: 4.2. Gestionar y desarrollar una adecuada comunicación entre las personas que atienden y cuidan a los pacientes que incluyan enfoques diferenciales. | C9: NC | D9: No se evidencia el mecanismo de comunicación farmacia-médico-enfermería (p. ej. registro de validación de órdenes o de intervenciones farmacéuticas). Se requieren el documento y registros de implementación. | E9: No evidenciado
A10: TSPP | B10: 4.3. Detectar, prevenir y reducir infecciones asociadas con la atención en salud (que incluya protocolo de higiene de manos o higienización con soluciones a base de alcohol). | C10: NC | D10: Afirmación sin evidencia. Se requieren el protocolo institucional, la dotación en el SF y la evaluación de adherencia del personal de farmacia. | E10: No evidenciado
A11: TSPP | B11: 4.4. Detectar, ana!izar y gestionar eventos adversos. | C11: NC | D11: Se requieren el procedimiento y evidencia de su ejecución: reportes de errores de medicación y RAM, análisis (p. ej. Protocolo de Londres) y planes de mejora con seguimiento. Tener el procedimiento no demuestra que se aplique. | E11: No evidenciado
A12: TSPP | B12: 4.5. Garantizar la funcionalidad de los procedimientos de consentimiento informado. | C12: NA | D12: No aplica al servicio farmacéutico: el consentimiento informado aplica a los procedimientos asistenciales. | E12: No aplica
A13: TSPP | B13: 4.6. Mejorar la seguridad en la utilización de medicamentos, en los servicios donde aplique. | C13: NC | D13: Práctica segura central del SF; la respuesta enumera buenas prácticas sin demostrarlas. Se requieren el listado institucional de medicamentos de alto riesgo y LASA, la señalización diferenciada en estantería (verificación en campo), el procedimiento de doble verificación, registros de conciliación y el control de electrolitos concentrados en los servicios. | E13: No evidenciado
A14: TSPP | B14: 4.7. Prevenir y reducir la frecuencia de caídas, en los servicios donde aplique. | C14: NA | D14: No aplica al servicio farmacéutico: la prevención de caídas aplica a los servicios con pacientes. | E14: No aplica
A15: TSPP | B15: 4.8. Garantizar la atención segura de ta gestante y el recién nacido, en los servicios donde aplique. | C15: NA | D15: No aplica al servicio farmacéutico: aplica a atención de la gestante y el recién nacido. | E15: No aplica
A16: TSPP | B16: 4.9. Prevenir complicaciones asociadas a disponibilidad y manejo de sangre, componentes y a la transfusión sanguínea, en los servicios donde aplique. | C16: NA | D16: No aplica al servicio farmacéutico: aplica a los servicios que manejan sangre y componentes. | E16: No aplica
A17: TSPP | B17: 4.10. Prevenir úlceras por presión, en los servicios donde aplique. | C17: NA | D17: No aplica al servicio farmacéutico: aplica a los servicios de internación. | E17: No aplica
A18: TSPP | B18: 4.11. Mejorar la seguridad en los procedimientos quirúrgicos, en los servicios donde aplique. | C18: NA | D18: No aplica al servicio farmacéutico: aplica a los procedimientos quirúrgicos. | E18: No aplica
A19: TSPP | B19: 5. El prestador de servicios de salud promueve la cultura de seguridad del paciente que involucra a todo el personal de manera sistemática con un enfoque educativo no punitivo mediante:
A20: TSPP | B20: 5.1. Capacitación del personal en el tema de seguridad del paciente y en los principales riesgos de la atención. | C20: NC | D20: Se requiere el plan de capacitación del SF con cronograma, temas, listas de asistencia y evaluaciones, incluidas la inducción y la reinducción del personal de farmacia. | E20: No evidenciado
A21: TSPP | B21: 5.2. Actividades donde se ilustra al paciente y sus allegados en el autocuidado de su seguridad. | C21: NC | D21: No se evidencian material educativo ni registros de educación al paciente de egreso sobre el uso de sus medicamentos. | E21: No evidenciado
A22: TSPP | B22: 6. El prestador de servicios de salud cuenta con información documentada de las actividades y procedimientos que se realizan en el servicio acordes con su objeto, alcance y enfoque diferencial, mediante guías de práctica clínica- GPC, procedimientos de atención, protocolos de atención y otros documentos que el prestador de servicios de salud determine, dicha información incluye talento humano, equipos biomédicos, medicamentos y dispositivos médicos e insumos requeridos. | C22: NC | D22: Se requiere el manual de procesos y procedimientos del SF bajo control documental (código, versión, fecha, firma del QF). No se aporta listado maestro de documentos. | E22: No evidenciado
A23: TSPP | B23: 7. La información documentada es conocida mediante acciones de formación continua por el talento humano encargado y responsable de su aplicación, incluyendo el talento humano en entrenamiento, y existe evidencia de su socialización. | C23: NC | D23: No se aportan actas de socialización ni evaluaciones de adherencia. Debe diferenciarse la existencia del documento de su apropiación por el personal. | E23: No evidenciado
A24: TSPP | B24: 8. Las guías de práctica clínica y protocolos a adoptar son en primera medida los que disponga el Ministerio de Salud y Protección Social. En caso de no estar disponibles, o si existe nueva evidencia científica que actualice alguna o algunas de las recomendaciones de las guías de práctica clínica o requerimientos de los protocolos, el prestador de servicios de salud adopta, adapta o desarrolla guías de práctica clínica o protocolos basados en evidencia científica, publicados nacional o internacionalmente. | C24: NC | D24: No se identifican los protocolos adoptados ni su fuente. Se requieren el listado de protocolos relacionados con medicamentos y el acto de adopción. | E24: No evidenciado
A25: TSPP | B25: 9. El prestador de servicios de salud de acuerdo con las patologías más frecuentes en el servicio define la guía o guías de práctica clínica a adoptar, o adaptar o desarrollar. | C25: NA | D25: No aplica al servicio farmacéutico: la definición de guías de práctica clínica por patología la hacen los servicios médicos. | E25: No aplica
A26: TSPP | B26: 10. El prestador de servicios de salud cuenta con información documentada de la adopción, o adaptación o desarrollo de guías práctica clínica o protocolos basados en evidencia científica. | C26: NC | D26: Se requiere el documento de adopción con la evidencia científica que lo soporta (p. ej. protocolo PROA, guía de dilución y estabilidad). No se aporta. | E26: No evidenciado
A27: TSPP | B27: 11. Los servicios de salud donde se atiendan pacientes con enfermedades terminales, crónicas, degenerativas e irreversibles, a los cuales se determine el manejo del dolor y cuidado paliativo, cuentan con información documentada para su manejo. | C27: NA | D27: No aplica al servicio farmacéutico: el manejo del dolor y cuidado paliativo aplica a los servicios médicos. El SF garantiza la disponibilidad de opioides. | E27: No aplica
A28: TSPP | B28: 12. El prestador de servicios de salud cuenta con la siguiente información documentada:
A29: TSPP | B29: 12.1. Detección, prevención y disminución del riesgo de accidentes e incidentes de carácter radiológico, en los servicios donde aplique. | C29: NA | D29: No aplica al servicio farmacéutico: la farmacia no maneja fuentes radiológicas. | E29: No aplica
A30: TSPP | B30: 12.2. Aseo, limpieza y desinfección de áreas y superficies. | C30: NC | D30: Se requieren el protocolo aplicado al SF y los registros de limpieza y desinfección de áreas y estanterías. Se verifica en campo. | E30: No evidenciado
A31: TSPP | B31: 12.3. Procedimiento de reanimación cerebro cardio pulmonar, en los servicios donde se realice. | C31: NA | D31: No aplica al servicio farmacéutico: en la farmacia no se realiza reanimación. El SF abastece los carros de paro. | E31: No aplica
A32: TSPP | B32: 12.4. Acciones para prevenir las flebitis infecciosas, químicas y mecánicas en los servicios donde se realicen procedimientos de venopunción. | C32: NA | D32: No aplica al servicio farmacéutico: en la farmacia no se hace venopunción. | E32: No aplica
A33: TSPP | B33: 12.5. Aspectos de bioseguridad acordes con las condiciones y características del servicio. | C33: NC | D33: Se requiere el manual de bioseguridad aplicable al SF, incluidos EPP y manejo de medicamentos peligrosos si se manipulan. No se evidencia. | E33: No evidenciado
A34: TSPP | B34: 12.6. Descontaminación por derrames de sangre u otros fluidos corporales. | C34: NA | D34: No aplica al servicio farmacéutico: en la farmacia no se manejan fluidos corporales. El kit de derrames de medicamentos se evalúa en la hoja 11.1.4, criterio 10. | E34: No aplica
A35: TSPP | B35: 12.7. Manejo de gases medicinales que incluya como mínimo la atención de emergencias y sistema de alarma, cuando se utilicen. | C35: NC | D35: Respuesta condicional. Debe definirse si el SF gestiona el oxígeno y los demás gases medicinales (son medicamentos). Si los gestiona, se requiere el procedimiento de manejo, almacenamiento de cilindros y atención de emergencias; si no, sustentar el NA indicando el área responsable. | E35: No evidenciado
A36: TSPP | B36: 13. El prestador de servicios de salud que realice el proceso de esterilización cuenta con la siguiente información documentada:
A37: TSPP | B37: 13.1. Buenas prácticas de esterilización de acuerdo con los procedimientos y técnicas que se utilicen, que describa como mínimo los siguientes aspectos:
A38: TSPP | B38: 13.1.1 Recibo de productos contaminados y entrega de material estéril. | C38: NA | D38: No aplica al servicio farmacéutico: en la farmacia no se realiza el proceso de esterilización. | E38: No aplica
A39: TSPP | B39: 13.1.2. Transporte | C39: NA | D39: No aplica al servicio farmacéutico: en la farmacia no se realiza el proceso de esterilización. | E39: No aplica
A40: TSPP | B40: 13.1.3. Lavado, secado y lubricación. | C40: NA | D40: No aplica al servicio farmacéutico: en la farmacia no se realiza el proceso de esterilización. | E40: No aplica
A41: TSPP | B41: 13.1.4. Empaque. | C41: NA | D41: No aplica al servicio farmacéutico: en la farmacia no se realiza el proceso de esterilización. | E41: No aplica
A42: TSPP | B42: 13.1.5. Etiquetado. | C42: NA | D42: No aplica al servicio farmacéutico: en la farmacia no se realiza el proceso de esterilización. | E42: No aplica
A43: TSPP | B43: 13.1.6. Esterilización. | C43: NA | D43: No aplica al servicio farmacéutico: en la farmacia no se realiza el proceso de esterilización. | E43: No aplica
A44: TSPP | B44: 13.1.7. Almacenamiento. | C44: NA | D44: No aplica al servicio farmacéutico: en la farmacia no se realiza el proceso de esterilización. | E44: No aplica
A45: TSPP | B45: 13.1.8. Verificación de la integridad del material estéril | C45: NA | D45: No aplica al servicio farmacéutico: en la farmacia no se realiza el proceso de esterilización. | E45: No aplica
A46: TSPP | B46: 13.1.9. Control de calidad que incluya el análisis de los reportes de dicho control, para la toma de medidas preventivas y correctivas. | C46: NA | D46: No aplica al servicio farmacéutico: en la farmacia no se realiza el proceso de esterilización. | E46: No aplica
A47: TSPP | B47: 14. Cuando un prestador de servicios de salud contrate el proceso de esterilización con un tercero, cuenta con un contrato, convenio o acuerdo escrito entre las partes, el cual debe incluir como mínimo las características de calidad de los productos, la supervisión del estado de las instalaciones y la aplicación de los procedimientos del tercero para realizar el proceso. No obstante, el prestador de servicios de salud que requiere el proceso de esterilización es el responsable de garantizar la esterilidad y el desempeño del producto final. | C47: NA | D47: No aplica al servicio farmacéutico: la farmacia no contrata el proceso de esterilización. | E47: No aplica
A48: TSPP | B48: 15. Los prestadores de servicios de salud tienen definidos procedimientos que garanticen el cumplimiento del no reúso de dispositivos médicos cuando el fabricante así lo haya establecido. | C48: NC | D48: Criterio institucional en el que el SF participa mediante tecnovigilancia. No se aportan el procedimiento ni evidencia del control de dispositivos de un solo uso. | E48: No evidenciado
A49: TSPP | B49: 16. Hasta tanto el Ministerio de Salud y Protección Social regule la materia, el prestador de servicios de salud podrá reusar dispositivos médicos, siempre y cuando el fabricante de dichos dispositivos autorice su reúso. En tal caso, el prestador de servicios de salud cuenta con información documentada que defina:
A50: TSPP | B50: 16.1. Los procedimientos, siguiendo las recomendaciones del fabricante, para el reprocesamiento y control de calidad que demuestren la eficacia, desempeño y esterilidad del producto. | C50: NC | D50: El NA se basa en el supuesto de que no se reúsan dispositivos médicos. Debe confirmarse a nivel institucional; si hay reúso, el SF debe participar en el seguimiento mediante tecnovigilancia. | E50: No evidenciado
A51: TSPP | B51: 16.2. Acciones de seguimiento a través de los comités de infecciones, de seguridad del paciente y del programa de tecnovigilancia, que garanticen que el dispositivo no ha perdido la eficacia y desempeño para el cual fue diseñado, ni exponga al riesgo de infecciones o complicaciones al usuario. | C51: NC | D51: El NA se basa en el supuesto de que no se reúsan dispositivos médicos. Debe confirmarse a nivel institucional; si hay reúso, el SF debe participar en el seguimiento mediante tecnovigilancia. | E51: No evidenciado
A52: TSPP | B52: 16.3. Los profesionales independientes de salud realizarán el seguimiento a través del programa de tecnovigilancia. | C52: NC | D52: El NA se basa en el supuesto de que no se reúsan dispositivos médicos. Debe confirmarse a nivel institucional; si hay reúso, el SF debe participar en el seguimiento mediante tecnovigilancia. | E52: No evidenciado
A53: TSPP | B53: 17. Para la referencia de pacientes, el prestador de servicios de salud cuenta con la siguiente información documentada:
A54: TSPP | B54: 17.1. Estabilización del paciente antes del traslado. | C54: NA | D54: No aplica al servicio farmacéutico: la referencia de pacientes aplica a los servicios asistenciales. | E54: No aplica
A55: TSPP | B55: 17.2. Medidas para el traslado. | C55: NA | D55: No aplica al servicio farmacéutico: la referencia de pacientes aplica a los servicios asistenciales. | E55: No aplica
A56: TSPP | B56: 17.3. Lista de chequeo de los documentos necesarios para el traslado que incluya:
A57: TSPP | B57: 17.3.1. Diligenciamiento del formato de referencia de pacientes. | C57: NA | D57: No aplica al servicio farmacéutico: la referencia de pacientes aplica a los servicios asistenciales. | E57: No aplica
A58: TSPP | B58: 17.3.2. Resultados de apoyos diagnósticos realizados al paciente. | C58: NA | D58: No aplica al servicio farmacéutico: la referencia de pacientes aplica a los servicios asistenciales. | E58: No aplica
A59: TSPP | B59: 17.3.3. Resumen de historia clínica. | C59: NA | D59: No aplica al servicio farmacéutico: la referencia de pacientes aplica a los servicios asistenciales. | E59: No aplica
A60: TSPP | B60: 17.3.4. Mecanismos tecnológicos que le permitan realizar el proceso (software, correo, entre otros). | C60: NA | D60: No aplica al servicio farmacéutico: la referencia de pacientes aplica a los servicios asistenciales. | E60: No aplica
A61: TSPP | B61: 17.3.5. Talento humano que debe responsabilizarse de cada una de las etapas del proceso. | C61: NA | D61: No aplica al servicio farmacéutico: la referencia de pacientes aplica a los servicios asistenciales. | E61: No aplica
A62: TSPP | B62: 17.3.6. La referencia de pacientes que se detecten como víctimas de violencia sexual debe hacerse a un servicio de urgencias. | C62: NA | D62: No aplica al servicio farmacéutico: la referencia de pacientes aplica a los servicios asistenciales. | E62: No aplica
A63: TSPP | B63: 18. Cuando se realicen procedimientos bajo sedación fuera de salas cirugía, el prestador de servicios de salud cuenta con información documentada para:
A64: TSPP | B64: 18.1. Realizar la sedación | C64: NA | D64: No aplica al servicio farmacéutico: en la farmacia no se realiza sedación. | E64: No aplica
A65: TSPP | B65: 18.2. Definición de la atención por médico especialista en anestesiología cuando se identifiquen riesgos para el paciente relacionados con la sedación | C65: NA | D65: No aplica al servicio farmacéutico: en la farmacia no se realiza sedación. | E65: No aplica
A66: TSPP | B66: 18.3. Manejo de emergencias. | C66: NA | D66: No aplica al servicio farmacéutico: en la farmacia no se realiza sedación. | E66: No aplica
A67: TSPP | B67: 18.4. Seguimiento al riesgo, que incluya fichas técnicas de indicadores de complicaciones terapéuticas y medicamentosas, relacionadas con la sedación, medición, seguimiento y planes de mejoramiento. | C67: NA | D67: No aplica al servicio farmacéutico: en la farmacia no se realiza sedación. | E67: No aplica
A68: TSPP | B68: 18.5. Lista de chequeo, consignada en la historia clínica del paciente, que incluya la verificación de:
A69: TSPP | B69: 18.5.1. Evaluación de la vía aérea. | C69: NA | D69: No aplica al servicio farmacéutico: en la farmacia no se realiza sedación. | E69: No aplica
A70: TSPP | B70: 18.5.2. Determinación del tiempo de ayuno. | C70: NA | D70: No aplica al servicio farmacéutico: en la farmacia no se realiza sedación. | E70: No aplica
A71: TSPP | B71: 18.5.3. Registro de monitoreo del nivel de conciencia, la saturación de oxígeno, frecuencia cardíaca, tensión arterial y frecuencia respiratoria. | C71: NA | D71: No aplica al servicio farmacéutico: en la farmacia no se realiza sedación. | E71: No aplica
A72: TSPP | B72: 18.5.4. Registro de las variables hemodinámicas y respiratorias, a intervalos regulares | C72: NA | D72: No aplica al servicio farmacéutico: en la farmacia no se realiza sedación. | E72: No aplica
A73: TSPP | B73: 18.6. Observación bajo la supervisión del profesional que realiza la sedación. | C73: NA | D73: No aplica al servicio farmacéutico: en la farmacia no se realiza sedación. | E73: No aplica
A74: TSPP | B74: 18.7. Todos estos registros se deben realizar antes, durante la intervención y hasta el momento del egreso del paciente. | C74: NA | D74: No aplica al servicio farmacéutico: en la farmacia no se realiza sedación. | E74: No aplica
A75: TSPP | B75: 18.8. Recomendaciones de egreso suministradas al acompañante o acudiente. | C75: NA | D75: No aplica al servicio farmacéutico: en la farmacia no se realiza sedación. | E75: No aplica
A76: TSPP | B76: 19. Si el prestador de servicios de salud no tiene habilitado el servicio de gestión pre transfusional, pero realiza procedimientos de transfusión sanguínea en alguno de sus servicios de salud habilitados, cuenta con la siguiente información documentada:
A77: TSPP | B77: 19.1. Transporte, conservación, embalaje y remisión de muestras al banco de sangre para la realización de pruebas pre transfusionales. | C77: NA | D77: No aplica al servicio farmacéutico: la transfusión sanguínea aplica a los servicios asistenciales. | E77: No aplica
A78: TSPP | B78: 19.2. Manejo, investigación y análisis de las reacciones adversas a las transfusiones sanguíneas y procesos de hemovigilancia. | C78: NA | D78: No aplica al servicio farmacéutico: la transfusión sanguínea aplica a los servicios asistenciales. | E78: No aplica
A79: TSPP | B79: 19.3. Guía de práctica clínica para el uso de componentes sanguíneos. | C79: NA | D79: No aplica al servicio farmacéutico: la transfusión sanguínea aplica a los servicios asistenciales. | E79: No aplica
A80: TSPP | B80: 20. La Institución Prestadora de Servicios de Salud que cuenten con servicios de salud de los grupos de consulta externa, internación o el servicio de urgencias, cuenta con:
A81: TSPP | B81: 20.1. Documento del proceso institucional que orienta la atención en salud de las víctimas de violencias sexuales. | C81: NA | D81: No aplica al servicio farmacéutico: el proceso de atención a víctimas de violencia sexual es institucional (urgencias). El SF debe garantizar la disponibilidad del kit de profilaxis y anticoncepción de emergencia. | E81: No aplica
A82: TSPP | B82: 20.2. Documento que dé cuenta la conformación del equipo institucional para la atención integral en salud para las víctimas de violencias sexuales | C82: NA | D82: No aplica al servicio farmacéutico: el equipo institucional para víctimas de violencia sexual se evalúa a nivel institucional. | E82: No aplica
A83: TSPP | B83: 21. El Profesional Independiente de Salud y las Entidades con Objeto Social Diferente que oferten y presten servicios de salud de los grupos de consulta externa y los prestadores de servicios de salud de Transporte Especial de Pacientes cuentan con documento del proceso que orienta la atención en salud de las víctimas de violencias sexuales. | C83: NA | D83: No aplica al servicio farmacéutico: aplica a profesionales independientes y entidades con objeto social diferente. | E83: No aplica
A84: TSPP | B84: 22. En los servicios de transporte asistencial, atención prehospitalaria y urgencias, se cuenta con documento del proceso que orienta la atención en salud a victimas de ataques con agentes químicos. | C84: NA | D84: No aplica al servicio farmacéutico: aplica a transporte asistencial, APH y urgencias. | E84: No aplica
A85: TSPP | B85: 23. Los prestadores de servicios de salud cuentan con información documentada de las condiciones de almacenamiento, conservación, control de fechas de vencimiento, uso y custodia de los medicamentos, dispositivos médicos e insumos contenidos en los kits de derrames de medicamentos, ataque con agentes químicos y de violencias sexuales, según su contenido. | C85: NC | D85: Criterio clave del SF. No se aportan los procedimientos ni evidencia de su aplicación en farmacia, stocks de servicios y carros de paro. Se requieren el documento y la verificación en campo de condiciones, vencimientos y custodia. | E85: No evidenciado
A86: TSPP | B86: 24. Las Instituciones Prestadoras de Servicios de Salud con servicios de hospitalización, hospitalización de paciente crónico con y sin ventilador, cuidado intensivo neonatal, pediátrico y adulto, urgencias y del grupo quirúrgico, en la modalidad intramural, cuentan con la siguiente Información documentada:
A87: TSPP | B87: 24.1. Manejo de la enfermedad cerebro vascular. | C87: NA | D87: No aplica al servicio farmacéutico: los protocolos de ECV, TCE y donantes aplican a los servicios médicos. | E87: No aplica
A88: TSPP | B88: 24.2. Manejo del Trauma Craneoencefálico. | C88: NA | D88: No aplica al servicio farmacéutico: los protocolos de ECV, TCE y donantes aplican a los servicios médicos. | E88: No aplica
A89: TSPP | B89: 24.3. Detección de donantes de componentes anatómicos | C89: NA | D89: No aplica al servicio farmacéutico: los protocolos de ECV, TCE y donantes aplican a los servicios médicos. | E89: No aplica
A90: TSPP | B90: 24.4. Mantenimiento del donante de componentes anatómicos | C90: NA | D90: No aplica al servicio farmacéutico: los protocolos de ECV, TCE y donantes aplican a los servicios médicos. | E90: No aplica
A91: TSPP | B91: 25. Las Instituciones Prestadoras de Servicios de Salud, con servicios de cuidado intensivo pediátrico y adulto que cuenten con servicios quirúrgicos de neurocirugía de alta complejidad, cuentan con información documentada del procedimiento para el diagnóstico de muerte encefálica y muerte en asistolia. | C91: NA | D91: No aplica al servicio farmacéutico: aplica a IPS con UCI y neurocirugía. | E91: No aplica
A92: TSPP | B92: 26. Los servicios de salud que realicen pruebas de interés en salud pública deben inscribirse en el Registro de Laboratorios- RELAB. | C92: NA | D92: No aplica al servicio farmacéutico: la farmacia no realiza pruebas de interés en salud pública (RELAB). | E92: No aplica
A93: TSPP | B93: 27. Cuando el prestador de servicios de salud realice "pruebas en el punto de atención del paciente - (Point of Care Testing - POCT)" en un servicio habilitado cuenta con:
A94: TSPP | B94: 27.1. Información documentada sobre la toma, procesamiento, control de calidad y entrega de resultados. | C94: NA | D94: No aplica al servicio farmacéutico: la farmacia no realiza pruebas POCT. | E94: No aplica
A95: TSPP | B95: 27.2. Controles de calidad realizados por un servicio de laboratorio clínico que puede ser propio o contratado para tal fin. cuando aplique, de acuerdo a las especificaciones del fabricante. | C95: NA | D95: No aplica al servicio farmacéutico: la farmacia no realiza pruebas POCT. | E95: No aplica
A96: TSPP | B96: 27.3. Análisis de los reportes del control de calidad y toma de medidas preventivas y correctivas. | C96: NA | D96: No aplica al servicio farmacéutico: la farmacia no realiza pruebas POCT. | E96: No aplica
A97: TSPP | B97: Adicional a los criterios enunciados que le aplique, para las siguientes modalidades el prestador de servicios de salud cuenta con la siguiente información documentada:
A98: TSPP | B98: Modalidad extramural jornadas en salud y unidad móvil
A99: TSPP | B99: 28. Orientación a los usuarios sobre las condiciones, requisitos y restricciones de acceso, permanencia y salida del vehículo, en condiciones de rutina o en condiciones de emergencia. a cargo del conductor del vehículo y el talento humano en salud. | C99: NA | D99: No aplica: el servicio farmacéutico no presta modalidad extramural (unidad móvil, jornada de salud ni domiciliaria). | E99: No aplica
A100: TSPP | B100: 29. Mecanismos que garanticen comunicación para el seguimiento de los pacientes que lo requieran. | C100: NA | D100: No aplica: el servicio farmacéutico no presta modalidad extramural (unidad móvil, jornada de salud ni domiciliaria). | E100: No aplica
...

Sheet 11.1.6.HCR
B1: VOLVER A TABLA DE CONTENIDO
B2: Estandar de Historia Clínica y Registros
B3: Modalidades intramural, extramural: unidad movil, domicialiria, jornada de salud y telemedicina prestador remisor - prestador de referencia.
A4: Estandar | B4: Criterios | C4: Estado | D4: Comentarios | E4: Concepto preauditoría (QF)
A5: TSHCR | B5: 1. Toda atención de primera vez a un usuario debe incluir el proceso de apertura de historia clínica. Todos los pacientes atendidos cuentan con historia clínica. | C5: NA | D5: No aplica al servicio farmacéutico: la apertura de historia clínica la hacen los servicios asistenciales. El SF consulta la HC y la orden médica para validar y dispensar. | E5: No aplica
A6: TSHCR | B6: 2. El prestador de servicios de salud cuenta con procedimientos para utilizar una historia única y para el registro de entrada y salida de historias del archivo físico. Ello implica que el prestador de servicios de salud cuente con un mecanismo para unificar la información de cada paciente y su disponibilidad para el equipo de salud. | C6: NA | D6: No aplica al servicio farmacéutico: el procedimiento de historia única y archivo es institucional. | E6: No aplica
A7: TSHCR | B7: 3. Los medios electrónicos para la gestión de la historia clínica garantizan la confidencialidad y seguridad, así como el carácter permanente de registrar en ésta y en otros registros asistenciales, sin que se puedan modificar los datos una vez se guarden los registros. | C7: NC | D7: No se identifica el software ni se aportan pruebas de perfiles de acceso, trazabilidad de cambios y copias de seguridad. Requiere demostración del sistema en campo. | E7: No evidenciado
A8: TSHCR | B8: 4. Las historias clínicas cuentan con los componentes y los contenidos mínimos definidos en la normatividad que regula la materia | C8: NA | D8: No aplica al servicio farmacéutico: los componentes mínimos de la HC los diligencian los servicios asistenciales (Res. 1995/1999). El SF registra en el perfil farmacoterapéutico. | E8: No aplica
A9: TSHCR | B9: 5. La historia clínica y los registros asistenciales se diligencian en forma clara, legible, sin tachones, enmendaduras, intercalaciones, sin dejar espacios en blanco y sin utilizar siglas. | C9: NC | D9: No se aportan registros del SF que permitan verificar su calidad. Se requiere revisar una muestra de registros de recepción, temperatura, dispensación y del libro de control especial. | E9: No evidenciado
A10: TSHCR | B10: 6. Cada anotación lleva la fecha y hora en la que se realiza, con el nombre completo y firma del autor de la misma. | C10: NC | D10: No se aporta evidencia. Debe verificarse en una muestra de registros del SF la presencia de fecha, hora, nombre y firma. | E10: No evidenciado
A11: TSHCR | B11: 7. El diligenciamiento de los registros de atención de la historia clínica se realiza simultánea o inmediatamente después de la atención en salud. | C11: NC | D11: Solo verificable en campo (p. ej. registros de temperatura diligenciados el mismo día, sin llenado retroactivo). No se aporta evidencia. | E11: No evidenciado
A12: TSHCR | B12: 8. La historia clínica y demás registros son conservados en archivo único garantizando la custodia y confidencialidad de los documentos o registros protegidos legalmente por reserva. | C12: NC | D12: No se aportan la tabla de retención documental ni el sitio de archivo de los registros del SF. Las fórmulas de control especial tienen tiempos de conservación definidos por la normatividad; debe verificarse su custodia. | E12: No evidenciado
A13: TSHCR | B13: 9. El prestador de servicios de salud cuenta con un procedimiento de consentimiento informado que incluye mecanismos para verificar su aplicación, para que el paciente o su responsable, aprueben o no documentalmente, el procedimiento e intervención en salud a que va a ser sometido, previa información de los beneficios, riesgos, alternativas e implicaciones del acto asistencial | C13: NA | D13: No aplica al servicio farmacéutico: el consentimiento informado aplica a los procedimientos asistenciales. | E13: No aplica
A14: TSHCR | B14: 10. Cuando el prestador de servicios de salud utilice mecanismos electrónicos, ópticos o similares para generar, recibir, almacenar, o disponer datos de la historia clínica y para conservarlos, debe avalar que el mecanismo utilizado cumple con características de: autenticidad, fiabilidad, integridad y disponibilidad del documento, de acuerdo con lo establecido en la normatividad vigente expedida por el Archivo General de la Nación, la Superintendencia de Industria y Comercio y el Ministerio de Tecnologías de información y Comunicaciones, para lo cual, el prestador presentará un documento firmado por un ingeniero de sistemas con tarjeta profesional vigente, certificando que el mecanismo usado por el prestador cumple con la normatividad mencionada | C14: NC | D14: Se citan normas sin demostrar su cumplimiento. Debe precisarse si los registros del SF son electrónicos y, si lo son, soportar la firma electrónica, la seguridad y la conservación de la información. | E14: No evidenciado
A15: TSHCR | B15: Cuenta con los siguientes registros, cuando los prestadores de servicios de salud realicen el proceso de esterilización dentro del servicio y fuera de centrales de esterilización:
A16: TSHCR | B16: 11.1. Actividades documentadas y realizadas en el procedimiento de reúso de dispositivos médicos acorde con las recomendaciones del fabricante, incluyendo el número de reúsos por cada dispositivo esterilizado. | C16: NA | D16: No aplica al servicio farmacéutico: en la farmacia no se esteriliza. | E16: No aplica
A17: TSHCR | B17: 11.2. Registro de cargas. | C17: NA | D17: No aplica al servicio farmacéutico: en la farmacia no se esteriliza. | E17: No aplica
A18: TSHCR | B18: 11.3. Resultados del control de calidad. | C18: NA | D18: No aplica al servicio farmacéutico: en la farmacia no se esteriliza. | E18: No aplica
A19: TSHCR | B19: 11.4. Listas del contenido de los paquetes que se esterilizan. | C19: NA | D19: No aplica al servicio farmacéutico: en la farmacia no se esteriliza. | E19: No aplica
A20: TSHCR | B20: 11.5. Etiquetado de cada paquete que permita la trazabilidad de la esterilización. | C20: NA | D20: No aplica al servicio farmacéutico: en la farmacia no se esteriliza. | E20: No aplica
A21: TSHCR | B21: 12. Cuando se realicen procedimientos de transfusión de sangre o sus componentes, cuenta con los siguientes registros: | C21: NA | D21: No aplica al servicio farmacéutico: los registros de transfusión aplican a los servicios donde se transfunde. | E21: No aplica
A22: TSHCR | B22: 12.1. Información de los componentes sanguíneos. | C22: NA | D22: No aplica al servicio farmacéutico: los registros de transfusión aplican a los servicios donde se transfunde. | E22: No aplica
A23: TSHCR | B23: 12.2. Solicitud de los componentes sanguíneos. | C23: NA | D23: No aplica al servicio farmacéutico: los registros de transfusión aplican a los servicios donde se transfunde. | E23: No aplica
A24: TSHCR | B24: 12.3. Muestras tomadas para la realización de pruebas pre transfusionales. | C24: NA | D24: No aplica al servicio farmacéutico: los registros de transfusión aplican a los servicios donde se transfunde. | E24: No aplica
A25: TSHCR | B25: 12.4. Muestras remitidas al Banco de Sangre y resultado de las pruebas pre transfusionales con el nombre del Banco de Sangre que las realizó, cuando el prestador no cuente con el servicio de gestión pre transfusional. | C25: NA | D25: No aplica al servicio farmacéutico: los registros de transfusión aplican a los servicios donde se transfunde. | E25: No aplica
A26: TSHCR | B26: 12.5. Información post-transfusional. | C26: NA | D26: No aplica al servicio farmacéutico: los registros de transfusión aplican a los servicios donde se transfunde. | E26: No aplica
A27: TSHCR | B27: 12.6. Informe ante la secretaria departamental o distrital, o la entidad que tenga a cargo dichas competencias, sobre la estadistica mensual de componentes sanguineos trasfundidos. | C27: NA | D27: No aplica al servicio farmacéutico: los registros de transfusión aplican a los servicios donde se transfunde. | E27: No aplica
... A30: TSHCR | B30: 12.9. Transfusiones en la historia clínica del paciente, que incluya como mínimo la razón para la transfusión, el producto y volumen que fue transfundido y la hora de la transfusión. | C30: NA | D30: No aplica al servicio farmacéutico: los registros de transfusión aplican a los servicios donde se transfunde. | E30: No aplica
A31: TSHCR | B31: 13. Las instituciones prestadoras de servicios de salud con servicios en la modalidad intramural para hospitalización, hospitalización paciente crónico con y sin ventilador, cuidados intensivos neonatales, pediatricos y adultos, urgencias y servicios del grupo quirurgico, cuentan con:
A32: TSHCR | B32: 13.1. Registro de donantes detectados | C32: NA | D32: No aplica al servicio farmacéutico: el registro de donantes aplica a los servicios asistenciales. | E32: No aplica
B33: 13.2. Registro de consulta del documento de voluntad anticipada de todos los pacientes facellidos | C33: NA | D33: No aplica al servicio farmacéutico: el registro de donantes aplica a los servicios asistenciales. | E33: No aplica
A34: TSHCR | B34: 13.3. Registros en la historia clínica de la información sobre el proceso de donación efectuado por los profesionales de salud inscritos ante el Instituto Nacional de Salud | C34: NA | D34: No aplica al servicio farmacéutico: el registro de donantes aplica a los servicios asistenciales. | E34: No aplica
A35: TSHCR | B35: Modalidad Extramural
A36: TSHCR | B36: 14. La historia clínica utilizada en la modalidad extramural es custodiada por el prestador de servicios de salud que oferta y presta el servicio de salud en la modalidad extramural y cuenta con los siguientes registros: | C36: NA | D36: No aplica: el servicio farmacéutico no presta modalidad extramural (unidad móvil, jornada de salud ni domiciliaria). | E36: No aplica
A37: TSHCR | B37: Modalidad Extramural Domiciliaria
A38: TSHCR | B38: 14.1. Valoración de ingreso con el respectivo plan de tratamiento | C38: NA | D38: No aplica: el servicio farmacéutico no presta modalidad extramural (unidad móvil, jornada de salud ni domiciliaria). | E38: No aplica
A39: TSHCR | B39: 14.2. Nombre de los pacientes atendidos | C39: NA | D39: No aplica: el servicio farmacéutico no presta modalidad extramural (unidad móvil, jornada de salud ni domiciliaria). | E39: No aplica
A40: TSHCR | B40: 14.3. Registros de referencia y contrarreferencia, cuando se requieran | C40: NA | D40: No aplica: el servicio farmacéutico no presta modalidad extramural (unidad móvil, jornada de salud ni domiciliaria). | E40: No aplica
A41: TSHCR | B41: 14.4. Cuidados por parte del personal de salud | C41: NA | D41: No aplica: el servicio farmacéutico no presta modalidad extramural (unidad móvil, jornada de salud ni domiciliaria). | E41: No aplica
A42: TSHCR | B42: 14.5. Cuidados encargados a la familia cuando aplique | C42: NA | D42: No aplica: el servicio farmacéutico no presta modalidad extramural (unidad móvil, jornada de salud ni domiciliaria). | E42: No aplica
A43: TSHCR | B43: Modalidad Extramural Jornada de Salud y Unidad Móvil
A44: TSHCR | B44: 14.6. Registro de rutas, horarios y frecuencias de la prestación de los servicios ofertados | C44: NA | D44: No aplica: el servicio farmacéutico no presta modalidad extramural (unidad móvil, jornada de salud ni domiciliaria). | E44: No aplica
A45: TSHCR | B45: 14.7. Nombre de los pacientes atendidos. | C45: NA | D45: No aplica: el servicio farmacéutico no presta modalidad extramural (unidad móvil, jornada de salud ni domiciliaria). | E45: No aplica
A46: TSHCR | B46: 14.8. Nombre de los pacientes trasladados | C46: NA | D46: No aplica: el servicio farmacéutico no presta modalidad extramural (unidad móvil, jornada de salud ni domiciliaria). | E46: No aplica
A47: TSHCR | B47: 14.9. Fecha y hora de ingreso al servicio | C47: NA | D47: No aplica: el servicio farmacéutico no presta modalidad extramural (unidad móvil, jornada de salud ni domiciliaria). | E47: No aplica
A48: TSHCR | B48: 14.10. Cuidados por parte del personal de salud | C48: NA | D48: No aplica: el servicio farmacéutico no presta modalidad extramural (unidad móvil, jornada de salud ni domiciliaria). | E48: No aplica
A49: TSHCR | B49: 14.11. Cuidados encargados a la familia cuando aplique | C49: NA | D49: No aplica: el servicio farmacéutico no presta modalidad extramural (unidad móvil, jornada de salud ni domiciliaria). | E49: No aplica
A50: TSHCR | B50: 14.12. Registros de las fechas de llegada y de salida, cuando aplique | C50: NA | D50: No aplica: el servicio farmacéutico no presta modalidad extramural (unidad móvil, jornada de salud ni domiciliaria). | E50: No aplica
A51: TSHCR | B51: 14.13. Registros de las actividades realizadas. | C51: NA | D51: No aplica: el servicio farmacéutico no presta modalidad extramural (unidad móvil, jornada de salud ni domiciliaria). | E51: No aplica
A52: TSHCR | B52: Modalidad Telemedicina - Prestador remisor - Prestador de referencia Cuenta con:
A53: TSHCR | B53: 15. Documento firmado por un ingeniero de sistemas con tarjeta profesional vigente, que certifique: | C53: NA | D53: No aplica: el servicio farmacéutico no está habilitado en modalidad telemedicina (verificar en el REPS). | E53: No aplica
A54: TSHCR | B54: 15.1. Los mecanismos que garanticen la custodia, seguridad confidencialidad y conservación integral, durante la transmisión y almacenamiento de la información contenida en la historia clínica y demás registros asistenciales y la reproducibilidad de la información de acuerdo con la legislación vigente | C54: NA | D54: No aplica: el servicio farmacéutico no está habilitado en modalidad telemedicina (verificar en el REPS). | E54: No aplica
A55: TSHCR | B55: 15.2. Los mecanismos de compresión utilizados por el prestador garantizan que la información recuperada corresponda al dato, imagen o señal original (compresión sin pérdidas). | C55: NA | D55: No aplica: el servicio farmacéutico no está habilitado en modalidad telemedicina (verificar en el REPS). | E55: No aplica
A56: TSHCR | B56: 15.3. El método utilizado para el uso de la firma electrónica o digital | C56: NA | D56: No aplica: el servicio farmacéutico no está habilitado en modalidad telemedicina (verificar en el REPS). | E56: No aplica
A57: TSHCR | B57: 15.4. La encriptación de la información para su transmisión y mecanismos de acceso a la misma de acuerdo con lo definido por el prestador de servicios de salud. | C57: NA | D57: No aplica: el servicio farmacéutico no está habilitado en modalidad telemedicina (verificar en el REPS). | E57: No aplica
A58: TSHCR | B58: 15.5. Los sistemas de seguridad y control de acceso a la aplicación, según tipo de usuario cuando se utilizan sistemas de información compartidos o de acceso remoto | C58: NA | D58: No aplica: el servicio farmacéutico no está habilitado en modalidad telemedicina (verificar en el REPS). | E58: No aplica
A59: TSHCR | B59: 16. Plan de contingencia en caso de fallas del sistema activo o pérdida de datos | C59: NA | D59: No aplica: el servicio farmacéutico no está habilitado en modalidad telemedicina (verificar en el REPS). | E59: No aplica
A60: TSHCR | B60: 17. Todos los eventos y transacciones que se realicen con ocasión de la prestación de servicios en la modalidad de telemedicina son documentados y almacenados, y son parte integral de la historia clínica | C60: NA | D60: No aplica: el servicio farmacéutico no está habilitado en modalidad telemedicina (verificar en el REPS). | E60: No aplica
A61: TSHCR | B61: 18. Registro de las atenciones realizadas en la modalidad de telemedicina | C61: NA | D61: No aplica: el servicio farmacéutico no está habilitado en modalidad telemedicina (verificar en el REPS). | E61: No aplica
B64: CUMPLE | C64: =COUNTIF($C$5:$C$61,"C")
B65: NO CUMPLE | C65: =COUNTIF($C$5:$C$61,"NC")
B66: NO APLICA | C66: =COUNTIF($C$5:$C$61,"NA")

Sheet 11.1.7INT
B1: VOLVER A TABLA DE CONTENIDO
B2: Estandar de Interdependencia
A3: Estandar | B3: Criterios | C3: Estado | D3: Comentarios | E3: Concepto preauditoría (QF)
A4: TSINT | B4: 1. Cuando el servicio interdependiente sea contratado, debe mediar un contrato o un acuerdo escrito entre las dos partes, en el que se establezca que el servicio interdependiente apoya el servicio principal, estableciendo como mínimo:
A5: TSINT | B5: 1.1 Calidad en la entrega de los productos | C5: NA | D5: No aplica al servicio farmacéutico: según la Res. 3100/2019, el servicio farmacéutico no tiene servicios interdependientes (criterios 21 y 22 de la hoja 11.3.2: 'No aplica'). La clínica no realiza ni contrata mezclas. | E5: No aplica
A6: TSINT | B6: 1.2. Procedimientos documentados de atención en cada servicio independiente | C6: NA | D6: No aplica al servicio farmacéutico: según la Res. 3100/2019, el servicio farmacéutico no tiene servicios interdependientes (criterios 21 y 22 de la hoja 11.3.2: 'No aplica'). La clínica no realiza ni contrata mezclas. | E6: No aplica
A7: TSINT | B7: 1.3 Tiempos de entrega de los productos | C7: NA | D7: No aplica al servicio farmacéutico: según la Res. 3100/2019, el servicio farmacéutico no tiene servicios interdependientes (criterios 21 y 22 de la hoja 11.3.2: 'No aplica'). La clínica no realiza ni contrata mezclas. | E7: No aplica
A8: TSINT | B8: 1.4 Supervisión al contratista que garantice la seguridad del resultado del producto contratado. | C8: NA | D8: No aplica al servicio farmacéutico: según la Res. 3100/2019, el servicio farmacéutico no tiene servicios interdependientes (criterios 21 y 22 de la hoja 11.3.2: 'No aplica'). La clínica no realiza ni contrata mezclas. | E8: No aplica
A9: TSINT | B9: 2. Cuando fuera de salas de cirugía, se realicen procedimientos bajo sedación y monitorización electroencelfalografica con video y radio; el prestador de servicios de salud tendrá disponibilidad del servicio de transporte asistencial | C9: NA | D9: No aplica al servicio farmacéutico: en la farmacia no se realiza sedación ni monitorización electroencefalográfica. | E9: No aplica
B12: CUMPLE | C12: =COUNTIF($C$5:$C$9,"C")
B13: NO CUMPLE | C13: =COUNTIF($C$5:$C$9,"NC")
B14: NO APLICA | C14: =COUNTIF($C$5:$C$9,"NA")

Sheet 11.2.1.S_CE_G
B1: VOLVER A TABLA DE CONTENIDO
B2: Grupo Consulta Externa
B3: Servicio de Consulta Externa General
A4: Estandar | B4: Criterios | C4: Estado | D4: Comentarios
A5: CEG_TH | B5: Complejidad baja
A6: CEG_TH | B6: Modalidad intramural, extramural unidad móvil, jornada de salud y domiciliaria
A7: CEG_TH | B7: 1. Cumple con los criterios que le sean aplicables de todos los servicios y adicionalmente. | C7: C
A8: CEG_TH | B8: 2. Cuenta con el profesional de la salud de acuerdo con el servicio a ofertar. | C8: NC
A9: CEG_TH | B9: 3. Cuando se oferte la estrategia para el majo de la Enfermedad Respiratoria Aguda (ERA), el servicio tiene disponibilidad de:
A10: CEG_TH | B10: 3.1. Profesional de la medicina. | C10: NA
A11: CEG_TH | B11: 3.2. Profesional de la enfermería o terapia respiratoria o fisioterapia.
A12: CEG_TH | B12: Modalidad telemedicina
A13: CEG_TH | B13: Categoría interactiva y no interactiva-prestador de referencia
A14: CEG_TH | B14: 4. Cumple con los criterios que le sean aplicables de todos los servicios y adicionalmente, cuenta con:
A15: CEG_TH | B15: 4.1. Profesional de la salud de acuerdo con el servicio a ofertar.
A16: CEG_TH | B16: Categoria telexperticia- prestador de remisor
A17: CEG_TH | B17: 5. Cumple con los criterios que le sean aplicables de todos los servicios y adicionalmente:
A18: CEG_TH | B18: 5.1. Cuando se realice telexperticia entre profesionales de la salud cuenta con el profesional de la salud de acuerdo con el servicio a ofertar.
A19: CEG_TH | B19: 5.2. Cuando realice telexperticia entre personal de salud no profesional y un profesional de la salud, el prestador remisor cuenta con técnico, tecnólogo o auxiliar que atiende presencialmente al usuario.
A20: CEG_TH | B20: Categoria telexperticia-prestador de referencia
A21: CEG_TH | B21: 6. Cumple con los criterios que le sean aplicables de todos los servicios y adicionalmente cuenta con profesional de la salud que atiende a distancia, de acuerdo con el servicio a ofertar.
A22: CEG_TH | B22: Categoría telemonitoreo-prestador de referencia
... A158: CEG_INT | B158: 44. No aplica
B161: CUMPLE | C161: =COUNTIF($C$5:$C$158,"C")
B162: NO CUMPLE | C162: =COUNTIF($C$5:$C$158,"NC")
B163: NO APLICA | C163: =COUNTIF($C$5:$C$158,"NA")

Sheet 11.2.2.S_CE_E
B1: VOLVER A TABLA DE CONTENIDO
B2: Grupo Consulta Externa
B3: Servicio de Consulta Externa Especializada | C3: Servicio xxx
A4: Estandar | B4: Criterios | C4: Estado | D4: Comentarios
A5: CEE_TH | B5: Complejidad mediana
A6: CEE_TH | B6: Modalidades intramural, extramural unidad móvil, jornada de salud y domiciliaria
A7: CEE_TH | B7: 1. Cumple con los criterios definidos para el servicio de consulta externa general y adicionalmente cuenta con: | C7: C
A8: CEE_TH | B8: 1.1. Profesional de la salud con titulo de especialista, según los programas académicos autorizados por el Ministerio de Educación Nacional. | C8: NC
A9: CEE_TH | B9: 1.2. Para medicina alternativa y terapias alternativas y complementarias, cuenta con profesional de la salud con título de especialista en el ámbito de su disciplina, para lo cual deberá acreditar la respectiva certificación académica de esa norma de competencia, expedida por una institución de educación superior legalmente reconocida por el Estado y de acuerdo con lo documentado por el prestador de servicios de salud en el estándar de procesos prioritarios. | C9: NA
A10: CEE_TH | B10: Modalidad telemedicina
A11: CEE_TH | B11: Categoría interactiva y no interactiva-prestador de referencia
A12: CEE_TH | B12: 2. Cumple con los criterios que le sean aplicables de todos los servicios y adicionalmente, cuenta con:
A13: CEE_TH | B13: Profesional de la salud con título de especialista de acuerdo con el servicio a o ofertar
A14: CEE_TH | B14: Categoría telexperticia -prestador remisor
A15: CEE_TH | B15: 3. Cumple con los criterios que le sean aplicables de todos los servicios y adicionalmente:
A16: CEE_TH | B16: 3.1. Cuando se realice telexperticia entre profesionales de la salud cuenta con el profesional de salud con título de especialista de acuerdo con el servicio a ofertar.
A17: CEE_TH | B17: 3.2. Cuando realice telexperticia entre personal de salud no profesional y un profesional de la salud con título de especialista, el prestador remisor cuenta con técnico, tecnólogo o auxiliar que atiende presencialmente al usuario.
A18: CEE_TH | B18: Categoría telexperticia-prestador de referencia
A19: CEE_TH | B19: 4. Cumple con los criterios que le sean aplicables de todos los servicios y adicionalmente cuenta con profesional de la salud con título de especailista que atiende a distancia, de acuedo con el servicio a ofertar.
A20: CEE_TH | B20: Categoría telemonitoreo-prestador referencia
A21: CEE_TH | B21: 5. Cumple con los criterios que le sean aplicables de todos los servicios y adicionalmente cuenta con el personal de salud profesional con título de especialista que se requiera para realizar el telemonitoreo de acuerdo con lo documentado por el prestador de servicios de salud en el estándar de procesos prioritarios.
... A91: CEE_ INT | B91: 30. No aplica
B94: CUMPLE | C94: =COUNTIF($C$5:$C$91,"C")
B95: NO CUMPLE | C95: =COUNTIF($C$5:$C$91,"NC")
B96: NO APLICA | C96: =COUNTIF($C$5:$C$91,"NA")

Sheet 11.2.3.S_CE_V
B1: VOLVER A TABLA DE CONTENIDO
B2: Grupo Consulta Externa
B3: Servicio de Vacunación
A4: Estandar | B4: Criterios | C4: Estado | D4: Comentarios
A5: CEV_TH | B5: Complejidad baja
A6: CEV_TH | B6: Modalidades intramural, extramural unidad móvil, jornada de salud y domiciliaria
A7: CEV_TH | B7: 1. Cumple con los criterios que le sean aplicables de todos los servicios y adicionalmente, cuenta con: | C7: C
A8: CEV_TH | B8: 1.1 Profesional de la medicina o profesional de la enfermeria. | C8: NC
A9: CEV_TH | B9: 2. Si se requiere personal adicional para:
A10: CEV_TH | B10: 2.1 La administración de la vacuna cuenta con auxiliar de enfermerla o auxiliar de salud pública bajo la supervisión del profesional de la medicina o profesional de la enfermería. | C10: NA
A11: CEV_TH | B11: 2.2. El manejo de la cadena de frio puede disponer de auxiliar de enfermeria o auxiliar en salud pública o gestor comunitario en salud (en zonas de dispersión geográfica) o regentes de farmacia o qulmico farmaceutico con experiencia en cadena de frio.
A12: CEV_INF | B12: Complejidad baja
A13: CEV_INF | B13: Modalidad intramural
A14: CEV_INF | B14: 3. Cumple con los criterios que le sean aplicables de todos los servicios y adicionalmente cuenta con:
A15: CEV_INF | B15: Para los servicios en modalidad intramural de prestadores de servicios de salud que separen el servicio de vacunación en dos ambientes cuenta con:
A16: CEV_INF | B16: 4. Consultorio o ambiente que, de acuerdo con la oferta, cumple con los siguientes requisitos:
A17: CEV_INF | B17: 4.1 Consultorio para administración de medicamentos biologicos que cuenta con:
A18: CEV_INF | B18: 4.1.1. Área para entrevista.
A19: CEV_INF | B19: 4.1.2. Área para el alistamiento y administración de medicamentos biológicos.
A20: CEV_INF | B20: 4.1.3. Lavamanos
A21: CEV_INF | B21: 4.2. Ambiente para almacenamiento y alistamiento de dispositivos y termos que cuenta con:
A22: CEV_INF | B22: 4.2.1. Área para el alistamiento de termos o cajas témicas.
... A81: CEV_INT | B81: 12. No aplica
B84: CUMPLE | C84: =COUNTIF($C$5:$C$81,"C")
B85: NO CUMPLE | C85: =COUNTIF($C$5:$C$81,"NC")
B86: NO APLICA | C86: =COUNTIF($C$5:$C$81,"NA")

Sheet 11.2.4.S_CE_SST
B1: VOLVER A TABLA DE CONTENIDO
B2: Grupo Consulta Externa
B3: Servicio de Seguridad y Salud en el Trabajo
A4: Estandar | B4: Criterios | C4: Estado | D4: Comentarios
A5: CESST_TH | B5: Complejidad mediana
A6: CESST_TH | B6: Modalidades intramural, extramural unidad móvil y jornada de salud
A7: CESST_TH | B7: 1. Cumple con los criterios que le sean aplicables de todos los servicios y adicionalmente cuenta con: | C7: C
A8: CESST_TH | B8: 1.1. Profesional de la medicina especialista en medicina del trabajo o medicina laboral o seguridad y salud en el trabajo con licencia vigente de seguridad y salud en el trabajo expedida por autoridad competente. | C8: NC
A9: CESST_TH | B9: 1.2. Cuando se realicen pruebas complementarlas de tamización (audiometria, visiometria, espirometrla según aplique), disponibilidad de profesionales de la salud de conformidad con lo documentado en el estándar de procesos prioritarios. | C9: NA
A10: CESST_TH | B10: Modalidad telemedicina-prestador remisor
A11: CESST_TH | B11: 2. Cumple con los criterios que le sean aplicables de todos los servicios y adicionalmente:
A12: CESST_TH | B12: 2.1. Cuando se realice telexperticia entre profesionales de la salud cuenta con el profesional de la salud.
A13: CESST_TH | B13: Modalidad telemedicina-prestador de referencia
A14: CESST_TH | B14: 3. Cumple con los criterios que le sean aplicables de todos los servicios y adicionalmente cuenta con:
A15: CESST_TH | B15: Profesional en salud según la oferta definida por el prestador de servicios de salud en el estándar de procesos prioritarios.
A16: CESST_INF | B16: Complejidad mediana
A17: CESST_INF | B17: Modalidades intramural y extramural unidad móvil, jornada de salud y telemedicina-prestador remisor
A18: CESST_INF | B18: 4. Cumple con los criterios definidos del servicio de consulta externa para consultorio donde se realiza examen físico.
A19: CESST_INF | B19: Modalidad telemedicina -prestador de referencia
A20: CESST_INF | B20: 5. Cumple con los criterios que le sean aplicables de todos los servicios.
A21: CESST_DOT | B21: Complejidad mediana
... A53: CESST_INT | B53: 14. No aplica
B56: CUMPLE | C56: =COUNTIF($C$5:$C$53,"C")
B57: NO CUMPLE | C57: =COUNTIF($C$5:$C$53,"NC")
B58: NO APLICA | C58: =COUNTIF($C$5:$C$53,"NA")

Sheet 11.3.1.S_TR
B1: VOLVER A TABLA DE CONTENIDO
B2: Grupo apoyo diagnóstico y complementación tereapeutica
B3: Servicio de Terapias
A4: Estandar | B4: Criterios | C4: Estado | D4: Comentarios
A5: TR_TH | B5: Modalidad intramural y extramural unidad móvil, jornada de salud y domiciliaria
A6: TR_TH | B6: 1. Cumple con los criterios definidos para todos los servicios y adicionalmente cuenta con: | C6: C
A7: TR_TH | B7: 1.1. Profesionales de la salud con título según los programas académicos autorizados por el Ministerio de Educación Nacional en el ámbito de la rehabilitación, según oferta. | C7: NC
A8: TR_TH | B8: 1.2. Si oferta evaluación y tratamiento desde el enfoque de integración neurosensorial, cuenta con constancia de asistencia en las acciones de formación continua para la realización de los procedimientos según la oferta. | C8: NA
A9: TR_TH | B9: Modalidad telemedicina Categoría interactiva y no interactiva - prestador de referencia
A10: TR_TH | B10: 2. Cumple con los criterios que le sean aplicables de todos los servicios y adicionalmente, cuenta con:
A11: TR_TH | B11: 2.1 Profesional de la salud de acuerdo con el servicio a ofertar.
A12: TR_TH | B12: Categoría telexperticia - prestador remisor
A13: TR_TH | B13: 3. Cumple con los criterios que le sean aplicables de todos los servicios y adicionalmente
A14: TR_TH | B14: 3.1. Cuando se realice telexperticia entre profesionales de la salud cuenta con el profesional de la salud de acuerdo con el servicio a ofertar
A15: TR_TH | B15: Categoría telexperticia - prestador de referencia
A16: TR_TH | B16: 4. Cumple con los criterios que le sean aplicablesde todos los servicios y adicionalmente cuenta con profesional de la salud que atiende a distancia, de acuerdo con el servicio a ofertar.
A17: TR_TH | B17: Categoría telemonitoreo - prestador de referencia
A18: TR_TH | B18: 5. Cumple con los criterios que le sean aplicables de todos los servicios y adicionalmente cuenta con el personal de la salud profesional que se requiere para realizar el telemonitoreo de acuerdo con lo documentado por el prestador de servicios de salud en el estándar de procesos prioritarios.
A19: TR_INF | B19: 6. Cumple con los criterios que le sean aplicables de todos los servicios, y adicionalmente
A20: TR_INF | B20: 7. De acuerdo con el tipo de terapia ofertada, el servicio cuenta con:
... A77: TER_INT | B77: 30. No aplica.
B80: CUMPLE | C80: =COUNTIF($C$5:$C$77,"C")
B81: NO CUMPLE | C81: =COUNTIF($C$5:$C$77,"NC")
B82: NO APLICA | C82: =COUNTIF($C$5:$C$77,"NA")

Sheet  11.3.2.SF
B1: VOLVER A TABLA DE CONTENIDO
B2: Grupo apoyo diagnóstico y complementación tereapeutica
B3: Servicio Farmacéutico
A4: Estandar | B4: Criterios | C4: Estado | D4: Comentarios | E4: Concepto preauditoría (QF)
A5: SF_TH | B5: Modalidades intramural y extramural domiciliaria
A6: SF_TH | B6: 1. Cumple con los criterios definidos para todos los servicios y adicionalmente: | C6: NC | D6: Depende del cumplimiento de los estándares 11.1.1 a 11.1.7, que en esta preauditoría queda como no evidenciado. No puede darse por cumplido hasta subsanar esos criterios. | E6: No evidenciado
A7: SF_TH | B7: Cumple con lo definido en el Decreto 2200 de 2005 compilado en el Decreto 780 de 2016 (Art 2.5.3.10.9) y la Resolución 1403 de 2007 (Manual de condiciones esenciales y procedimientos del servicio farmacéutico Título I Capitulo II Numeral 3.2 y Capítulo III Numeral 1.2), o las normas que los modifiquen, adicionen o sustituyan. | C7: NC | D7: Criterio de talento humano específico del SF. No se aportan hojas de vida, títulos, tarjeta profesional del QF director técnico, certificados de regentes y auxiliares, inducción ni capacitación. Además, la complejidad (mediana/alta) es un supuesto que debe confirmarse en REPS, porque define el perfil exigido. | E7: No evidenciado
A8: SF_TH | B8: Modalidad telemedicina Categoría interactiva y no interactiva – prestador de referencia Categoría telexperticia – prestador remisor – prestador de referencia
A9: SF_TH | B9: 2. Cumple con los criterios que le sean aplicables de todos los servicios y adicionalmente, cuenta con lo definido con el numeral 1 del servicio farmacéutico. | C9: NA | D9: No aplica: se asume que el servicio farmacéutico no está habilitado en modalidad telemedicina (verificar en el REPS). | E9: No aplica
A10: SF_TH | B10: 3. El talento humano brinda en esta modalidad lo relacionado con la atención farmacéutica a los pacientes que lo requieran, a través de telemedicina – categorías interactiva y no interactiva, telexperticia sincrónico y asincrónico. | C10: NA | D10: No aplica: se asume que el servicio farmacéutico no está habilitado en modalidad telemedicina (verificar en el REPS). | E10: No aplica
A11: SF_TH | B11: El apoyo a distancia del profesional Químico Farmacéutico no reemplaza el contar con el talento humano definido en el servicio | C11: NA | D11: No aplica: se asume que el servicio farmacéutico no está habilitado en modalidad telemedicina (verificar en el REPS). | E11: No aplica
A12: SF_INF | B12: Complejidad baja
A13: SF_INF | B13: Modalidades intramural, extramural domiciliaria, telemedicina categoría telexperticia – prestador remisor
A14: SF_INF | B14: 4. Cumple con los criterios que le sean aplicables a todos los servicios | C14: NC | D14: Depende del cumplimiento de la hoja 11.1.2 (infraestructura), que en esta preauditoría queda como no evidenciado. No puede darse por cumplido hasta subsanar esos criterios. | E14: No evidenciado
A15: SF_INF | B15: 5. Cuenta con:
A16: SF_INF | B16: 5.1. Ambiente o área administrativa. | C16: NC | D16: No se evidencia el área administrativa del SF. Requiere verificación en campo y plano del servicio. | E16: No evidenciado
A17: SF_INF | B17: 5.2. Ambiente o área de recepción de medicamentos y dispositivos médicos. | C17: NC | D17: No se evidencia que el área de recepción esté delimitada y separada del almacenamiento. Requiere verificación en campo y señalización. | E17: No evidenciado
A18: SF_INF | B18: 5.3. Ambiente o área de dispensación de medicamentos y entrega de dispositivos médicos. | C18: NC | D18: No se evidencia el área de dispensación ni su separación de las demás áreas. Requiere verificación en campo. | E18: No evidenciado
A19: SF_INF | B19: 5.4. Ambiente o área de almacenamiento, que garantice las condiciones temperatura y humedad recomendadas por el fabricante. Incluye cadena de frio, cuando aplique. | C19: NC | D19: La respuesta fija rangos genéricos (15-30 °C; HR ≤65-70 %), pero el criterio exige las condiciones que recomienda el fabricante de cada producto. Deben verificarse los rangos por producto, los registros diarios y la cadena de frío en campo. No se aporta ningún registro. | E19: No evidenciado
A20: SF_INF | B20: 5.5. Ambiente o área independiente de medicamentos de control especial cuando aplique, que garantice las condiciones temperatura y humedad recomendadas por el fabricante. | C20: NC | D20: No se evidencian el área o mueble independiente con seguridad para medicamentos de control especial, el control de acceso ni el control ambiental del área. Requiere verificación en campo. | E20: No evidenciado
A21: SF_INF | B21: 5.6. Ambiente o área para almacenamiento de productos rechazados, devueltos y retirados. | C21: NC | D21: No se evidencia el área de productos rechazados, devueltos y retirados. Se verifica en campo: puede ser un área delimitada dentro del almacén, pero debe estar identificada, señalizada y separada. | E21: No evidenciado
A22: SF_INF | B22: 5.7. Ambiente o área para almacenamiento de productos destruidos o desnaturalizados por vencimiento o deterioro. | C22: NC | D22: No se evidencia el área de productos vencidos o deteriorados pendientes de destrucción. Se verifica en campo: puede ser un área delimitada dentro del almacén, pero debe estar identificada, señalizada y separada. | E22: No evidenciado
A23: SF_INF | B23: 5.8. Ambiente o área de cuarentena de medicamentos. | C23: NC | D23: No se evidencia el área de cuarentena. Se verifica en campo: puede ser un área delimitada dentro del almacén, pero debe estar identificada, señalizada y separada. | E23: No evidenciado
A24: SF_INF | B24: Modalidad telemedicina Categoría interactiva y no interactiva – prestador de referencia Categoría telexperticia – prestador de referencia
A25: SF_INF | B25: 6. Cumple con los criterios que le sean aplicables de todos los servicios. | C25: NA | D25: No aplica: se asume que el servicio farmacéutico no está habilitado en modalidad telemedicina (verificar en el REPS). | E25: No aplica
A26: SF_INF | B26: Complejidades mediana y alta Modalidades intramural, extramural domiciliaria, telemedicina categoría telexperticia – prestador remisor
A27: SF_INF | B27: 7. Cumple con los criterios definidos para el servicio farmacéutico de baja complejidad y adicionalmente cumple con lo definido en el Manual que adopta la Resolución 1403 de 2007, en el Título I Capítulo II numeral 1.2.2 y Título I Capítulo III numeral 1, o las normas que los modifiquen, adicionen o sustituyan. | C27: NC | D27: La complejidad es un supuesto no confirmado; debe verificarse en REPS. Si es mediana/alta, debe demostrarse lo exigido por la Res. 1403/2007, en particular el sistema de distribución de medicamentos en dosis unitaria y sus áreas. No se aporta evidencia. | E27: No evidenciado
A28: SF_INF | B28: Modalidad telemedicina Categoría interactiva y no interactiva – prestador de referencia Categoría telexperticia – prestador de referencia
A29: SF_INF | B29: 8. Cumple con los criterios que le sean aplicables de todos los servicios. | C29: NA | D29: No aplica: se asume que el servicio farmacéutico no está habilitado en modalidad telemedicina (verificar en el REPS). | E29: No aplica
A30: SF_DOT | B30: Complejidades baja, mediana y alta
A31: SF_DOT | B31: Modalidades intramural, extramural domiciliaria, telemedicina categoría telexperticia – prestador remisor
A32: SF_DOT | B32: 9. Cumple con los criterios que le sean aplicables de todos los servicios y adicionalmente cuenta con: | C32: NC | D32: Depende del cumplimiento de la hoja 11.1.3 (dotación), que en esta preauditoría queda como no evidenciado. No puede darse por cumplido hasta subsanar esos criterios. | E32: No evidenciado
A33: SF_DOT | B33: 9.1. La dotación y mobiliario exclusivos y necesarios para el cumplimiento de los objetivos de los procesos generales y especiales que brinda el servicio, de acuerdo con las recomendaciones dadas por los fabricantes. | C33: NC | D33: Se enumera la dotación esperada sin demostrar que exista. Requiere el inventario de dotación del SF y verificación en campo, incluidos la nevera exclusiva y el mueble de seguridad para control especial. | E33: No evidenciado
A34: SF_DOT | B34: 9.2. Instrumentos para medir la humedad relativa y la temperatura, en donde se almacenen medicamentos y dispositivos médicos. | C34: NC | D34: No se evidencian la ubicación de los termohigrómetros ni sus certificados de calibración. Sin calibración vigente, los registros ambientales no son confiables; verificar un instrumento por cada área de almacenamiento. | E34: No evidenciado
A35: SF_DOT | B35: Modalidad telemedicina Categoría interactiva y no interactiva – prestador de referencia Categoría telexperticia – prestador de referencia
A36: SF_DOT | B36: 10. Cumple con los criterios que le sean aplicables de todos los servicios. | C36: NA | D36: No aplica: se asume que el servicio farmacéutico no está habilitado en modalidad telemedicina (verificar en el REPS). | E36: No aplica
A37: SF_MED | B37: Complejidad baja
A38: SF_MED | B38: Modalidades intramural, extramural domiciliaria, telemedicina categoría telexperticia – prestador remisor
A39: SF_MED | B39: 11. Cumple con los criterios que le sean aplicables de todos los servicios. | C39: NC | D39: Depende del cumplimiento de la hoja 11.1.4 (medicamentos, dispositivos e insumos), que en esta preauditoría queda como no evidenciado. No puede darse por cumplido hasta subsanar esos criterios. | E39: No evidenciado
A40: SF_MED | B40: Modalidad telemedicina Categoría interactiva y no interactiva – prestador de referencia Categoría telexperticia – prestador de referencia
A41: SF_MED | B41: 12. Cumple con los criterios que le sean aplicables de todos los servicios. | C41: NA | D41: No aplica: se asume que el servicio farmacéutico no está habilitado en modalidad telemedicina (verificar en el REPS). | E41: No aplica
A42: SF_MED | B42: Complejidades mediana y alta
A43: SF_MED | B43: Modalidades intramural, extramural domiciliaria, telemedicina categoría telexperticia – prestador remisor
A44: SF_MED | B44: 13. Cumple con los criterios definidos para el servicio farmacéutico de baja complejidad y adicionalmente cuenta con: | C44: NC | D44: Depende del criterio de baja complejidad (criterio 11), que no está evidenciado. El requisito de central de mezclas no aplica (ver fila siguiente). | E44: No evidenciado
A45: SF_MED | B45: Certificación en buenas prácticas de elaboración vigente, expedida por el Invima para los procesos especiales que se realicen en la central de mezclas ya sea propia o contratada. | C45: NA | D45: No aplica: la institución informó que no realiza ni contrata mezclas. Debe confirmarse que no se prescriben preparaciones que exijan central de mezclas (p. ej. nutrición parenteral); si se prescriben, deben provenir de una central certificada en BPE y el criterio aplica. | E45: No aplica
A46: SF_MED | B46: Modalidad telemedicina Categoría interactiva y no interactiva – prestador de referencia Categoría telexperticia – prestador de referencia
A47: SF_MED | B47: 14. Cumple con los criterios que le sean aplicables de todos los servicios. | C47: NA | D47: No aplica: se asume que el servicio farmacéutico no está habilitado en modalidad telemedicina (verificar en el REPS). | E47: No aplica
A48: SF_PP | B48: Complejidad baja
A49: SF_PP | B49: Modalidades intramural, extramural domiciliaria, telemedicina categoría telexperticia - prestador remisor
A50: SF_PP | B50: 15. Cumple con los criterios que le sean aplicables de todos los servicios y adicionalmente cuenta con la siguiente información documentada: | C50: NC | D50: Depende del cumplimiento de la hoja 11.1.5 (procesos prioritarios), que en esta preauditoría queda como no evidenciado. No puede darse por cumplido hasta subsanar esos criterios. | E50: No evidenciado
A51: SF_PP | B51: 15.1. Procesos generales que realice, elaborado por el responsable del servicio. | C51: NC | D51: Se describe el contenido esperado sin aportar los procedimientos. Se requiere el listado maestro de documentos del SF firmado por el QF responsable, verificando que cubra todos los procesos generales que se realizan. | E51: No evidenciado
A52: SF_PP | B52: 15.2. Información visible al usuario que prohíba la asesoría farmacológica, por parte de personal diferente al profesional químico farmacéutico o al Profesional en Medicina tratante. | C52: NC | D52: Requiere verificar en campo el aviso visible en el área de dispensación. No se aporta evidencia de su existencia ni ubicación. | E52: No evidenciado
A53: SF_PP | B53: 15.3. Manejo de medicamentos de control especial cuando lo realice. | C53: NC | D53: Se requiere el procedimiento de manejo de medicamentos de control especial y, como soporte de implementación, la resolución vigente del Fondo Rotatorio de Estupefacientes, el libro oficial y los informes mensuales. | E53: No evidenciado
A54: SF_PP | B54: 15.4. Seguimiento a condiciones ambientales de temperatura y humedad. | C54: NC | D54: Se requieren el procedimiento, los formatos diligenciados y la evidencia de acciones ante desviaciones. No se aportan registros. | E54: No evidenciado
A55: SF_PP | B55: Modalidad telemedicina Categoría interactiva y no interactiva – prestador de referencia Categoría telexperticia – prestador de referencia
A56: SF_PP | B56: 16. Cumple con los criterios que le sean aplicables de todos los servicios. | C56: NA | D56: No aplica: se asume que el servicio farmacéutico no está habilitado en modalidad telemedicina (verificar en el REPS). | E56: No aplica
A57: SF_PP | B57: Complejidades mediana y alta
A58: SF_PP | B58: Modalidades intramural, extramural domiciliaria, telemedicina categoría telexperticia - prestador remisor
A59: SF_PP | B59: 17. Cumple con los criterios definidos para el servicio farmacéutico en baja complejidad y adicionalmente, cuenta con información documentada de cada uno de los procesos especiales que se realicen en el servicio. | C59: NC | D59: No se identifican los procesos especiales que realiza el SF (dosis unitaria, reempaque, reenvase, adecuación de dosis, atención farmacéutica). Debe definirse el alcance y aportar el procedimiento documentado de cada uno. | E59: No evidenciado
A60: SF_PP | B60: Modalidad telemedicina Categoría interactiva y no interactiva – prestador de referencia Categoría telexperticia – prestador de referencia
A61: SF_PP | B61: 18. Cumple con los criterios que le sean aplicables de todos los servicios. | C61: NA | D61: No aplica: se asume que el servicio farmacéutico no está habilitado en modalidad telemedicina (verificar en el REPS). | E61: No aplica
A62: SF_HC | B62: Complejidades baja, mediana y alta
A63: SF_HC | B63: Modalidades intramural, extramural domiciliaria, telemedicina categoría telexperticia - prestador remisor
A64: SF_HC | B64: 19. Cumple con los criterios que le sean aplicables de todos los servicios | C64: NC | D64: Depende del cumplimiento de la hoja 11.1.6 (historia clínica y registros), que en esta preauditoría queda como no evidenciado. No puede darse por cumplido hasta subsanar esos criterios. | E64: No evidenciado
A65: SF_HC | B65: Modalidad telemedicina Categoría interactiva y no interactiva – prestador de referencia Categoría telexperticia – prestador de referencia
A66: SF_HC | B66: 20. Cumple con los criterios que le sean aplicables de todos los servicios | C66: NA | D66: No aplica: se asume que el servicio farmacéutico no está habilitado en modalidad telemedicina (verificar en el REPS). | E66: No aplica
A67: SF_INT | B67: Complejidades baja, mediana y alta
A68: SF_INT | B68: Modalidades intramural, extramural domiciliaria, telemedicina categoría telexperticia - prestador remisor
A69: SF_INT | B69: 21. No aplica. | C69: NA | D69: El estándar de interdependencia no aplica al servicio farmacéutico (criterio 21: 'No aplica'). | E69: No aplica
A70: SF_INT | B70: Modalidad telemedicina Categoría interactiva y no interactiva – prestador de referencia Categoría telexperticia – prestador de referencia
A71: SF_INT | B71: 22. No aplica. | C71: NA | D71: El estándar de interdependencia no aplica al servicio farmacéutico (criterio 22: 'No aplica'). | E71: No aplica
B74: CUMPLE | C74: =COUNTIF($C$5:$C$71,"C")
B75: NO CUMPLE | C75: =COUNTIF($C$5:$C$71,"NC")
B76: NO APLICA | C76: =COUNTIF($C$5:$C$71,"NA")

Sheet 11.3.3.S_Rx_OD
B1: VOLVER A TABLA DE CONTENIDO
B2: Grupo apoyo diagnóstico y complementación tereapeutica
B3: Servicio de Radiologia Odontológica
A4: Estandar | B4: Criterios | C4: Estado | D4: Comentarios
A5: Rx_OD_TH | B5: Modalidades intramural y extramural unidad móvil
A6: Rx_OD_TH | B6: 1. Cumple con los criterios que le sean aplicables de todos los servicios y adicionalmente, cuenta con: | C6: C
A7: Rx_OD_TH | B7: Profesional de odontología o tecnólogo en radiología e imágenes diagnósticas, o técnico profesional o auxiliar de odontología o auxiliar en salud oral o auxiliar de higiene oral. | C7: NC
A8: Rx_OD_TH | B8: 2. Disponibilidad de profesional de la odontología, si la toma de radiografías la realiza un auxiliar de odontología o auxiliar en salud oral o auxiliar de higiene oral. | C8: NA
A9: Rx_OD_TH | B9: 3. La interpretación de las radiografías odontológicas es realizada por el profesional de la odontología.
A10: Rx_OD_TH | B10: Modalidad Telemedicina: Categoría telexperticia - prestador remisor
A11: Rx_OD_TH | B11: 4. Cumple con los criterios que le sean aplicables de todos los servicios y adicionalmente:
A12: Rx_OD_TH | B12: 4.1. Cuando se realice telexperticia entre profesionales de la salud cuenta con el profesional de la salud.
A13: Rx_OD_TH | B13: 4.2. Cuando realice telexperticia entre personal de salud no profesional y un profesional de la salud, el prestador remisor cuenta con técnico, tecnólogo o auxiliar que atiende presencialmente al usuario.
A14: Rx_OD_TH | B14: Categoría telexperticia - prestador de referencia
A15: Rx_OD_TH | B15: 5. Cumple con los criterios que le sean aplicables de todos los servicios y adicionalmente cuenta con profesional de la salud que atiende a distancia.
A16: RX_OD_INF | B16: Modalidades intramural, telemedicina - prestador remisor
A17: RX_OD_INF | B17: 6. Cumple con los criterios que le sean aplicables de todos los servicios y adicionalmente cuenta con:
A18: RX_OD_INF | B18: 6.1. Ambiente de radiología odontológica, si la tecnología lo requiere. Las dimensiones estarán determinadas según la ficha técnica del equipo.
A19: RX_OD_INF | B19: 6.2. Área de revelado o ambiente oscuro con extracción de gases e iluminación adecuada, con mesón de trabajo con poceta, si la tecnología lo requiere.
A20: RX_OD_INF | B20: 7. Disponibilidad de:
... A69: RX_OD_INT | B69: 21. No aplica.
B72: CUMPLE | C72: =COUNTIF($C$5:$C$69,"C")
B73: NO CUMPLE | C73: =COUNTIF($C$5:$C$69,"NC")
B74: NO APLICA | C74: =COUNTIF($C$5:$C$69,"NA")

Sheet 11.3.4.S_IDx
B1: VOLVER A TABLA DE CONTENIDO
B2: Grupo apoyo diagnóstico y complementación tereapeutica
B3: Servicio de imágenes diagnósticas
B4: Métodos diagnósticos con imágenes obtenidas mediante equipos generadores de radiaciones ionizantes
A5: Estandar | B5: Criterios | C5: Estado | D5: Comentarios
A6: IDX_TH | B6: Complejidad baja
A7: IDX_TH | B7: Modalidades intramural, extramural unidad móvil, telemedicina - prestador remisor
A8: IDX_TH | B8: 1. Cumple con los criterios definidos para todos los servicios y adicionalmente, | C8: C
A9: IDX_TH | B9: 2. Cuenta con:
A10: IDX_TH | B10: Técnico profesional o tecnólogo en imágenes diagnósticas, para la operación de equipos y adquisición de imágenes. | C10: NC
A11: IDX_TH | B11: 3. Disponibilidad de:
A12: IDX_TH | B12: Médico especializado en radiología e imágenes diagnósticas o aquellos médicos especialistas quienes en su pensum o formación académica hayan adquirido los conocimientos del manejo e interpretación del espectro electromagnético, del ultrasonido especialmente, así como de las radiaciones ionizantes para establecer el diagnóstico y/o el tratamiento de las enfermedades inherentes a sus especialidades, para lo cual deberán acreditar el respectivo certificado. La interpretación de las radiografías e imágenes diagnósticas y la supervisión del técnico profesional o tecnólogo en imágenes diagnósticas es realizada por dichos profesionales. | C12: NA
A13: IDX_TH | B13: Complejidad mediana
A14: IDX_TH | B14: Modalidades extramural unidad móvil, telemedicina - prestador remisor
A15: IDX_TH | B15: 4. Cumple con los criterios que le sean aplicables de todos los servicios y adicionalmente cuenta con:
A16: IDX_TH | B16: 4.1. Tecnólogo en radiología e imágenes diagnósticas para la operación de equipos y adquisición de imágenes, con supervisión por el profesional de la medicina especialista en radiología e imágenes diagnósticas.
A17: IDX_TH | B17: 4.2. Médico especializado en radiología e imágenes diagnósticas o aquellos médicos especialistas quienes en su pensum o formación académica hayan adquirido los conocimientos del manejo e interpretación del espectro electromagnético, del ultrasonido especialmente, así como de las radiaciones ionizantes para establecer el diagnóstico y/o el tratamiento de las enfermedades inherentes a sus especialidades. Para lo cual deberá acreditar el respectivo certificado. La interpretación de las radiografías e imágenes diagnósticas y la supervisión del técnico profesional o tecnólogo en imágenes diagnósticas es realizada por dichos profesionales.
A18: IDX_TH | B18: Complejidades mediana y alta
A19: IDX_TH | B19: Modalidades intramural, telemedicina - prestador remisor
A20: IDX_TH | B20: 5. Cumple con los criterios que le sean aplicables de todos los servicios y adicionalmente cuenta con:
A21: IDX_TH | B21: 5.1. Tecnólogo en radiología e imágenes diagnósticas para la operación de equipos y adquisición de imágenes, con supervisión por el profesional de la medicina especialista en radiología e imágenes diagnósticas.
A22: IDX_TH | B22: 5.2. Médico especializado en radiología e imágenes diagnósticas o aquellos médicos especialistas quienes en su pensum o formación académica hayan adquirido los conocimientos del manejo e interpretación del espectro electromagnético, del ultrasonido especialmente, así como de las radiaciones ionizantes para establecer el diagnóstico y/o el tratamiento de las enfermedades inherentes a sus especialidades, para lo cual deberán acreditar el respectivo certificado. La interpretación de las radiografías e imágenes diagnósticas y la supervisión del técnico profesional o tecnólogo en imágenes diagnósticas es realizada por dichos profesionales.
A23: IDX_TH | B23: Complejidad baja, mediana y alta
A24: IDX_TH | B24: Modalidad telemedicina - prestador de referencia
... A154: IDX_INT | B154: 41. No aplica.
B159: Servicio de imágenes diagnósticas
B160: Métodos diagnósticos con imágenes obtenidas mediante equipos generadores de radiaciones NO ionizantes
A161: Estandar | B161: Criterios | C161: Estado | D161: Comentarios
A162: IDX_TH | B162: Complejidad mediana
A163: IDX_TH | B163: Modalidades intramural, extramural jornada de salud, unidad móvil y domiciliaria, telemedicina - prestador remisor
A164: IDX_TH | B164: 1. Cumple con los criterios que le sean aplicables de todos los servicios y adicionalmente cuenta con:
A165: IDX_TH | B165: 1.1. Médico especializado en radiología e imágenes diagnósticas o aquellos médicos especialistas quienes en su pensum o formación académica hayan adquirido los conocimientos del manejo e interpretación del espectro electromagnético, del ultrasonido especialmente, así como de las radiaciones ionizantes para establecer el diagnóstico y/o el tratamiento de las enfermedades inherentes a sus especialidades. Para lo cual deberá acreditar el respectivo certificado.
A166: IDX_TH | B166: 1.2. Cuando se realicen procedimientos de resonancia magnética cuenta con Técnico profesional o tecnólogo en imágenes diagnósticas, para la operación de equipos y adquisición de imágenes.
A167: IDX_TH | B167: Modalidad telemedicina - prestador de referencia
A168: IDX_TH | B168: 2. Cumple con los criterios que le sean aplicables de todos los servicios.
A169: IDX_TH | B169: 3. La interpretación de las imágenes diagnósticas es realizada médico especializado en radiología e imágenes diagnósticas o aquellos médicos especialistas quienes en su pensum o formación académica hayan adquirido los conocimientos del manejo e interpretación del espectro electromagnético, del ultrasonido especialmente, así como de las radiaciones ionizantes para establecer el diagnóstico y/o el tratamiento de las enfermedades inherentes a sus especialidades. Para lo cual deberá acreditar el respectivo certificado.
A170: IDX_INF | B170: Complejidad mediana
A171: IDX_INF | B171: Modalidades intramural, extramural unidad móvil, telemedicina - prestador remisor
A172: IDX_INF | B172: 4. Cumple con los criterios que le sean aplicables de todos los servicios y adicionalmente, cuenta con:
A173: IDX_INF | B173: 4.1 Ambiente exclusivo para el equipo generador de radiación no ionizante. La dimensión de este ambiente debe ser acorde al tipo de equipo generador de radiación no ionizante, su ficha técnica y a los procedimientos que se realicen, debe permitir movilización del talento humano, pacientes, usuarios y equipos biomédicos.
... A215: IDX_INT | B215: 17. No aplica
B218: CUMPLE | C218: =COUNTIF($C$5:$C$215,"C")
B219: NO CUMPLE | C219: =COUNTIF($C$5:$C$215,"NC")
B220: NO APLICA | C220: =COUNTIF($C$5:$C$215,"NA")

Sheet  11.3.5.S_MNuc
B1: VOLVER A TABLA DE CONTENIDO
A2: Grupo | B2: Apoyo diagnóstico y complementación terapeútica
A3: Descripción | B3: Servicio Medicina Nuclear: Servicio en el que se realizan procedimientos diagnósticos o terapeúticos mediante fuentes no selladas de radicación constituidas por isótopos radiactivos, radiofármacos o radionúclidos de uso en humanos.
A4: Complejidad | B4: Alta
A5: Modalidad | B5: Intramural
B6: Telemedicina: Telexperticia sincrónico, prestador remisor y prestador de referencia, entre dos profesionales.
A7: Estandar | B7: Criterios | C7: Estado | D7: Comentarios
A8: TH | B8: Modalidades intramural, telemedicina - prestador remisor
A9: TH | B9: 1. Cumple con los criterios que le sean aplicables de todos los servicios y adicionalmente cuenta con:
A10: TH | B10: 1.1 Profesional de la enfermería, cuando en el servicio se administren terapias con radionúclidos con actividad mayor a 30 mCi, que cuenta con constancia de asistencia en las acciones de formación continua en protección radiológica, radiofarmacia y radiofármacos. | C10: C
A11: TH | B11: 1.2 Tecnólogo en medicina nuclear o tecnólogo en manejo de fuentes no selladas de uso diagnóstico y terapéutico o tecnólogo en imágenes diagnósticas, que cuenta con constancia de asistencia en las acciones de formación continua en protección radiológica, radiofarmacia y radiofármacos. | C11: NC
A12: TH | B12: 1.3 Oficial de protección radiológica para toda la institución. | C12: NA
A13: TH | B13: 2. Disponibilidad de:
A14: TH | B14: 2.1 Profesional de la medicina especialista en medicina nuclear, con permanencia durante los procedimientos definidos por el prestador de servicios de salud en el estándar de procesos prioritarios.
A15: TH | B15: 2.2 Profesional con título de postgrado en física médica con permanencia durante los procedimientos definidos por el prestador de servicios de salud en el estándar de procesos prioritarios.
A16: TH | B16: Modalidad telemedicina - prestador de referencia
A17: TH | B17: 3. Cumple con los criterios que le sean aplicables de todos los servicios.
A18: TH | B18: 4. El profesional de la medicina especialista en medicina nuclear, cuando esté en disponibilidad y no se requiera su permanencia, puede hacer uso de la categoría telexperticia sincrónica entre profesionales de la salud, de acuerdo con lo definido por el prestador de servicios de salud en el estándar de procesos prioritarios.
A19: Infraestructura | B19: Modalidades intramural, telemedicina - prestador remisor
A20: Infraestructura | B20: 5. Cumple con los criterios que le sean aplicables de todos los servicios y adicionalmente cuenta con:
A21: Infraestructura | B21: 5.1 Ducha de seguridad
A22: Infraestructura | B22: 6. Disponibilidad de:
A23: Infraestructura | B23: 6.1 Sala de espera.
A24: Infraestructura | B24: 6.2 Unidades sanitarias discriminadas por sexo.
... A99: Interdependencia | B99: 24. No aplica
B102: CUMPLE | C102: =COUNTIF($C$5:$C$99,"C")
B103: NO CUMPLE | C103: =COUNTIF($C$5:$C$99,"NC")
B104: NO APLICA | C104: =COUNTIF($C$5:$C$99,"NA")

Sheet 11.3.6.S_Radio
B1: VOLVER A TABLA DE CONTENIDO
A2: Grupo | B2: Apoyo diagnóstico y complementación tereapeutica
A3: Descripción | B3: Servicio Radioterapia: Servicio en el que se lleva a cabo tratamiento médico que hace uso de radiación ionizante con et fin de erradicar un volumen tumoral benigno o maligno y en patologías no tumorales.
A4: Complejidad | B4: Alta
A5: Modalidades | B5: Intramural
B6: Telemedicina: Telexperticia sincrónico, prestador remisor y prestador de referencia, entre dos profesionales.
A7: Estandar | B7: Criterios | C7: Estado | D7: Comentarios
A8: Talento Humano | B8: Modalidades intramural, telemedicina - prestador remisor
A9: Talento Humano | B9: 1. Cumple con los criterios que le sean aplicables de todos los servicios y adicionalmente cuenta con: | C9: C
A10: Talento Humano | B10: 1.1. Tecnólogo en radioterapia. | C10: NC
A11: Talento Humano | B11: 1.2. Profesional con título de postgrado en física médica. | C11: NA
A12: Talento Humano | B12: 1.3. Oficial de protección radiológica para toda la institución.
A13: Talento Humano | B13: 2. Disponibilidad de:
A14: Talento Humano | B14: Profesional de la medicina especialista en radioterapia u oncología radioterápica, con permanencia durante los procedimientos definidos por el prestador de servicios de salud en el estándar de procesos prioritarios.
A15: Talento Humano | B15: Modalidad telemedicina - prestador de referencia
A16: Talento Humano | B16: 3. Cumple con los criterios que le sean aplicables de todos los servicios.
A17: Talento Humano | B17: 4. El profesional de la medicina especialista en radioterapia u oncología radioterápica, cuando esté en disponibilidad y no se requiera su permanencia, puede hacer uso de la categor!a telexperticia sincrónica entre profesionales de la salud, de acuerdo con lo definido por el prestador de servicios de salud en e1 estándar de procesos prioritarios.
A18: Infraestructura | B18: Modalidades intramural, telemedicina - prestador remisor
A19: Infraestructura | B19: 5. Cumple con los criterios que le sean aplicables de todos los servicios y adicionalmente cuenta con:
A20: Infraestructura | B20: 5.1. Ambiente de moldeo con disponibilidad de área para mesón de trabajo con poceta, cuando la tecnologia utilizada la requiera.
A21: Infraestructura | B21: 5.2. Ambiente para delimitación, planeación y dosimetría clinica de tratamientos, con ambiente o área para el almacenamiento de equipos de dosimetría.
A22: Infraestructura | B22: 5.3. Ambiente de tratamiento de teleterapia con unidades de mega voltaje (acelerador lineal). La dimensión de este ambiente debe ser acorde al tipo de equipo, su ficha técnica y a los procedimientos que se realicen, debe permitir movilización del talento humano, pacientes, usuarios y equipos biomédicos.
A23: Infraestructura | B23: Cuenta con:
... A115: Interdependencias | B115: 17. No aplica
B118: CUMPLE | C118: =COUNTIF($C$5:$C$115,"C")
B119: NO CUMPLE | C119: =COUNTIF($C$5:$C$115,"NC")
B120: NO APLICA | C120: =COUNTIF($C$5:$C$115,"NA")

Sheet 11.3.7.S_Quimio
B1: VOLVER A TABLA DE CONTENIDO
A2: Grupo | B2: Apoyo diagnóstico y complementación tereapeutica
A3: Descripción | B3: Servicio Quimioterapia: Servicio de administración de medicamentos oncológicos.
A4: Complejidad | B4: Alta
A5: Modaliadades | B5: Intramural
B6: Telemedicina - prestador remisor
A7: Estandar | B7: Criterios | C7: Estado | D7: Comentarios
A8: Talento Humano | B8: Modalidades intramural, telemedicina - prestador remisor
A9: Talento Humano | B9: 1. Cumple con los criterios que le sean aplicables de todos los servicios y adicionalmente cuenta con: | C9: C
A10: Talento Humano | B10: 1.1. Profesional de la enfermerfa especialista en oncologfa o profesional de la enfermerla con constancia de asistencia en las acciones de formación continua en el cuidado integral del paciente adulto o pediátrico con quimioterapia, segün oferta. | C10: NC
A11: Talento Humano | B11: 1.2. Auxiliares de enfermerra con constancia de asistencia en las acciones de formación continua en el cuidado integral del paciente adulto o pediátrico con quimioterapia, según oferta. | C11: NA
A12: Talento Humano | B12: 1.3. Qufmico (a) Farmacéutico (a) con constancia de asistencia en las acciones de formación continua en el cuidado integral del paciente adulto o pediátrico con quimioterapia, según oferta.
A13: Talento Humano | B13: 2. Disponibilidad de:
A14: Talento Humano | B14: Profesional de la medicina especialista en oncologla o especialista en hemato-oncologla o especialista en hematotogla, según el tipo de cáncer a tratar.
A15: Talento Humano | B15: 3. Si se ofrecen servicios de oncologra pediátrica, el talento humano en salud cuenta con constancia de asistencia en las acciones de formación continua del cuidado del paciente pediátrico con quimioterapia o con patología onco-hematológica a excepción del Profesional de la medicina especialista en pediatría.
A16: Talento Humano | B16: Modalidad telemedicina - prestador de referencia
A17: Talento Humano | B17: 4. Cumple con ros criterios que le sean aplicables de todos los servicios.
A18: Talento Humano | B18: 5. El profesional de la medicina especialista en oncología o especialista en hemato-oncologia o especialista en hematología, según el tipo de cáncer a tratar, puede realizar la disponibilidad en la categoría tetexperticia sincrónica entre profesionales de la salud de acuerdo con lo definido por el prestador de servicios de salud en el estándar de procesos prioritarios.
A19: Infraestructura | B19: Modalidades intramural, telemedicina - prestador remisor
A20: Infraestructura | B20: 6. Cumple con los criterios que le sean aplicables de todos los servicios y adicionalmente cuenta con:
A21: Infraestructura | B21: 6.1. Sala de espera.
A22: Infraestructura | B22: 6.2. Unidades sanitarias discriminadas por sexo.
A23: Infraestructura | B23: 6.3. Ambiente de quimioterapia que cuenta con área para casilleros.
... A107: Interdependencias | B107: 20. No aplica
B110: CUMPLE | C110: =COUNTIF($C$5:$C$107,"C")
B111: NO CUMPLE | C111: =COUNTIF($C$5:$C$107,"NC")
B112: NO APLICA | C112: =COUNTIF($C$5:$C$107,"NA")

Sheet 11.3.8 S_Dx VASC
B1: VOLVER A TABLA DE CONTENIDO
C2: 1
B3: Grupo apoyo diagnóstico y complementación tereapeutica
B4: 11.3.2 Servicio de Diagnóstico Vascular | C4: Servicio X1
B5: Complejidad mediana
A6: Estandar | B6: Criterios | C6: Estado | D6: Comentarios
A7: DXVASC_TH | B7: Modalidades intramural, telemedicina, prestador remisor
A8: DXVASC_TH | B8: 1. Cumple con los criterios definidos para todos los servicios y adicionalmente cuenta con: | C8: C
A9: DXVASC_TH | B9: 1.1. Profesional de la medicina especialista en cardiología, o profesional de la medicina especialista en cirugía vascular, o profesional de la medicina especialista en medicina vascular o profesional de la medicina especialista en angiología clínica o profesional de la medicina especialista en radiología e imágenes diagnósticas. Este talento humano realiza procedimientos y su interpretación, en el ámbito de su competencia | C9: NC
A10: DXVASC_TH | B10: 1.2. Profesional de la enfermería que cuenta con constancia de asistencia en acciones de formación continua en soporte vital básico y para la realización del o los procedimientos ofertados. | C10: NA
A11: DXVASC_TH | B11: Modalidad de Telemedicina - prestador de referencia
A12: DXVASC_TH | B12: 2. Cumple con los criterios que le sean aplicables de todos los servicios.
A13: DXVASC_TH | B13: 3. El profesional de la medicina especialista en cardiología, o profesional de la medicina especialista en cirugía vascular, o profesional de la medicina especialista en medicina vascular o profesional de la medicina especialista en angiología clínica o profesional de la medicina especiallsta en radiología e imágenes diagnósticas puede hacer uso de la categoría telexperticia sincrónica o asincrónica entre profesionales de la salud de acuerdo con lo definido por el prestador de servicios de salud en el estándar de procesos prioritarios.
A14: DXVASC_INF | B14: Modalidades intramural, telemedicina - prestador remisor
A15: DXVASC_INF | B15: 4. Cumple con los criterios que le sean aplicables de todos los servicios y adicionalmente,
A16: DXVASC_INF | B16: 5. Cuenta con:
A17: DXVASC_INF | B17: 5.1. Lavamanos
A18: DXVASC_INF | B18: 5.2. Vestidor de pacientes con área para casilleros.
A19: DXVASC_INF | B19: 5.3. Sala de procedimientos.
A20: DXVASC_INF | B20: 6. Disponibilidad de:
A21: DXVASC_INF | B21: 6.1. Sala de espera.
A22: DXVASC_INF | B22: 6.2.Unidades sanitarias discriminadas por sexo.
... A53: DXVAC_INT | B53: 16. No aplica.
B56: CUMPLE | C56: =COUNTIF($C$5:$C$53,"C")
B57: NO CUMPLE | C57: =COUNTIF($C$5:$C$53,"NC")
B58: NO APLICA | C58: =COUNTIF($C$5:$C$53,"NA")

Sheet 11.3.9S_HI
B1: VOLVER A TABLA DE CONTENIDO
B2: Grupo apoyo diagnóstico y complementación tereapeutica
B3: 11.3.9Servicio de Hemodinamia e Intervencionismo
A4: Estandar | B4: Criterios | C4: Estado | D4: Comentarios
A5: HI_TH | B5: Complejidad alta
A6: HI_TH | B6: Modalidades intramural, tefemedicina - prestador remisor
A7: HI_TH | B7: 1.Cumple con los criterios que le sean aplicables de todos los servicios y adicionalmente cuenta con: | C7: C
A8: HI_TH | B8: 1.1. Profesional de la medicina especialista en cardiología intervencionista y hemodinámia o profesional de la medicina especialista en electrofisiología o profesional de la medicina especialista en cirugía vascular o profesional de la medicina especialista en radiología intervencionista. | C8: NC
A9: HI_TH | B9: 1.2. Profesional de la enfermería que cuenta con constancia de asistencia en las acciones de formación continua en la realización del procedimiento ofertado y en soporte vital avanzado. | C9: NA
A10: HI_TH | B10: 1.3. Tecnólogo en radiología e imágenes diagnósticas.
A11: HI_TH | B11: 2. Disponibilidad de profesional de la medicina especialista en anestesiología.
A12: HI_TH | B12: Modalidad telemedicina - prestador de referencia
A13: HI_TH | B13: 3. Cumple con los criterios que le sean aplicables de todos los servicios.
A14: HI_TH | B14: 4. El profesional de la medicina especialista en cardiología intervencionista y hemodinámia o profesional de la medicina especialista en electrofisiología o profesional de la medicina especialista en cirugía vascular o profesional de la medicina especialista en radiología intervencionista, puede hacer uso de la categoría telexperticia sincrónica o asincrónica entre profesionales de la salud de acuerdo con lo definido por el prestador de servicios de salud en el estándar de procesos prioritarios
A15: HI_INF | B15: Modalidades intramural, telemedicina - prestador remisor
A16: HI_INF | B16: 5. Cumple con los criterios que le sean aplicables de todos los servicios y adicionalmente cuenta con:
A17: HI_INF | B17: 5.1. Área para recepción y entrega de pacientes.
A18: HI_INF | B18: 5.2. Área para almacenamiento de material estéril.
A19: HI_INF | B19: 5.3. Vestidor de personal que funciona como filtro
A20: HI_INF | B20: 5.4. Vestidor de pacientes y área para casilleros.
A21: HI_INF | B21: 5.5. Unidad sanitaria.
... A116: HCA_INT | B116: 20. No aplica.
B119: CUMPLE | C119: =COUNTIF($C$5:$C116,"C")
B120: NO CUMPLE | C120: =COUNTIF($C$5:$C$116,"NC")
B121: NO APLICA | C121: =COUNTIF($C$5:$C$116,"NA")

Sheet 11.3.10 S_GPT
B1: VOLVER A TABLA DE CONTENIDO
B2: Grupo apoyo diagnóstico y complementación tereapeutica
B3: Servicio de Gestión Pre-Trasfusional
A4: Estandar | B4: Criterios | C4: Estado | D4: Comentarios
A5: GPT_TH | B5: 1. Cumple con los criterios que le sean aplicables de todos los servicios y adicionalmente, cuando el servicio de gestión pre- transfusional sea interdependiente de: | C5: C
A6: GPT_TH | B6: Servicios de salud de alta complejidad:
A7: GPT_TH | B7: 1.1 Cuenta con profesional de bacteriología. | C7: NC
A8: GPT_TH | B8: Servicios de salud de baja y mediana complejidad:
A9: GPT_TH | B9: 1.2. Disponibilidad de profesional de bacteriología. | C9: NA
A10: GPT_TH | B10: 2. El profesional de bacteriología cuenta con constancia de asistencia en las acciones de formación continua en el manejo de la gestión pre transfusional.
A11: GPT_INF | B11: 3. Cumple con los criterios que le sean aplicables de todos los servicios y adicionalmente.
A12: GPT_INF | B12: 4. Cuenta con:
A13: GPT_INF | B13: 4.1 Área para recepción, información y entrega de componentes sanguíneos.
A14: GPT_INF | B14: 4.2.1. Lavamanos.
A15: GPT_INF | B15: 4.2.2. Mesón de trabajo.
A16: GPT_INF | B16: 4.2.3. Poceta, cuando la requiera, según los procedimientos que documente en el estándar de procesos prioritarios.
A17: GPT_INF | B17: 4.2.4. Área para refrigeración y congelación.
A18: GPT_DOT | B18: 5. Cumple con los criterios que le sean aplicables de todos los servicios y adicionalmente cuenta con
A19: GPT_DOT | B19: 5.1. Nevera o depósito frío para el almacenamiento de sangre o sus componentes con sistema de control de temperatura entre 1ºC y 6ºC y alarma audible o sistema de monitoreo que alerte cambios próximos al limite en que la sangre o sus componentes puedan deteriorarse.
A20: GPT_DOT | B20: 5.2. Equipo para descongelar plasma cuando se requiera, con sistema de control de temperatura
A21: GPT_DOT | B21: 5.3. Congelador para la conservación de plasma o crioprecipitados, cuando se requiera, éste cuenta con sistema de control de temperatura por debajo de -18ºC y alarma audible o sistema de monitoreo que alerte cambios próximos al límite en que el componente almacenado pueda deteriorarse
... A47: GPT_INT | B47: 9. No aplica.
B50: CUMPLE | C50: =COUNTIF($C$4:$C$47,"C")
B51: NO CUMPLE | C51: =COUNTIF($C$4:$C$47,"NC")
B52: NO APLICA | C52: =COUNTIF($C$4:$C$47,"NA")

Sheet 11.3.11.S_TMLC
B1: VOLVER A TABLA DE CONTENIDO
B2: Grupo apoyo diagnóstico y complementación tereapeutica
B3: Servicio de Toma de Muestras de Laboratorio Clinico
A4: Estandar | B4: Criterios | C4: Estado | D4: Comentarios
A5: TMLC_TH | B5: Modalidades intramural, extramural unidad móvil, jornada de salud y domiciliaria
A6: TMLC_TH | B6: 1. Cumple con los criterios que le sean aplicables de todos los servicios y adicionalmente cuenta con: | C6: C
A7: TMLC_TH | B7: Profesional de bacteriología o auxiliar de laboratorio clínico o auxiliar de enfermería. | C7: NC
A8: TMLC_TH | B8: 2. Disponibilidad de:
A9: TMLC_TH | B9: Profesional de bacteriología quien realiza la supervisión cuando la toma de muestras es realizada por el auxiliar. | C9: NA
A10: TMLC_INF | B10: Modalidad intramural
A11: TMLC_INF | B11: Modalidad intramural
A12: TMLC_INF | B12: 3. Cumple con los criterios que le sean aplicables de todos los servicios y adicionalmente,
A13: TMLC_INF | B13: 4. Cuenta con:
A14: TMLC_INF | B14: 4.1. Área para recepción de muestras, información y entrega de resultados.
A15: TMLC_INF | B15: 4.2. Cubículo para la toma de muestras.
A16: TMLC_INF | B16: 4.3. Ambiente para la toma de muestras especiales cuando lo oferte, cuenta con unidad sanitaria y perchero (si el procedimiento lo indica).
A17: TMLC_INF | B17: 4.4. Lavamanos.
A18: TMLC_INF | B18: 4.5. Área de preparación, embalaje y remisión de las muestras que cuenta con:
A19: TMLC_INF | B19: 4.5.1. Mesón de trabajo, con poceta cuando ésta se requiera.
A20: TMLC_INF | B20: 5. Disponibilidad de:
A21: TMLC_INF | B21: 5.1. Sala de espera.
... A45: TM_INT | B45: Servicio de laboratorio clínico.
B48: CUMPLE | C48: =COUNTIF($C$4:$C$45,"C")
B49: NO CUMPLE | C49: =COUNTIF($C$4:$C$45,"NC")
B50: NO APLICA | C50: =COUNTIF($C$4:$C$45,"NA")

Sheet 11.3.12.S_LC
B1: VOLVER A TABLA DE CONTENIDO
B2: Grupo apoyo diagnóstico y complementación tereapeutica
B3: Servicio de Laboratorio Clinico
A4: Estandar | B4: Criterios | C4: Estado | D4: Comentarios
A5: LC_TH | B5: Modalidades intramural, extramural unidad móvil, jornada de salud y telemedicina - prestador remisor.
A6: LC_TH | B6: 1. Cumple con los criterios definidos para todos los servicios y adicionalmente, | C6: C
A7: LC_TH | B7: 1.1. Cuenta con:
A8: LC_TH | B8: 1.1.1. Bacteriólogo (a). | C8: NC
